Workbook

Sheet Baseline 2025
A4: 97% Jet-A1 & 3% SAF
AC5: Crew costs | AI5: Costs | AO5: Revenue
B6: Destination | C6: Aircraft | D6: Fuel type | E6: Frequency [per year] | F6: # retour | G6: # flights | H6: Lookup: Distance [km] | I6: Total distance travelled [km] | J6: Lookup: Flight Type | K6: Lookup: fuel consumption [l/100km] | L6: Conditional: Total fuel consumption [l] | M6: SAF LFEC CO2 per kg [kg/kg] | N6: Total CO2 emmission [kg] (tons) | O6: NOX per KG | P6: Total NOX emmision(Tons) | Q6: Sox per KG | R6: Total Sox emmission(Ton) | S6: Seats | T6: Passengers per year | U6: Available cargo (Tons) | V6: Flight time | W6: Fuel | X6: jet-A1 Fuel | Y6: Jet-A1 price | Z6: SAF fuel | AA6: SAF price | AB6: Ticket price | AC6: Pilot | AD6: Cabin crew | AE6: Freight rate (Euro/KG) | AF6: Crew costs | AG6: Airport & Navigation charges | AH6: Maintenance costs | AI6: Maintenance reserve | AJ6: Operational lease | AK6: catering and inflight services | AL6: Insurance and overhead | AM6: Total costs | AN6: Passenger revenu | AO6: Cargo revenu | AP6: Total revenue
B7: 1 ALC | C7: Fokker 100 | D7: SAF | E7: =7*52*2 -> 728 | F7: =E7/2 -> 364 | G7: =E7 -> 728 | H7: =_xlfn.XLOOKUP(B7,'[1]Baseline 2025'!$B:$B,'[1]Baseline 2025'!$C:$C) -> 1613 | I7: =E7*H7 -> 1174264 | J7: =_xlfn.XLOOKUP(B7,'[1]Baseline 2025'!$B:$B,'[1]Baseline 2025'!$E:$E) -> Short Haul | K7: =_xlfn.XLOOKUP(B7,'[1]Baseline 2025'!$B:$B,'[1]Baseline 2025'!$I:$I)/100 -> 43095.489 | L7: =K7*100 -> 4309548.9 | M7: 3.84 | N7: =(L7*M7)/1000 -> 16548.668 | O7: =12/1000 -> 0.012 | P7: =(O7*L7)/1000 -> 51.714587 | Q7: =1.2/1000 -> 0.0012 | R7: =Q7*L7/1000 -> 5.1714587 | S7: 100 | T7: =G7*S7*assumptions!$D$6 -> 61880 | U7: 10.9 | V7: 0.11111111 | W7: 5919.71 | X7: =W7*0.97 -> 5742.1187 | Y7: =X7*assumptions!$C$7 -> 7464.7543 | Z7: =W7*0.03 -> 177.5913 | AA7: =Z7*assumptions!$C$8 -> 319.66434 | AB7: 172 | AC7: 2 | AD7: 3 | AE7: 3.5 | AF7: 1201.5 | AG7: 6845 | AH7: 21360 | AI7: 5340 | AJ7: 1669 | AK7: 2550 | AL7: 3341 | AM7: =Y7+AF7+AG7+AH7+AI7+AJ7+AK7+AL7+AA7 -> 50090.919 | AN7: 14620 | AO7: 38150 | AP7: =AN7+AO7 -> 52770
B8: 2 ARN | C8: Fokker 100 | D8: SAF | E8: =7*52*2 -> 728 | F8: =E8/2 -> 364 | G8: =E8 -> 728 | H8: =_xlfn.XLOOKUP(B8,'[1]Baseline 2025'!$B:$B,'[1]Baseline 2025'!$C:$C) -> 1155 | I8: =E8*H8 -> 840840 | J8: =_xlfn.XLOOKUP(B8,'[1]Baseline 2025'!$B:$B,'[1]Baseline 2025'!$E:$E) -> Short Haul | K8: =_xlfn.XLOOKUP(B8,'[1]Baseline 2025'!$B:$B,'[1]Baseline 2025'!$I:$I)/100 -> 30858.828 | L8: =K8*100 -> 3085882.8 | M8: 3.84 | N8: =(L8*M8)/1000 -> 11849.79 | O8: =12/1000 -> 0.012 | P8: =(O8*L8)/1000 -> 37.030594 | Q8: =1.2/1000 -> 0.0012 | R8: =Q8*L8/1000 -> 3.7030594 | S8: 100 | T8: =G8*S8*assumptions!$D$6 -> 61880 | U8: 10.9 | V8: 0.083333333 | W8: 4238.85 | X8: =W8*0.97 -> 4111.6845 | Y8: =X8*assumptions!$C$7 -> 5345.1899 | Z8: =W8*0.03 -> 127.1655 | AA8: =Z8*assumptions!$C$8 -> 228.8979 | AB8: 99 | AC8: 2 | AD8: 3 | AE8: 3 | AF8: 900 | AG8: 6158 | AH8: 16000 | AI8: 4000 | AJ8: 1250 | AK8: 2550 | AL8: 2603 | AM8: =Y8+AF8+AG8+AH8+AI8+AJ8+AK8+AL8+AA8 -> 39035.088 | AN8: 8415 | AO8: 32700 | AP8: =AN8+AO8 -> 41115
B9: 3 BCN | C9: Fokker 100 | D9: SAF | E9: =7*52*2 -> 728 | F9: =E9/2 -> 364 | G9: =E9 -> 728 | H9: =_xlfn.XLOOKUP(B9,'[1]Baseline 2025'!$B:$B,'[1]Baseline 2025'!$C:$C) -> 1241 | I9: =E9*H9 -> 903448 | J9: =_xlfn.XLOOKUP(B9,'[1]Baseline 2025'!$B:$B,'[1]Baseline 2025'!$E:$E) -> Short Haul | K9: =_xlfn.XLOOKUP(B9,'[1]Baseline 2025'!$B:$B,'[1]Baseline 2025'!$I:$I)/100 -> 33156.542 | L9: =K9*100 -> 3315654.2 | M9: 3.84 | N9: =(L9*M9)/1000 -> 12732.112 | O9: =12/1000 -> 0.012 | P9: =(O9*L9)/1000 -> 39.78785 | Q9: =1.2/1000 -> 0.0012 | R9: =Q9*L9/1000 -> 3.978785 | S9: 100 | T9: =G9*S9*assumptions!$D$6 -> 61880 | U9: 10.9 | V9: 0.097222222 | W9: 4554.47 | X9: =W9*0.97 -> 4417.8359 | Y9: =X9*assumptions!$C$7 -> 5743.1867 | Z9: =W9*0.03 -> 136.6341 | AA9: =Z9*assumptions!$C$8 -> 245.94138 | AB9: 90 | AC9: 2 | AD9: 3 | AE9: 3.5 | AF9: 1048.5 | AG9: 6287 | AH9: 18640 | AI9: 4660 | AJ9: 1456 | AK9: 2550 | AL9: 2903 | AM9: =Y9+AF9+AG9+AH9+AI9+AJ9+AK9+AL9+AA9 -> 43533.628 | AN9: 7650 | AO9: 38150 | AP9: =AN9+AO9 -> 45800
B10: 4 BRU | C10: Fokker 100 | D10: SAF | E10: =14*52 -> 728 | F10: =E10/2 -> 364 | G10: =E10 -> 728 | H10: =_xlfn.XLOOKUP(B10,'[1]Baseline 2025'!$B:$B,'[1]Baseline 2025'!$C:$C) -> 158 | I10: =E10*H10 -> 115024 | J10: =_xlfn.XLOOKUP(B10,'[1]Baseline 2025'!$B:$B,'[1]Baseline 2025'!$E:$E) -> Short Haul | K10: =_xlfn.XLOOKUP(B10,'[1]Baseline 2025'!$B:$B,'[1]Baseline 2025'!$I:$I)/100 -> 8442.7616 | L10: =K10*100 -> 844276.16 | M10: 3.84 | N10: =(L10*M10)/1000 -> 3242.0205 | O10: =12/1000 -> 0.012 | P10: =(O10*L10)/1000 -> 10.131314 | Q10: =1.2/1000 -> 0.0012 | R10: =Q10*L10/1000 -> 1.0131314 | S10: 100 | T10: =G10*S10*assumptions!$D$6 -> 61880 | U10: 10.9 | V10: 0.027777778 | W10: 579.86 | X10: =W10*0.97 -> 562.4642 | Y10: =X10*assumptions!$C$7 -> 731.20346 | Z10: =W10*0.03 -> 17.3958 | AA10: =Z10*assumptions!$C$8 -> 31.31244 | AB10: 37.5 | AC10: 2 | AD10: 3 | AE10: 3.5 | AF10: 300.015 | AG10: 4662 | AH10: 5333.6 | AI10: 1333.4 | AJ10: 417 | AK10: 2550 | AL10: 1097 | AM10: =Y10+AF10+AG10+AH10+AI10+AJ10+AK10+AL10+AA10 -> 16455.531 | AN10: 3187.5 | AO10: 38150 | AP10: =AN10+AO10 -> 41337.5
B11: 5 BSL | C11: Fokker 100 | D11: SAF | E11: =7*52*2 -> 728 | F11: =E11/2 -> 364 | G11: =E11 -> 728 | H11: =_xlfn.XLOOKUP(B11,'[1]Baseline 2025'!$B:$B,'[1]Baseline 2025'!$C:$C) -> 561 | I11: =E11*H11 -> 408408 | J11: =_xlfn.XLOOKUP(B11,'[1]Baseline 2025'!$B:$B,'[1]Baseline 2025'!$E:$E) -> Short Haul | K11: =_xlfn.XLOOKUP(B11,'[1]Baseline 2025'!$B:$B,'[1]Baseline 2025'!$I:$I)/100 -> 14988.574 | L11: =K11*100 -> 1498857.4 | M11: 3.84 | N11: =(L11*M11)/1000 -> 5755.6123 | O11: =12/1000 -> 0.012 | P11: =(O11*L11)/1000 -> 17.986288 | Q11: =1.2/1000 -> 0.0012 | R11: =Q11*L11/1000 -> 1.7986288 | S11: 100 | T11: =G11*S11*assumptions!$D$6 -> 61880 | U11: 10.9 | V11: 0.055555556 | W11: 2058.87 | X11: =W11*0.97 -> 1997.1039 | Y11: =X11*assumptions!$C$7 -> 2596.2351 | Z11: =W11*0.03 -> 61.7661 | AA11: =Z11*assumptions!$C$8 -> 111.17898 | AB11: 45 | AC11: 2 | AD11: 3 | AE11: 3.5 | AF11: 598.5 | AG11: 5267 | AH11: 10640 | AI11: 2660 | AJ11: 831 | AK11: 2550 | AL11: 1805 | AM11: =Y11+AF11+AG11+AH11+AI11+AJ11+AK11+AL11+AA11 -> 27058.914 | AN11: 3825 | AO11: 38150 | AP11: =AN11+AO11 -> 41975
B12: 6 CDG | C12: Fokker 100 | D12: SAF | E12: =7*52 -> 364 | F12: =E12/2 -> 182 | G12: =E12 -> 364 | H12: =_xlfn.XLOOKUP(B12,'[1]Baseline 2025'!$B:$B,'[1]Baseline 2025'!$C:$C) -> 399 | I12: =E12*H12 -> 145236 | J12: =_xlfn.XLOOKUP(B12,'[1]Baseline 2025'!$B:$B,'[1]Baseline 2025'!$E:$E) -> Short Haul | K12: =_xlfn.XLOOKUP(B12,'[1]Baseline 2025'!$B:$B,'[1]Baseline 2025'!$I:$I)/100 -> 10660.322 | L12: =K12*100 -> 1066032.2 | M12: 3.84 | N12: =(L12*M12)/1000 -> 4093.5638 | O12: =12/1000 -> 0.012 | P12: =(O12*L12)/1000 -> 12.792387 | Q12: =1.2/1000 -> 0.0012 | R12: =Q12*L12/1000 -> 1.2792387 | S12: 100 | T12: =G12*S12*assumptions!$D$6 -> 30940 | U12: 10.9 | V12: 0.055555556 | W12: 1464.33 | X12: =W12*0.97 -> 1420.4001 | Y12: =X12*assumptions!$C$7 -> 1846.5201 | Z12: =W12*0.03 -> 43.9299 | AA12: =Z12*assumptions!$C$8 -> 79.07382 | AB12: 30 | AC12: 2 | AD12: 3 | AE12: 3.5 | AF12: 598.5 | AG12: 5024 | AH12: 10640 | AI12: 2660 | AJ12: 831 | AK12: 2550 | AL12: 1811 | AM12: =Y12+AF12+AG12+AH12+AI12+AJ12+AK12+AL12+AA12 -> 26040.094 | AN12: 2550 | AO12: 38150 | AP12: =AN12+AO12 -> 40700
B13: 7 DUB | C13: Fokker 100 | D13: SAF | E13: =7*52 -> 364 | F13: =E13/2 -> 182 | G13: =E13 -> 364 | H13: =_xlfn.XLOOKUP(B13,'[1]Baseline 2025'!$B:$B,'[1]Baseline 2025'!$C:$C) -> 753 | I13: =E13*H13 -> 274092 | J13: =_xlfn.XLOOKUP(B13,'[1]Baseline 2025'!$B:$B,'[1]Baseline 2025'!$E:$E) -> Short Haul | K13: =_xlfn.XLOOKUP(B13,'[1]Baseline 2025'!$B:$B,'[1]Baseline 2025'!$I:$I)/100 -> 20118.353 | L13: =K13*100 -> 2011835.3 | M13: 3.84 | N13: =(L13*M13)/1000 -> 7725.4475 | O13: =12/1000 -> 0.012 | P13: =(O13*L13)/1000 -> 24.142023 | Q13: =1.2/1000 -> 0.0012 | R13: =Q13*L13/1000 -> 2.4142023 | S13: 100 | T13: =G13*S13*assumptions!$D$6 -> 30940 | U13: 10.9 | V13: 0.069444444 | W13: 2763.51 | X13: =W13*0.97 -> 2680.6047 | Y13: =X13*assumptions!$C$7 -> 3484.7861 | Z13: =W13*0.03 -> 82.9053 | AA13: =Z13*assumptions!$C$8 -> 149.22954 | AB13: 75 | AC13: 2 | AD13: 3 | AE13: 3.5 | AF13: 747 | AG13: 5555 | AH13: 13280 | AI13: 3320 | AJ13: 1038 | AK13: 2550 | AL13: 2273 | AM13: =Y13+AF13+AG13+AH13+AI13+AJ13+AK13+AL13+AA13 -> 32397.016 | AN13: 6375 | AO13: 38150 | AP13: =AN13+AO13 -> 44525
B14: 8 FAO | C14: Fokker 100 | D14: SAF | E14: =7*52 -> 364 | F14: =E14/2 -> 182 | G14: =E14 -> 364 | H14: =_xlfn.XLOOKUP(B14,'[1]Baseline 2025'!$B:$B,'[1]Baseline 2025'!$C:$C) -> 1970 | I14: =E14*H14 -> 717080 | J14: =_xlfn.XLOOKUP(B14,'[1]Baseline 2025'!$B:$B,'[1]Baseline 2025'!$E:$E) -> Short Haul | K14: =_xlfn.XLOOKUP(B14,'[1]Baseline 2025'!$B:$B,'[1]Baseline 2025'!$I:$I)/100 -> 52633.672 | L14: =K14*100 -> 5263367.2 | M14: 3.84 | N14: =(L14*M14)/1000 -> 20211.33 | O14: =12/1000 -> 0.012 | P14: =(O14*L14)/1000 -> 63.160406 | Q14: =1.2/1000 -> 0.0012 | R14: =Q14*L14/1000 -> 6.3160406 | S14: 100 | T14: =G14*S14*assumptions!$D$6 -> 30940 | U14: 10.9 | V14: 0.125 | W14: 7229.9 | X14: =W14*0.97 -> 7013.003 | Y14: =X14*assumptions!$C$7 -> 9116.9039 | Z14: =W14*0.03 -> 216.897 | AA14: =Z14*assumptions!$C$8 -> 390.4146 | AB14: 250 | AC14: 2 | AD14: 3 | AE14: 3.5 | AF14: 1350 | AG14: 7380 | AH14: 24000 | AI14: 6000 | AJ14: 1875 | AK14: 2550 | AL14: 3763 | AM14: =Y14+AF14+AG14+AH14+AI14+AJ14+AK14+AL14+AA14 -> 56425.318 | AN14: 21250 | AO14: 38150 | AP14: =AN14+AO14 -> 59400
B15: 9 LIS | C15: Fokker 100 | D15: SAF | E15: =7*52 -> 364 | F15: =E15/2 -> 182 | G15: =E15 -> 364 | H15: =_xlfn.XLOOKUP(B15,'[1]Baseline 2025'!$B:$B,'[1]Baseline 2025'!$C:$C) -> 1848 | I15: =E15*H15 -> 672672 | J15: =_xlfn.XLOOKUP(B15,'[1]Baseline 2025'!$B:$B,'[1]Baseline 2025'!$E:$E) -> Short Haul | K15: =_xlfn.XLOOKUP(B15,'[1]Baseline 2025'!$B:$B,'[1]Baseline 2025'!$I:$I)/100 -> 49374.125 | L15: =K15*100 -> 4937412.5 | M15: 3.84 | N15: =(L15*M15)/1000 -> 18959.664 | O15: =12/1000 -> 0.012 | P15: =(O15*L15)/1000 -> 59.24895 | Q15: =1.2/1000 -> 0.0012 | R15: =Q15*L15/1000 -> 5.924895 | S15: 100 | T15: =G15*S15*assumptions!$D$6 -> 30940 | U15: 10.9 | V15: 0.13194444 | W15: 6782.16 | X15: =W15*0.97 -> 6578.6952 | Y15: =X15*assumptions!$C$7 -> 8552.3038 | Z15: =W15*0.03 -> 203.4648 | AA15: =Z15*assumptions!$C$8 -> 366.23664 | AB15: 264 | AC15: 2 | AD15: 3 | AE15: 3.5 | AF15: 1425.015 | AG15: 7197 | AH15: 25333.6 | AI15: 6333.4 | AJ15: 1979 | AK15: 2550 | AL15: 3840 | AM15: =Y15+AF15+AG15+AH15+AI15+AJ15+AK15+AL15+AA15 -> 57576.555 | AN15: 22440 | AO15: 38150 | AP15: =AN15+AO15 -> 60590
B16: 10 MUC | C16: Fokker 100 | D16: SAF | E16: =7*52 -> 364 | F16: =E16/2 -> 182 | G16: =E16 -> 364 | H16: =_xlfn.XLOOKUP(B16,'[1]Baseline 2025'!$B:$B,'[1]Baseline 2025'!$C:$C) -> 665 | I16: =E16*H16 -> 242060 | J16: =_xlfn.XLOOKUP(B16,'[1]Baseline 2025'!$B:$B,'[1]Baseline 2025'!$E:$E) -> Short Haul | K16: =_xlfn.XLOOKUP(B16,'[1]Baseline 2025'!$B:$B,'[1]Baseline 2025'!$I:$I)/100 -> 17767.204 | L16: =K16*100 -> 1776720.4 | M16: 3.84 | N16: =(L16*M16)/1000 -> 6822.6063 | O16: =12/1000 -> 0.012 | P16: =(O16*L16)/1000 -> 21.320645 | Q16: =1.2/1000 -> 0.0012 | R16: =Q16*L16/1000 -> 2.1320645 | S16: 100 | T16: =G16*S16*assumptions!$D$6 -> 30940 | U16: 10.9 | V16: 0.059027778 | W16: 2440.55 | X16: =W16*0.97 -> 2367.3335 | Y16: =X16*assumptions!$C$7 -> 3077.5335 | Z16: =W16*0.03 -> 73.2165 | AA16: =Z16*assumptions!$C$8 -> 131.7897 | AB16: 49 | AC16: 2 | AD16: 3 | AE16: 3.5 | AF16: 639 | AG16: 5423 | AH16: 11360 | AI16: 2840 | AJ16: 888 | AK16: 2550 | AL16: 1923 | AM16: =Y16+AF16+AG16+AH16+AI16+AJ16+AK16+AL16+AA16 -> 28832.323 | AN16: 4143.75 | AO16: 38150 | AP16: =AN16+AO16 -> 42293.75
B17: 11 OSL | C17: Fokker 100 | D17: SAF | E17: =7*52 -> 364 | F17: =E17/2 -> 182 | G17: =E17 -> 364 | H17: =_xlfn.XLOOKUP(B17,'[1]Baseline 2025'!$B:$B,'[1]Baseline 2025'!$C:$C) -> 961 | I17: =E17*H17 -> 349804 | J17: =_xlfn.XLOOKUP(B17,'[1]Baseline 2025'!$B:$B,'[1]Baseline 2025'!$E:$E) -> Short Haul | K17: =_xlfn.XLOOKUP(B17,'[1]Baseline 2025'!$B:$B,'[1]Baseline 2025'!$I:$I)/100 -> 25675.614 | L17: =K17*100 -> 2567561.4 | M17: 3.84 | N17: =(L17*M17)/1000 -> 9859.4356 | O17: =12/1000 -> 0.012 | P17: =(O17*L17)/1000 -> 30.810736 | Q17: =1.2/1000 -> 0.0012 | R17: =Q17*L17/1000 -> 3.0810736 | S17: 100 | T17: =G17*S17*assumptions!$D$6 -> 30940 | U17: 10.9 | V17: 0.072916667 | W17: 3526.87 | X17: =W17*0.97 -> 3421.0639 | Y17: =X17*assumptions!$C$7 -> 4447.3831 | Z17: =W17*0.03 -> 105.8061 | AA17: =Z17*assumptions!$C$8 -> 190.45098 | AB17: 52.5 | AC17: 2 | AD17: 3 | AE17: 3.5 | AF17: 787.5 | AG17: 5867 | AH17: 14000 | AI17: 3500 | AJ17: 1094 | AK17: 2550 | AL17: 2318 | AM17: =Y17+AF17+AG17+AH17+AI17+AJ17+AK17+AL17+AA17 -> 34754.334 | AN17: 4462.5 | AO17: 38150 | AP17: =AN17+AO17 -> 42612.5
B18: 12 PMI | C18: Fokker 100 | D18: SAF | E18: =7*52 -> 364 | F18: =E18/2 -> 182 | G18: =E18 -> 364 | H18: =_xlfn.XLOOKUP(B18,'[1]Baseline 2025'!$B:$B,'[1]Baseline 2025'!$C:$C) -> 1426 | I18: =E18*H18 -> 519064 | J18: =_xlfn.XLOOKUP(B18,'[1]Baseline 2025'!$B:$B,'[1]Baseline 2025'!$E:$E) -> Short Haul | K18: =_xlfn.XLOOKUP(B18,'[1]Baseline 2025'!$B:$B,'[1]Baseline 2025'!$I:$I)/100 -> 38099.298 | L18: =K18*100 -> 3809929.8 | M18: 3.84 | N18: =(L18*M18)/1000 -> 14630.13 | O18: =12/1000 -> 0.012 | P18: =(O18*L18)/1000 -> 45.719157 | Q18: =1.2/1000 -> 0.0012 | R18: =Q18*L18/1000 -> 4.5719157 | S18: 100 | T18: =G18*S18*assumptions!$D$6 -> 30940 | U18: 10.9 | V18: 0.10069444 | W18: 5233.42 | X18: =W18*0.97 -> 5076.4174 | Y18: =X18*assumptions!$C$7 -> 6599.3426 | Z18: =W18*0.03 -> 157.0026 | AA18: =Z18*assumptions!$C$8 -> 282.60468 | AB18: 128 | AC18: 2 | AD18: 3 | AE18: 3.5 | AF18: 1089 | AG18: 6564 | AH18: 19360 | AI18: 4840 | AJ18: 1513 | AK18: 2550 | AL18: 3058 | AM18: =Y18+AF18+AG18+AH18+AI18+AJ18+AK18+AL18+AA18 -> 45855.947 | AN18: 10837.5 | AO18: 38150 | AP18: =AN18+AO18 -> 48987.5
B19: 13 VIE | C19: Fokker 100 | D19: SAF | E19: =7*52 -> 364 | F19: =E19/2 -> 182 | G19: =E19 -> 364 | H19: =_xlfn.XLOOKUP(B19,'[1]Baseline 2025'!$B:$B,'[1]Baseline 2025'!$C:$C) -> 962 | I19: =E19*H19 -> 350168 | J19: =_xlfn.XLOOKUP(B19,'[1]Baseline 2025'!$B:$B,'[1]Baseline 2025'!$E:$E) -> Short Haul | K19: =_xlfn.XLOOKUP(B19,'[1]Baseline 2025'!$B:$B,'[1]Baseline 2025'!$I:$I)/100 -> 25702.331 | L19: =K19*100 -> 2570233.1 | M19: 3.84 | N19: =(L19*M19)/1000 -> 9869.6952 | O19: =12/1000 -> 0.012 | P19: =(O19*L19)/1000 -> 30.842797 | Q19: =1.2/1000 -> 0.0012 | R19: =Q19*L19/1000 -> 3.0842797 | S19: 100 | T19: =G19*S19*assumptions!$D$6 -> 30940 | U19: 10.9 | V19: 0.072916667 | W19: 3530.54 | X19: =W19*0.97 -> 3424.6238 | Y19: =X19*assumptions!$C$7 -> 4452.0109 | Z19: =W19*0.03 -> 105.9162 | AA19: =Z19*assumptions!$C$8 -> 190.64916 | AB19: 60.75 | AC19: 2 | AD19: 3 | AE19: 3.5 | AF19: 787.5 | AG19: 5868 | AH19: 14000 | AI19: 3500 | AJ19: 1094 | AK19: 2550 | AL19: 2318 | AM19: =Y19+AF19+AG19+AH19+AI19+AJ19+AK19+AL19+AA19 -> 34760.16 | AN19: 5163.75 | AO19: 38150 | AP19: =AN19+AO19 -> 43313.75
B20: 14 WAW | C20: Fokker 100 | D20: SAF | E20: =7*52 -> 364 | F20: =E20/2 -> 182 | G20: =E20 -> 364 | H20: =_xlfn.XLOOKUP(B20,'[1]Baseline 2025'!$B:$B,'[1]Baseline 2025'!$C:$C) -> 1105 | I20: =E20*H20 -> 402220 | J20: =_xlfn.XLOOKUP(B20,'[1]Baseline 2025'!$B:$B,'[1]Baseline 2025'!$E:$E) -> Short Haul | K20: =_xlfn.XLOOKUP(B20,'[1]Baseline 2025'!$B:$B,'[1]Baseline 2025'!$I:$I)/100 -> 29522.948 | L20: =K20*100 -> 2952294.8 | M20: 3.84 | N20: =(L20*M20)/1000 -> 11336.812 | O20: =12/1000 -> 0.012 | P20: =(O20*L20)/1000 -> 35.427538 | Q20: =1.2/1000 -> 0.0012 | R20: =Q20*L20/1000 -> 3.5427538 | S20: 100 | T20: =G20*S20*assumptions!$D$6 -> 30940 | U20: 10.9 | V20: 0.079861111 | W20: 4055.35 | X20: =W20*0.97 -> 3933.6895 | Y20: =X20*assumptions!$C$7 -> 5113.7964 | Z20: =W20*0.03 -> 121.6605 | AA20: =Z20*assumptions!$C$8 -> 218.9889 | AB20: 66 | AC20: 2 | AD20: 3 | AE20: 3.5 | AF20: 862.515 | AG20: 6083 | AH20: 15333.6 | AI20: 3833.4 | AJ20: 1198 | AK20: 2550 | AL20: 2515 | AM20: =Y20+AF20+AG20+AH20+AI20+AJ20+AK20+AL20+AA20 -> 37708.3 | AN20: 5610 | AO20: 38150 | AP20: =AN20+AO20 -> 43760
B21: 15 ZRH | C21: Fokker 100 | D21: SAF | E21: =14*52*2 -> 1456 | F21: =E21/2 -> 728 | G21: =E21 -> 1456 | H21: =_xlfn.XLOOKUP(B21,'[1]Baseline 2025'!$B:$B,'[1]Baseline 2025'!$C:$C) -> 603 | I21: =E21*H21 -> 877968 | J21: =_xlfn.XLOOKUP(B21,'[1]Baseline 2025'!$B:$B,'[1]Baseline 2025'!$E:$E) -> Short Haul | K21: =_xlfn.XLOOKUP(B21,'[1]Baseline 2025'!$B:$B,'[1]Baseline 2025'!$I:$I)/100 -> 32221.426 | L21: =K21*100 -> 3222142.6 | M21: 3.84 | N21: =(L21*M21)/1000 -> 12373.027 | O21: =12/1000 -> 0.012 | P21: =(O21*L21)/1000 -> 38.665711 | Q21: =1.2/1000 -> 0.0012 | R21: =Q21*L21/1000 -> 3.8665711 | S21: 100 | T21: =G21*S21*assumptions!$D$6 -> 123760 | U21: 10.9 | V21: 0.059027778 | W21: 2213.01 | X21: =W21*0.97 -> 2146.6197 | Y21: =X21*assumptions!$C$7 -> 2790.6056 | Z21: =W21*0.03 -> 66.3903 | AA21: =Z21*assumptions!$C$8 -> 119.50254 | AB21: 48.75 | AC21: 2 | AD21: 3 | AE21: 3.5 | AF21: 637.515 | AG21: 5330 | AH21: 11333.6 | AI21: 2833.4 | AJ21: 885 | AK21: 2550 | AL21: 1892 | AM21: =Y21+AF21+AG21+AH21+AI21+AJ21+AK21+AL21+AA21 -> 28371.623 | AN21: 4143.75 | AO21: 38150 | AP21: =AN21+AO21 -> 42293.75
B22: 16 BKK | C22: B777-200er | D22: SAF | E22: =3*52*2 -> 312 | F22: =E22/2 -> 156 | G22: =E22 -> 312 | H22: =_xlfn.XLOOKUP(B22,'[1]Baseline 2025'!$B:$B,'[1]Baseline 2025'!$C:$C) -> 9217 | I22: =E22*H22 -> 2875704 | J22: =_xlfn.XLOOKUP(B22,'[1]Baseline 2025'!$B:$B,'[1]Baseline 2025'!$E:$E) -> Long Haul | K22: =_xlfn.XLOOKUP(B22,'[1]Baseline 2025'!$B:$B,'[1]Baseline 2025'!$I:$I)/100 -> 213377.24 | L22: =K22*100 -> 21337724 | M22: 3.84 | N22: =(L22*M22)/1000 -> 81936.859 | O22: =12/1000 -> 0.012 | P22: =(O22*L22)/1000 -> 256.05268 | Q22: =1.2/1000 -> 0.0012 | R22: =Q22*L22/1000 -> 25.605268 | S22: 300 | T22: =G22*S22*assumptions!$D$6 -> 79560 | U22: 20 | V22: 0.46875 | W22: 68390.14 | X22: =W22*0.97 -> 66338.436 | Y22: =X22*assumptions!$C$7 -> 86239.967 | Z22: =W22*0.03 -> 2051.7042 | AA22: =Z22*assumptions!$C$8 -> 3693.0676 | AB22: 920 | AC22: 3 | AD22: 12 | AE22: 3.5 | AF22: 11812.5 | AG22: 27101 | AH22: 90000 | AI22: 22500 | AJ22: 21094 | AK22: 7650 | AL22: 19300 | AM22: =Y22+AF22+AG22+AH22+AI22+AJ22+AK22+AL22+AA22 -> 289390.53 | AN22: 234600 | AO22: 70000 | AP22: =AN22+AO22 -> 304600
B23: 17 MFM | C23: B777-200er | D23: SAF | E23: =3*52*2 -> 312 | F23: =E23/2 -> 156 | G23: =E23 -> 312 | H23: =_xlfn.XLOOKUP(B23,'[1]Baseline 2025'!$B:$B,'[1]Baseline 2025'!$C:$C) -> 9285 | I23: =E23*H23 -> 2896920 | J23: =_xlfn.XLOOKUP(B23,'[1]Baseline 2025'!$B:$B,'[1]Baseline 2025'!$E:$E) -> Long Haul | K23: =_xlfn.XLOOKUP(B23,'[1]Baseline 2025'!$B:$B,'[1]Baseline 2025'!$I:$I)/100 -> 214951.46 | L23: =K23*100 -> 21495146 | M23: 3.84 | N23: =(L23*M23)/1000 -> 82541.362 | O23: =12/1000 -> 0.012 | P23: =(O23*L23)/1000 -> 257.94176 | Q23: =1.2/1000 -> 0.0012 | R23: =Q23*L23/1000 -> 25.794176 | S23: 300 | T23: =G23*S23*assumptions!$D$6 -> 79560 | U23: 20 | V23: 0.46875 | W23: 68894.7 | X23: =W23*0.97 -> 66827.859 | Y23: =X23*assumptions!$C$7 -> 86876.217 | Z23: =W23*0.03 -> 2066.841 | AA23: =Z23*assumptions!$C$8 -> 3720.3138 | AB23: 924 | AC23: 3 | AD23: 12 | AE23: 3.5 | AF23: 11812.5 | AG23: 27203 | AH23: 90000 | AI23: 22500 | AJ23: 21094 | AK23: 7650 | AL23: 19354 | AM23: =Y23+AF23+AG23+AH23+AI23+AJ23+AK23+AL23+AA23 -> 290210.03 | AN23: 235620 | AO23: 70000 | AP23: =AN23+AO23 -> 305620
B24: 18 HAN | C24: B777-200er | D24: SAF | E24: =52*2 -> 104 | F24: =E24/2 -> 52 | G24: =E24 -> 104 | H24: =_xlfn.XLOOKUP(B24,'[1]Baseline 2025'!$B:$B,'[1]Baseline 2025'!$C:$C) -> 8886 | I24: =E24*H24 -> 924144 | J24: =_xlfn.XLOOKUP(B24,'[1]Baseline 2025'!$B:$B,'[1]Baseline 2025'!$E:$E) -> Long Haul | K24: =_xlfn.XLOOKUP(B24,'[1]Baseline 2025'!$B:$B,'[1]Baseline 2025'!$I:$I)/100 -> 68571.485 | L24: =K24*100 -> 6857148.5 | M24: 3.84 | N24: =(L24*M24)/1000 -> 26331.45 | O24: =12/1000 -> 0.012 | P24: =(O24*L24)/1000 -> 82.285782 | Q24: =1.2/1000 -> 0.0012 | R24: =Q24*L24/1000 -> 8.2285782 | S24: 300 | T24: =G24*S24*assumptions!$D$6 -> 26520 | U24: 20 | V24: 0.45833333 | W24: 65934.12 | X24: =W24*0.97 -> 63956.096 | Y24: =X24*assumptions!$C$7 -> 83142.925 | Z24: =W24*0.03 -> 1978.0236 | AA24: =Z24*assumptions!$C$8 -> 3560.4425 | AB24: 889 | AC24: 3 | AD24: 12 | AE24: 3.5 | AF24: 11550 | AG24: 26604 | AH24: 88000 | AI24: 22000 | AJ24: 20625 | AK24: 7650 | AL24: 18802 | AM24: =Y24+AF24+AG24+AH24+AI24+AJ24+AK24+AL24+AA24 -> 281934.37 | AN24: 226695 | AO24: 70000 | AP24: =AN24+AO24 -> 296695
B25: 19 PTY | C25: B777-200er | D25: SAF | E25: =156*2 -> 312 | F25: =E25/2 -> 156 | G25: =E25 -> 312 | H25: =_xlfn.XLOOKUP(B25,'[1]Baseline 2025'!$B:$B,'[1]Baseline 2025'!$C:$C) -> 8818 | I25: =E25*H25 -> 2751216 | J25: =_xlfn.XLOOKUP(B25,'[1]Baseline 2025'!$B:$B,'[1]Baseline 2025'!$E:$E) -> Long Haul | K25: =_xlfn.XLOOKUP(B25,'[1]Baseline 2025'!$B:$B,'[1]Baseline 2025'!$I:$I)/100 -> 204140.23 | L25: =K25*100 -> 20414023 | M25: 3.84 | N25: =(L25*M25)/1000 -> 78389.847 | O25: =12/1000 -> 0.012 | P25: =(O25*L25)/1000 -> 244.96827 | Q25: =1.2/1000 -> 0.0012 | R25: =Q25*L25/1000 -> 24.496827 | S25: 300 | T25: =G25*S25*assumptions!$D$6 -> 79560 | U25: 20 | V25: 0.46527778 | W25: 65429.56 | X25: =W25*0.97 -> 63466.673 | Y25: =X25*assumptions!$C$7 -> 82506.675 | Z25: =W25*0.03 -> 1962.8868 | AA25: =Z25*assumptions!$C$8 -> 3533.1962 | AB25: 896 | AC25: 3 | AD25: 12 | AE25: 3.5 | AF25: 11718 | AG25: 26502 | AH25: 89280 | AI25: 22320 | AJ25: 20925 | AK25: 7650 | AL25: 18895 | AM25: =Y25+AF25+AG25+AH25+AI25+AJ25+AK25+AL25+AA25 -> 283329.87 | AN25: 228480 | AO25: 70000 | AP25: =AN25+AO25 -> 298480
B26: 20 MEX | C26: B777-200er | D26: SAF | E26: =156*2 -> 312 | F26: =E26/2 -> 156 | G26: =E26 -> 312 | H26: =_xlfn.XLOOKUP(B26,'[1]Baseline 2025'!$B:$B,'[1]Baseline 2025'!$C:$C) -> 9220 | I26: =E26*H26 -> 2876640 | J26: =_xlfn.XLOOKUP(B26,'[1]Baseline 2025'!$B:$B,'[1]Baseline 2025'!$E:$E) -> Long Haul | K26: =_xlfn.XLOOKUP(B26,'[1]Baseline 2025'!$B:$B,'[1]Baseline 2025'!$I:$I)/100 -> 213446.69 | L26: =K26*100 -> 21344669 | M26: 3.84 | N26: =(L26*M26)/1000 -> 81963.528 | O26: =12/1000 -> 0.012 | P26: =(O26*L26)/1000 -> 256.13603 | Q26: =1.2/1000 -> 0.0012 | R26: =Q26*L26/1000 -> 25.613603 | S26: 300 | T26: =G26*S26*assumptions!$D$6 -> 79560 | U26: 20 | V26: 0.47916667 | W26: 68412.4 | X26: =W26*0.97 -> 66360.028 | Y26: =X26*assumptions!$C$7 -> 86268.036 | Z26: =W26*0.03 -> 2052.372 | AA26: =Z26*assumptions!$C$8 -> 3694.2696 | AB26: 935 | AC26: 3 | AD26: 12 | AE26: 3.5 | AF26: 12075 | AG26: 27105 | AH26: 92000 | AI26: 23000 | AJ26: 21563 | AK26: 7650 | AL26: 19533 | AM26: =Y26+AF26+AG26+AH26+AI26+AJ26+AK26+AL26+AA26 -> 292888.31 | AN26: 238425 | AO26: 70000 | AP26: =AN26+AO26 -> 308425
B27: 21 GIG | C27: B777-200er | D27: SAF | E27: =52*2 -> 104 | F27: =E27/2 -> 52 | G27: =E27 -> 104 | H27: =_xlfn.XLOOKUP(B27,'[1]Baseline 2025'!$B:$B,'[1]Baseline 2025'!$C:$C) -> 9536 | I27: =E27*H27 -> 991744 | J27: =_xlfn.XLOOKUP(B27,'[1]Baseline 2025'!$B:$B,'[1]Baseline 2025'!$E:$E) -> Long Haul | K27: =_xlfn.XLOOKUP(B27,'[1]Baseline 2025'!$B:$B,'[1]Baseline 2025'!$I:$I)/100 -> 73587.405 | L27: =K27*100 -> 7358740.5 | M27: 3.84 | N27: =(L27*M27)/1000 -> 28257.563 | O27: =12/1000 -> 0.012 | P27: =(O27*L27)/1000 -> 88.304886 | Q27: =1.2/1000 -> 0.0012 | R27: =Q27*L27/1000 -> 8.8304886 | S27: 300 | T27: =G27*S27*assumptions!$D$6 -> 26520 | U27: 20 | V27: 0.5 | W27: 70757.12 | X27: =W27*0.97 -> 68634.406 | Y27: =X27*assumptions!$C$7 -> 89224.728 | Z27: =W27*0.03 -> 2122.7136 | AA27: =Z27*assumptions!$C$8 -> 3820.8845 | AB27: 979 | AC27: 3 | AD27: 12 | AE27: 3.5 | AF27: 12600 | AG27: 27579 | AH27: 96000 | AI27: 24000 | AJ27: 22500 | AK27: 7650 | AL27: 20249 | AM27: =Y27+AF27+AG27+AH27+AI27+AJ27+AK27+AL27+AA27 -> 303623.61 | AN27: 249645 | AO27: 70000 | AP27: =AN27+AO27 -> 319645
B28: 22 CPT | C28: B777-200er | D28: SAF | E28: =156*2 -> 312 | F28: =E28/2 -> 156 | G28: =E28 -> 312 | H28: =_xlfn.XLOOKUP(B28,'[1]Baseline 2025'!$B:$B,'[1]Baseline 2025'!$C:$C) -> 9652 | I28: =E28*H28 -> 3011424 | J28: =_xlfn.XLOOKUP(B28,'[1]Baseline 2025'!$B:$B,'[1]Baseline 2025'!$E:$E) -> Long Haul | K28: =_xlfn.XLOOKUP(B28,'[1]Baseline 2025'!$B:$B,'[1]Baseline 2025'!$I:$I)/100 -> 223447.66 | L28: =K28*100 -> 22344766 | M28: 3.84 | N28: =(L28*M28)/1000 -> 85803.902 | O28: =12/1000 -> 0.012 | P28: =(O28*L28)/1000 -> 268.13719 | Q28: =1.2/1000 -> 0.0012 | R28: =Q28*L28/1000 -> 26.813719 | S28: 300 | T28: =G28*S28*assumptions!$D$6 -> 79560 | U28: 20 | V28: 0.47222222 | W28: 71617.84 | X28: =W28*0.97 -> 69469.305 | Y28: =X28*assumptions!$C$7 -> 90310.096 | Z28: =W28*0.03 -> 2148.5352 | AA28: =Z28*assumptions!$C$8 -> 3867.3634 | AB28: 946 | AC28: 3 | AD28: 12 | AE28: 3.5 | AF28: 11896.5 | AG28: 27753 | AH28: 90640 | AI28: 22660 | AJ28: 21244 | AK28: 7650 | AL28: 19723 | AM28: =Y28+AF28+AG28+AH28+AI28+AJ28+AK28+AL28+AA28 -> 295743.96 | AN28: 241230 | AO28: 70000 | AP28: =AN28+AO28 -> 311230
N29: =SUM(N7:N28) -> 631234.43 | P29: =SUM(P7:P28) -> 1972.6076 | R29: =SUM(R7:R28) -> 197.26076
A31: yearly fuel ussage [tons] | D31: yearly costs | F31: yearly revenue
A32: =(E7*W7)/1000 -> 4309.5489 | D32: =E7*AM7 -> 36466189 | F32: =E7*AP7 -> 38416560
A33: =(E8*W8)/1000 -> 3085.8828 | D33: =E8*AM8 -> 28417544 | F33: =E8*AP8 -> 29931720
A34: =(E9*W9)/1000 -> 3315.6542 | D34: =E9*AM9 -> 31692481 | F34: =E9*AP9 -> 33342400
A35: =(E10*W10)/1000 -> 422.13808 | D35: =E10*AM10 -> 11979626 | F35: =E10*AP10 -> 30093700
A36: =(E11*W11)/1000 -> 1498.8574 | D36: =E11*AM11 -> 19698889 | F36: =E11*AP11 -> 30557800
A37: =(E12*W12)/1000 -> 533.01612 | D37: =E12*AM12 -> 9478594.2 | F37: =E12*AP12 -> 14814800
A38: =(E13*W13)/1000 -> 1005.9176 | D38: =E13*AM13 -> 11792514 | F38: =E13*AP13 -> 16207100
A39: =(E14*W14)/1000 -> 2631.6836 | D39: =E14*AM14 -> 20538816 | F39: =E14*AP14 -> 21621600
A40: =(E15*W15)/1000 -> 2468.7062 | D40: =E15*AM15 -> 20957866 | F40: =E15*AP15 -> 22054760
A41: =(E16*W16)/1000 -> 888.3602 | D41: =E16*AM16 -> 10494966 | F41: =E16*AP16 -> 15394925
A42: =(E17*W17)/1000 -> 1283.7807 | D42: =E17*AM17 -> 12650578 | F42: =E17*AP17 -> 15510950
A43: =(E18*W18)/1000 -> 1904.9649 | D43: =E18*AM18 -> 16691565 | F43: =E18*AP18 -> 17831450
... A53: =(E28*W28)/1000 -> 22344.766 | D53: =E28*AM28 -> 92272115 | F53: =E28*AP28 -> 97103760
A55: sum | D55: sum | F55: sum
A56: =SUM(A32:A53) -> 150484.13 | D56: =SUM(D32:D53) -> 8.1233282e+08 | F56: =SUM(F32:F53) -> 919998430

Sheet Baseline 2050
A4: 97% Jet-A1 & 3% SAF
AC5: Crew costs | AJ5: Costs | AP5: Revenue
B6: Destination | C6: Aircraft | D6: Fuel type | E6: Frequency [per year] | F6: # retour | G6: # flights | H6: Lookup: Distance [km] | I6: Total distance travelled [km] | J6: Lookup: Flight Type | K6: Lookup: fuel consumption [l/100km] | L6: Conditional: Total fuel consumption [l] | M6: SAF LFEC CO2 per kg [kg/kg] | N6: Total CO2 emmission [kg] (tons) | O6: NOX per KG | P6: Total NOX emmision(Tons) | Q6: Sox per KG | R6: Total Sox emmission(Ton) | S6: Seats | T6: Passengers per year | U6: Available cargo (Tons) | V6: Flight time | W6: Fuel | X6: jet-A1 Fuel | Y6: Jet-A1 price | Z6: SAF fuel | AA6: SAF price | AB6: Ticket price | AC6: Pilot | AD6: Cabin crew | AE6: Freight rate (Euro/KG) | AF6: CO2 Price(KG/TON) | AG6: Crew costs | AH6: Airport & Navigation charges | AI6: Maintenance costs | AJ6: Maintenance reserve | AK6: Operational lease | AL6: catering and inflight services | AM6: Insurance and overhead | AN6: Total costs | AO6: Passenger revenu | AP6: Cargo revenu | AQ6: Total revenue
B7: 1 ALC | C7: Fokker 100 | D7: SAF | E7: =7*52*2 -> 728 | F7: =E7/2 -> 364 | G7: =E7 -> 728 | H7: =_xlfn.XLOOKUP(B7,'[1]Baseline 2025'!$B:$B,'[1]Baseline 2025'!$C:$C) -> 1613 | I7: =E7*H7 -> 1174264 | J7: =_xlfn.XLOOKUP(B7,'[1]Baseline 2025'!$B:$B,'[1]Baseline 2025'!$E:$E) -> Short Haul | K7: =_xlfn.XLOOKUP(B7,'[1]Baseline 2025'!$B:$B,'[1]Baseline 2025'!$I:$I)/100 -> 43095.489 | L7: =K7*100 -> 4309548.9 | M7: 3.84 | N7: =(L7*M7)/1000 -> 16548.668 | O7: =12/1000 -> 0.012 | P7: =(O7*L7)/1000 -> 51.714587 | Q7: =1.2/1000 -> 0.0012 | R7: =Q7*L7/1000 -> 5.1714587 | S7: 100 | T7: =G7*S7*assumptions!$D$6 -> 61880 | U7: 10.9 | V7: 0.11111111 | W7: 5919.71 | X7: =W7*0.97 -> 5742.1187 | Y7: =X7*assumptions!$C$7 -> 7464.7543 | Z7: =W7*0.03 -> 177.5913 | AA7: =Z7*assumptions!$D$8 -> 230.86869 | AB7: 172 | AC7: 2 | AD7: 3 | AE7: 3.5 | AF7: 9071 | AG7: 1197 | AH7: 6845 | AI7: 21280 | AJ7: 5320 | AK7: 1663 | AL7: 2550 | AM7: 3333 | AN7: =Y7+AG7+AH7+AI7+AJ7+AK7+AL7+AM7+AA7+AF7 -> 58954.623 | AO7: 14620 | AP7: 38150 | AQ7: =AO7+AP7 -> 52770
B8: 2 ARN | C8: Fokker 100 | D8: SAF | E8: =7*52*2 -> 728 | F8: =E8/2 -> 364 | G8: =E8 -> 728 | H8: =_xlfn.XLOOKUP(B8,'[1]Baseline 2025'!$B:$B,'[1]Baseline 2025'!$C:$C) -> 1155 | I8: =E8*H8 -> 840840 | J8: =_xlfn.XLOOKUP(B8,'[1]Baseline 2025'!$B:$B,'[1]Baseline 2025'!$E:$E) -> Short Haul | K8: =_xlfn.XLOOKUP(B8,'[1]Baseline 2025'!$B:$B,'[1]Baseline 2025'!$I:$I)/100 -> 30858.828 | L8: =K8*100 -> 3085882.8 | M8: 3.84 | N8: =(L8*M8)/1000 -> 11849.79 | O8: =12/1000 -> 0.012 | P8: =(O8*L8)/1000 -> 37.030594 | Q8: =1.2/1000 -> 0.0012 | R8: =Q8*L8/1000 -> 3.7030594 | S8: 100 | T8: =G8*S8*assumptions!$D$6 -> 61880 | U8: 10.9 | V8: 0.083333333 | W8: 4238.85 | X8: =W8*0.97 -> 4111.6845 | Y8: =X8*assumptions!$C$7 -> 5345.1899 | Z8: =W8*0.03 -> 127.1655 | AA8: =Z8*assumptions!$D$8 -> 165.31515 | AB8: 99 | AC8: 2 | AD8: 3 | AE8: 3 | AF8: 6496 | AG8: 900 | AH8: 6158 | AI8: 16000 | AJ8: 4000 | AK8: 1250 | AL8: 2550 | AM8: 2603 | AN8: =Y8+AG8+AH8+AI8+AJ8+AK8+AL8+AM8+AA8+AF8 -> 45467.505 | AO8: 8415 | AP8: 32700 | AQ8: =AO8+AP8 -> 41115
B9: 3 BCN | C9: Fokker 100 | D9: SAF | E9: =7*52*2 -> 728 | F9: =E9/2 -> 364 | G9: =E9 -> 728 | H9: =_xlfn.XLOOKUP(B9,'[1]Baseline 2025'!$B:$B,'[1]Baseline 2025'!$C:$C) -> 1241 | I9: =E9*H9 -> 903448 | J9: =_xlfn.XLOOKUP(B9,'[1]Baseline 2025'!$B:$B,'[1]Baseline 2025'!$E:$E) -> Short Haul | K9: =_xlfn.XLOOKUP(B9,'[1]Baseline 2025'!$B:$B,'[1]Baseline 2025'!$I:$I)/100 -> 33156.542 | L9: =K9*100 -> 3315654.2 | M9: 3.84 | N9: =(L9*M9)/1000 -> 12732.112 | O9: =12/1000 -> 0.012 | P9: =(O9*L9)/1000 -> 39.78785 | Q9: =1.2/1000 -> 0.0012 | R9: =Q9*L9/1000 -> 3.978785 | S9: 100 | T9: =G9*S9*assumptions!$D$6 -> 61880 | U9: 10.9 | V9: 0.097222222 | W9: 4554.47 | X9: =W9*0.97 -> 4417.8359 | Y9: =X9*assumptions!$C$7 -> 5743.1867 | Z9: =W9*0.03 -> 136.6341 | AA9: =Z9*assumptions!$D$8 -> 177.62433 | AB9: 90 | AC9: 2 | AD9: 3 | AE9: 3.5 | AF9: 6979 | AG9: 1048.5 | AH9: 6287 | AI9: 18640 | AJ9: 4660 | AK9: 1456 | AL9: 2550 | AM9: 2903 | AN9: =Y9+AG9+AH9+AI9+AJ9+AK9+AL9+AM9+AA9+AF9 -> 50444.311 | AO9: 7650 | AP9: 38150 | AQ9: =AO9+AP9 -> 45800
B10: 4 BRU | C10: Fokker 100 | D10: SAF | E10: =14*52 -> 728 | F10: =E10/2 -> 364 | G10: =E10 -> 728 | H10: =_xlfn.XLOOKUP(B10,'[1]Baseline 2025'!$B:$B,'[1]Baseline 2025'!$C:$C) -> 158 | I10: =E10*H10 -> 115024 | J10: =_xlfn.XLOOKUP(B10,'[1]Baseline 2025'!$B:$B,'[1]Baseline 2025'!$E:$E) -> Short Haul | K10: =_xlfn.XLOOKUP(B10,'[1]Baseline 2025'!$B:$B,'[1]Baseline 2025'!$I:$I)/100 -> 8442.7616 | L10: =K10*100 -> 844276.16 | M10: 3.84 | N10: =(L10*M10)/1000 -> 3242.0205 | O10: =12/1000 -> 0.012 | P10: =(O10*L10)/1000 -> 10.131314 | Q10: =1.2/1000 -> 0.0012 | R10: =Q10*L10/1000 -> 1.0131314 | S10: 100 | T10: =G10*S10*assumptions!$D$6 -> 61880 | U10: 10.9 | V10: 0.027777778 | W10: 579.86 | X10: =W10*0.97 -> 562.4642 | Y10: =X10*assumptions!$C$7 -> 731.20346 | Z10: =W10*0.03 -> 17.3958 | AA10: =Z10*assumptions!$D$8 -> 22.61454 | AB10: 37.5 | AC10: 2 | AD10: 3 | AE10: 3.5 | AF10: 888 | AG10: 300.015 | AH10: 4662 | AI10: 5333.6 | AJ10: 1333.4 | AK10: 417 | AL10: 2550 | AM10: 1097 | AN10: =Y10+AG10+AH10+AI10+AJ10+AK10+AL10+AM10+AA10+AF10 -> 17334.833 | AO10: 3187.5 | AP10: 38150 | AQ10: =AO10+AP10 -> 41337.5
B11: 5 BSL | C11: Fokker 100 | D11: SAF | E11: =7*52*2 -> 728 | F11: =E11/2 -> 364 | G11: =E11 -> 728 | H11: =_xlfn.XLOOKUP(B11,'[1]Baseline 2025'!$B:$B,'[1]Baseline 2025'!$C:$C) -> 561 | I11: =E11*H11 -> 408408 | J11: =_xlfn.XLOOKUP(B11,'[1]Baseline 2025'!$B:$B,'[1]Baseline 2025'!$E:$E) -> Short Haul | K11: =_xlfn.XLOOKUP(B11,'[1]Baseline 2025'!$B:$B,'[1]Baseline 2025'!$I:$I)/100 -> 14988.574 | L11: =K11*100 -> 1498857.4 | M11: 3.84 | N11: =(L11*M11)/1000 -> 5755.6123 | O11: =12/1000 -> 0.012 | P11: =(O11*L11)/1000 -> 17.986288 | Q11: =1.2/1000 -> 0.0012 | R11: =Q11*L11/1000 -> 1.7986288 | S11: 100 | T11: =G11*S11*assumptions!$D$6 -> 61880 | U11: 10.9 | V11: 0.055555556 | W11: 2058.87 | X11: =W11*0.97 -> 1997.1039 | Y11: =X11*assumptions!$C$7 -> 2596.2351 | Z11: =W11*0.03 -> 61.7661 | AA11: =Z11*assumptions!$D$8 -> 80.29593 | AB11: 45 | AC11: 2 | AD11: 3 | AE11: 3.5 | AF11: 3155 | AG11: 598.5 | AH11: 5267 | AI11: 10640 | AJ11: 2660 | AK11: 831 | AL11: 2550 | AM11: 1805 | AN11: =Y11+AG11+AH11+AI11+AJ11+AK11+AL11+AM11+AA11+AF11 -> 30183.031 | AO11: 3825 | AP11: 38150 | AQ11: =AO11+AP11 -> 41975
B12: 6 CDG | C12: Fokker 100 | D12: SAF | E12: =7*52 -> 364 | F12: =E12/2 -> 182 | G12: =E12 -> 364 | H12: =_xlfn.XLOOKUP(B12,'[1]Baseline 2025'!$B:$B,'[1]Baseline 2025'!$C:$C) -> 399 | I12: =E12*H12 -> 145236 | J12: =_xlfn.XLOOKUP(B12,'[1]Baseline 2025'!$B:$B,'[1]Baseline 2025'!$E:$E) -> Short Haul | K12: =_xlfn.XLOOKUP(B12,'[1]Baseline 2025'!$B:$B,'[1]Baseline 2025'!$I:$I)/100 -> 10660.322 | L12: =K12*100 -> 1066032.2 | M12: 3.84 | N12: =(L12*M12)/1000 -> 4093.5638 | O12: =12/1000 -> 0.012 | P12: =(O12*L12)/1000 -> 12.792387 | Q12: =1.2/1000 -> 0.0012 | R12: =Q12*L12/1000 -> 1.2792387 | S12: 100 | T12: =G12*S12*assumptions!$D$6 -> 30940 | U12: 10.9 | V12: 0.055555556 | W12: 1464.33 | X12: =W12*0.97 -> 1420.4001 | Y12: =X12*assumptions!$C$7 -> 1846.5201 | Z12: =W12*0.03 -> 43.9299 | AA12: =Z12*assumptions!$D$8 -> 57.10887 | AB12: 30 | AC12: 2 | AD12: 3 | AE12: 3.5 | AF12: 2243 | AG12: 598.5 | AH12: 5024 | AI12: 10640 | AJ12: 2660 | AK12: 831 | AL12: 2550 | AM12: 1811 | AN12: =Y12+AG12+AH12+AI12+AJ12+AK12+AL12+AM12+AA12+AF12 -> 28261.129 | AO12: 2550 | AP12: 38150 | AQ12: =AO12+AP12 -> 40700
B13: 7 DUB | C13: Fokker 100 | D13: SAF | E13: =7*52 -> 364 | F13: =E13/2 -> 182 | G13: =E13 -> 364 | H13: =_xlfn.XLOOKUP(B13,'[1]Baseline 2025'!$B:$B,'[1]Baseline 2025'!$C:$C) -> 753 | I13: =E13*H13 -> 274092 | J13: =_xlfn.XLOOKUP(B13,'[1]Baseline 2025'!$B:$B,'[1]Baseline 2025'!$E:$E) -> Short Haul | K13: =_xlfn.XLOOKUP(B13,'[1]Baseline 2025'!$B:$B,'[1]Baseline 2025'!$I:$I)/100 -> 20118.353 | L13: =K13*100 -> 2011835.3 | M13: 3.84 | N13: =(L13*M13)/1000 -> 7725.4475 | O13: =12/1000 -> 0.012 | P13: =(O13*L13)/1000 -> 24.142023 | Q13: =1.2/1000 -> 0.0012 | R13: =Q13*L13/1000 -> 2.4142023 | S13: 100 | T13: =G13*S13*assumptions!$D$6 -> 30940 | U13: 10.9 | V13: 0.069444444 | W13: 2763.51 | X13: =W13*0.97 -> 2680.6047 | Y13: =X13*assumptions!$C$7 -> 3484.7861 | Z13: =W13*0.03 -> 82.9053 | AA13: =Z13*assumptions!$D$8 -> 107.77689 | AB13: 75 | AC13: 2 | AD13: 3 | AE13: 3.5 | AF13: 4235 | AG13: 747 | AH13: 5555 | AI13: 13280 | AJ13: 3320 | AK13: 1038 | AL13: 2550 | AM13: 2273 | AN13: =Y13+AG13+AH13+AI13+AJ13+AK13+AL13+AM13+AA13+AF13 -> 36590.563 | AO13: 6375 | AP13: 38150 | AQ13: =AO13+AP13 -> 44525
B14: 8 FAO | C14: Fokker 100 | D14: SAF | E14: =7*52 -> 364 | F14: =E14/2 -> 182 | G14: =E14 -> 364 | H14: =_xlfn.XLOOKUP(B14,'[1]Baseline 2025'!$B:$B,'[1]Baseline 2025'!$C:$C) -> 1970 | I14: =E14*H14 -> 717080 | J14: =_xlfn.XLOOKUP(B14,'[1]Baseline 2025'!$B:$B,'[1]Baseline 2025'!$E:$E) -> Short Haul | K14: =_xlfn.XLOOKUP(B14,'[1]Baseline 2025'!$B:$B,'[1]Baseline 2025'!$I:$I)/100 -> 52633.672 | L14: =K14*100 -> 5263367.2 | M14: 3.84 | N14: =(L14*M14)/1000 -> 20211.33 | O14: =12/1000 -> 0.012 | P14: =(O14*L14)/1000 -> 63.160406 | Q14: =1.2/1000 -> 0.0012 | R14: =Q14*L14/1000 -> 6.3160406 | S14: 100 | T14: =G14*S14*assumptions!$D$6 -> 30940 | U14: 10.9 | V14: 0.125 | W14: 7229.9 | X14: =W14*0.97 -> 7013.003 | Y14: =X14*assumptions!$C$7 -> 9116.9039 | Z14: =W14*0.03 -> 216.897 | AA14: =Z14*assumptions!$D$8 -> 281.9661 | AB14: 250 | AC14: 2 | AD14: 3 | AE14: 3.5 | AF14: 11079 | AG14: 1350 | AH14: 7380 | AI14: 24000 | AJ14: 6000 | AK14: 1875 | AL14: 2550 | AM14: 3763 | AN14: =Y14+AG14+AH14+AI14+AJ14+AK14+AL14+AM14+AA14+AF14 -> 67395.87 | AO14: 21250 | AP14: 38150 | AQ14: =AO14+AP14 -> 59400
B15: 9 LIS | C15: Fokker 100 | D15: SAF | E15: =7*52 -> 364 | F15: =E15/2 -> 182 | G15: =E15 -> 364 | H15: =_xlfn.XLOOKUP(B15,'[1]Baseline 2025'!$B:$B,'[1]Baseline 2025'!$C:$C) -> 1848 | I15: =E15*H15 -> 672672 | J15: =_xlfn.XLOOKUP(B15,'[1]Baseline 2025'!$B:$B,'[1]Baseline 2025'!$E:$E) -> Short Haul | K15: =_xlfn.XLOOKUP(B15,'[1]Baseline 2025'!$B:$B,'[1]Baseline 2025'!$I:$I)/100 -> 49374.125 | L15: =K15*100 -> 4937412.5 | M15: 3.84 | N15: =(L15*M15)/1000 -> 18959.664 | O15: =12/1000 -> 0.012 | P15: =(O15*L15)/1000 -> 59.24895 | Q15: =1.2/1000 -> 0.0012 | R15: =Q15*L15/1000 -> 5.924895 | S15: 100 | T15: =G15*S15*assumptions!$D$6 -> 30940 | U15: 10.9 | V15: 0.13194444 | W15: 6782.16 | X15: =W15*0.97 -> 6578.6952 | Y15: =X15*assumptions!$C$7 -> 8552.3038 | Z15: =W15*0.03 -> 203.4648 | AA15: =Z15*assumptions!$D$8 -> 264.50424 | AB15: 264 | AC15: 2 | AD15: 3 | AE15: 3.5 | AF15: 10393 | AG15: 1425.015 | AH15: 7197 | AI15: 25333.6 | AJ15: 6333.4 | AK15: 1979 | AL15: 2550 | AM15: 3840 | AN15: =Y15+AG15+AH15+AI15+AJ15+AK15+AL15+AM15+AA15+AF15 -> 67867.823 | AO15: 22440 | AP15: 38150 | AQ15: =AO15+AP15 -> 60590
B16: 10 MUC | C16: Fokker 100 | D16: SAF | E16: =7*52 -> 364 | F16: =E16/2 -> 182 | G16: =E16 -> 364 | H16: =_xlfn.XLOOKUP(B16,'[1]Baseline 2025'!$B:$B,'[1]Baseline 2025'!$C:$C) -> 665 | I16: =E16*H16 -> 242060 | J16: =_xlfn.XLOOKUP(B16,'[1]Baseline 2025'!$B:$B,'[1]Baseline 2025'!$E:$E) -> Short Haul | K16: =_xlfn.XLOOKUP(B16,'[1]Baseline 2025'!$B:$B,'[1]Baseline 2025'!$I:$I)/100 -> 17767.204 | L16: =K16*100 -> 1776720.4 | M16: 3.84 | N16: =(L16*M16)/1000 -> 6822.6063 | O16: =12/1000 -> 0.012 | P16: =(O16*L16)/1000 -> 21.320645 | Q16: =1.2/1000 -> 0.0012 | R16: =Q16*L16/1000 -> 2.1320645 | S16: 100 | T16: =G16*S16*assumptions!$D$6 -> 30940 | U16: 10.9 | V16: 0.059027778 | W16: 2440.55 | X16: =W16*0.97 -> 2367.3335 | Y16: =X16*assumptions!$C$7 -> 3077.5335 | Z16: =W16*0.03 -> 73.2165 | AA16: =Z16*assumptions!$D$8 -> 95.18145 | AB16: 49 | AC16: 2 | AD16: 3 | AE16: 3.5 | AF16: 4855 | AG16: 639 | AH16: 5423 | AI16: 11360 | AJ16: 2840 | AK16: 888 | AL16: 2550 | AM16: 1923 | AN16: =Y16+AG16+AH16+AI16+AJ16+AK16+AL16+AM16+AA16+AF16 -> 33650.715 | AO16: 4143.75 | AP16: 38150 | AQ16: =AO16+AP16 -> 42293.75
B17: 11 OSL | C17: Fokker 100 | D17: SAF | E17: =7*52 -> 364 | F17: =E17/2 -> 182 | G17: =E17 -> 364 | H17: =_xlfn.XLOOKUP(B17,'[1]Baseline 2025'!$B:$B,'[1]Baseline 2025'!$C:$C) -> 961 | I17: =E17*H17 -> 349804 | J17: =_xlfn.XLOOKUP(B17,'[1]Baseline 2025'!$B:$B,'[1]Baseline 2025'!$E:$E) -> Short Haul | K17: =_xlfn.XLOOKUP(B17,'[1]Baseline 2025'!$B:$B,'[1]Baseline 2025'!$I:$I)/100 -> 25675.614 | L17: =K17*100 -> 2567561.4 | M17: 3.84 | N17: =(L17*M17)/1000 -> 9859.4356 | O17: =12/1000 -> 0.012 | P17: =(O17*L17)/1000 -> 30.810736 | Q17: =1.2/1000 -> 0.0012 | R17: =Q17*L17/1000 -> 3.0810736 | S17: 100 | T17: =G17*S17*assumptions!$D$6 -> 30940 | U17: 10.9 | V17: 0.072916667 | W17: 3526.87 | X17: =W17*0.97 -> 3421.0639 | Y17: =X17*assumptions!$C$7 -> 4447.3831 | Z17: =W17*0.03 -> 105.8061 | AA17: =Z17*assumptions!$D$8 -> 137.54793 | AB17: 52.5 | AC17: 2 | AD17: 3 | AE17: 3.5 | AF17: 5404 | AG17: 787.5 | AH17: 5867 | AI17: 14000 | AJ17: 3500 | AK17: 1094 | AL17: 2550 | AM17: 2318 | AN17: =Y17+AG17+AH17+AI17+AJ17+AK17+AL17+AM17+AA17+AF17 -> 40105.431 | AO17: 4462.5 | AP17: 38150 | AQ17: =AO17+AP17 -> 42612.5
B18: 12 PMI | C18: Fokker 100 | D18: SAF | E18: =7*52 -> 364 | F18: =E18/2 -> 182 | G18: =E18 -> 364 | H18: =_xlfn.XLOOKUP(B18,'[1]Baseline 2025'!$B:$B,'[1]Baseline 2025'!$C:$C) -> 1426 | I18: =E18*H18 -> 519064 | J18: =_xlfn.XLOOKUP(B18,'[1]Baseline 2025'!$B:$B,'[1]Baseline 2025'!$E:$E) -> Short Haul | K18: =_xlfn.XLOOKUP(B18,'[1]Baseline 2025'!$B:$B,'[1]Baseline 2025'!$I:$I)/100 -> 38099.298 | L18: =K18*100 -> 3809929.8 | M18: 3.84 | N18: =(L18*M18)/1000 -> 14630.13 | O18: =12/1000 -> 0.012 | P18: =(O18*L18)/1000 -> 45.719157 | Q18: =1.2/1000 -> 0.0012 | R18: =Q18*L18/1000 -> 4.5719157 | S18: 100 | T18: =G18*S18*assumptions!$D$6 -> 30940 | U18: 10.9 | V18: 0.10069444 | W18: 5233.42 | X18: =W18*0.97 -> 5076.4174 | Y18: =X18*assumptions!$C$7 -> 6599.3426 | Z18: =W18*0.03 -> 157.0026 | AA18: =Z18*assumptions!$D$8 -> 204.10338 | AB18: 128 | AC18: 2 | AD18: 3 | AE18: 3.5 | AF18: 8019 | AG18: 1089 | AH18: 6564 | AI18: 19360 | AJ18: 4840 | AK18: 1513 | AL18: 2550 | AM18: 3058 | AN18: =Y18+AG18+AH18+AI18+AJ18+AK18+AL18+AM18+AA18+AF18 -> 53796.446 | AO18: 10837.5 | AP18: 38150 | AQ18: =AO18+AP18 -> 48987.5
B19: 13 VIE | C19: Fokker 100 | D19: SAF | E19: =7*52 -> 364 | F19: =E19/2 -> 182 | G19: =E19 -> 364 | H19: =_xlfn.XLOOKUP(B19,'[1]Baseline 2025'!$B:$B,'[1]Baseline 2025'!$C:$C) -> 962 | I19: =E19*H19 -> 350168 | J19: =_xlfn.XLOOKUP(B19,'[1]Baseline 2025'!$B:$B,'[1]Baseline 2025'!$E:$E) -> Short Haul | K19: =_xlfn.XLOOKUP(B19,'[1]Baseline 2025'!$B:$B,'[1]Baseline 2025'!$I:$I)/100 -> 25702.331 | L19: =K19*100 -> 2570233.1 | M19: 3.84 | N19: =(L19*M19)/1000 -> 9869.6952 | O19: =12/1000 -> 0.012 | P19: =(O19*L19)/1000 -> 30.842797 | Q19: =1.2/1000 -> 0.0012 | R19: =Q19*L19/1000 -> 3.0842797 | S19: 100 | T19: =G19*S19*assumptions!$D$6 -> 30940 | U19: 10.9 | V19: 0.072916667 | W19: 3530.54 | X19: =W19*0.97 -> 3424.6238 | Y19: =X19*assumptions!$C$7 -> 4452.0109 | Z19: =W19*0.03 -> 105.9162 | AA19: =Z19*assumptions!$D$8 -> 137.69106 | AB19: 60.75 | AC19: 2 | AD19: 3 | AE19: 3.5 | AF19: 5411 | AG19: 787.5 | AH19: 5868 | AI19: 14000 | AJ19: 3500 | AK19: 1094 | AL19: 2550 | AM19: 2318 | AN19: =Y19+AG19+AH19+AI19+AJ19+AK19+AL19+AM19+AA19+AF19 -> 40118.202 | AO19: 5163.75 | AP19: 38150 | AQ19: =AO19+AP19 -> 43313.75
B20: 14 WAW | C20: Fokker 100 | D20: SAF | E20: =7*52 -> 364 | F20: =E20/2 -> 182 | G20: =E20 -> 364 | H20: =_xlfn.XLOOKUP(B20,'[1]Baseline 2025'!$B:$B,'[1]Baseline 2025'!$C:$C) -> 1105 | I20: =E20*H20 -> 402220 | J20: =_xlfn.XLOOKUP(B20,'[1]Baseline 2025'!$B:$B,'[1]Baseline 2025'!$E:$E) -> Short Haul | K20: =_xlfn.XLOOKUP(B20,'[1]Baseline 2025'!$B:$B,'[1]Baseline 2025'!$I:$I)/100 -> 29522.948 | L20: =K20*100 -> 2952294.8 | M20: 3.84 | N20: =(L20*M20)/1000 -> 11336.812 | O20: =12/1000 -> 0.012 | P20: =(O20*L20)/1000 -> 35.427538 | Q20: =1.2/1000 -> 0.0012 | R20: =Q20*L20/1000 -> 3.5427538 | S20: 100 | T20: =G20*S20*assumptions!$D$6 -> 30940 | U20: 10.9 | V20: 0.079861111 | W20: 4055.35 | X20: =W20*0.97 -> 3933.6895 | Y20: =X20*assumptions!$C$7 -> 5113.7964 | Z20: =W20*0.03 -> 121.6605 | AA20: =Z20*assumptions!$D$8 -> 158.15865 | AB20: 66 | AC20: 2 | AD20: 3 | AE20: 3.5 | AF20: 6559 | AG20: 862.515 | AH20: 6083 | AI20: 15333.6 | AJ20: 3833.4 | AK20: 1198 | AL20: 2550 | AM20: 2515 | AN20: =Y20+AG20+AH20+AI20+AJ20+AK20+AL20+AM20+AA20+AF20 -> 44206.47 | AO20: 5610 | AP20: 38150 | AQ20: =AO20+AP20 -> 43760
B21: 15 ZRH | C21: Fokker 100 | D21: SAF | E21: =14*52*2 -> 1456 | F21: =E21/2 -> 728 | G21: =E21 -> 1456 | H21: =_xlfn.XLOOKUP(B21,'[1]Baseline 2025'!$B:$B,'[1]Baseline 2025'!$C:$C) -> 603 | I21: =E21*H21 -> 877968 | J21: =_xlfn.XLOOKUP(B21,'[1]Baseline 2025'!$B:$B,'[1]Baseline 2025'!$E:$E) -> Short Haul | K21: =_xlfn.XLOOKUP(B21,'[1]Baseline 2025'!$B:$B,'[1]Baseline 2025'!$I:$I)/100 -> 32221.426 | L21: =K21*100 -> 3222142.6 | M21: 3.84 | N21: =(L21*M21)/1000 -> 12373.027 | O21: =12/1000 -> 0.012 | P21: =(O21*L21)/1000 -> 38.665711 | Q21: =1.2/1000 -> 0.0012 | R21: =Q21*L21/1000 -> 3.8665711 | S21: 100 | T21: =G21*S21*assumptions!$D$6 -> 123760 | U21: 10.9 | V21: 0.059027778 | W21: 2213.01 | X21: =W21*0.97 -> 2146.6197 | Y21: =X21*assumptions!$C$7 -> 2790.6056 | Z21: =W21*0.03 -> 66.3903 | AA21: =Z21*assumptions!$D$8 -> 86.30739 | AB21: 48.75 | AC21: 2 | AD21: 3 | AE21: 3.5 | AF21: 3392 | AG21: 637.515 | AH21: 5330 | AI21: 11333.6 | AJ21: 2833.4 | AK21: 885 | AL21: 2550 | AM21: 1892 | AN21: =Y21+AG21+AH21+AI21+AJ21+AK21+AL21+AM21+AA21+AF21 -> 31730.428 | AO21: 4143.75 | AP21: 38150 | AQ21: =AO21+AP21 -> 42293.75
B22: 16 BKK | C22: B777-200er | D22: SAF | E22: =3*52*2 -> 312 | F22: =E22/2 -> 156 | G22: =E22 -> 312 | H22: =_xlfn.XLOOKUP(B22,'[1]Baseline 2025'!$B:$B,'[1]Baseline 2025'!$C:$C) -> 9217 | I22: =E22*H22 -> 2875704 | J22: =_xlfn.XLOOKUP(B22,'[1]Baseline 2025'!$B:$B,'[1]Baseline 2025'!$E:$E) -> Long Haul | K22: =_xlfn.XLOOKUP(B22,'[1]Baseline 2025'!$B:$B,'[1]Baseline 2025'!$I:$I)/100 -> 213377.24 | L22: =K22*100 -> 21337724 | M22: 3.84 | N22: =(L22*M22)/1000 -> 81936.859 | O22: =12/1000 -> 0.012 | P22: =(O22*L22)/1000 -> 256.05268 | Q22: =1.2/1000 -> 0.0012 | R22: =Q22*L22/1000 -> 25.605268 | S22: 300 | T22: =G22*S22*assumptions!$D$6 -> 79560 | U22: 20 | V22: 0.46875 | W22: 68390.14 | X22: =W22*0.97 -> 66338.436 | Y22: =X22*assumptions!$C$7 -> 86239.967 | Z22: =W22*0.03 -> 2051.7042 | AA22: =Z22*assumptions!$D$8 -> 2667.2155 | AB22: 920 | AC22: 3 | AD22: 12 | AE22: 3.5 | AF22: 104795 | AG22: 11812.5 | AH22: 27101 | AI22: 90000 | AJ22: 22500 | AK22: 21094 | AL22: 7650 | AM22: 19300 | AN22: =Y22+AG22+AH22+AI22+AJ22+AK22+AL22+AM22+AA22+AF22 -> 393159.68 | AO22: 234600 | AP22: 70000 | AQ22: =AO22+AP22 -> 304600
B23: 17 MFM | C23: B777-200er | D23: SAF | E23: =3*52*2 -> 312 | F23: =E23/2 -> 156 | G23: =E23 -> 312 | H23: =_xlfn.XLOOKUP(B23,'[1]Baseline 2025'!$B:$B,'[1]Baseline 2025'!$C:$C) -> 9285 | I23: =E23*H23 -> 2896920 | J23: =_xlfn.XLOOKUP(B23,'[1]Baseline 2025'!$B:$B,'[1]Baseline 2025'!$E:$E) -> Long Haul | K23: =_xlfn.XLOOKUP(B23,'[1]Baseline 2025'!$B:$B,'[1]Baseline 2025'!$I:$I)/100 -> 214951.46 | L23: =K23*100 -> 21495146 | M23: 3.84 | N23: =(L23*M23)/1000 -> 82541.362 | O23: =12/1000 -> 0.012 | P23: =(O23*L23)/1000 -> 257.94176 | Q23: =1.2/1000 -> 0.0012 | R23: =Q23*L23/1000 -> 25.794176 | S23: 300 | T23: =G23*S23*assumptions!$D$6 -> 79560 | U23: 20 | V23: 0.46875 | W23: 68894.7 | X23: =W23*0.97 -> 66827.859 | Y23: =X23*assumptions!$C$7 -> 86876.217 | Z23: =W23*0.03 -> 2066.841 | AA23: =Z23*assumptions!$D$8 -> 2686.8933 | AB23: 924 | AC23: 3 | AD23: 12 | AE23: 3.5 | AF23: 105569 | AG23: 11812.5 | AH23: 27203 | AI23: 90000 | AJ23: 22500 | AK23: 21094 | AL23: 7650 | AM23: 19354 | AN23: =Y23+AG23+AH23+AI23+AJ23+AK23+AL23+AM23+AA23+AF23 -> 394745.61 | AO23: 235620 | AP23: 70000 | AQ23: =AO23+AP23 -> 305620
B24: 18 HAN | C24: B777-200er | D24: SAF | E24: =52*2 -> 104 | F24: =E24/2 -> 52 | G24: =E24 -> 104 | H24: =_xlfn.XLOOKUP(B24,'[1]Baseline 2025'!$B:$B,'[1]Baseline 2025'!$C:$C) -> 8886 | I24: =E24*H24 -> 924144 | J24: =_xlfn.XLOOKUP(B24,'[1]Baseline 2025'!$B:$B,'[1]Baseline 2025'!$E:$E) -> Long Haul | K24: =_xlfn.XLOOKUP(B24,'[1]Baseline 2025'!$B:$B,'[1]Baseline 2025'!$I:$I)/100 -> 68571.485 | L24: =K24*100 -> 6857148.5 | M24: 3.84 | N24: =(L24*M24)/1000 -> 26331.45 | O24: =12/1000 -> 0.012 | P24: =(O24*L24)/1000 -> 82.285782 | Q24: =1.2/1000 -> 0.0012 | R24: =Q24*L24/1000 -> 8.2285782 | S24: 300 | T24: =G24*S24*assumptions!$D$6 -> 26520 | U24: 20 | V24: 0.45833333 | W24: 65934.12 | X24: =W24*0.97 -> 63956.096 | Y24: =X24*assumptions!$C$7 -> 83142.925 | Z24: =W24*0.03 -> 1978.0236 | AA24: =Z24*assumptions!$D$8 -> 2571.4307 | AB24: 889 | AC24: 3 | AD24: 12 | AE24: 3.5 | AF24: 101032 | AG24: 11550 | AH24: 26604 | AI24: 88000 | AJ24: 22000 | AK24: 20625 | AL24: 7650 | AM24: 18802 | AN24: =Y24+AG24+AH24+AI24+AJ24+AK24+AL24+AM24+AA24+AF24 -> 381977.36 | AO24: 226695 | AP24: 70000 | AQ24: =AO24+AP24 -> 296695
B25: 19 PTY | C25: B777-200er | D25: SAF | E25: =156*2 -> 312 | F25: =E25/2 -> 156 | G25: =E25 -> 312 | H25: =_xlfn.XLOOKUP(B25,'[1]Baseline 2025'!$B:$B,'[1]Baseline 2025'!$C:$C) -> 8818 | I25: =E25*H25 -> 2751216 | J25: =_xlfn.XLOOKUP(B25,'[1]Baseline 2025'!$B:$B,'[1]Baseline 2025'!$E:$E) -> Long Haul | K25: =_xlfn.XLOOKUP(B25,'[1]Baseline 2025'!$B:$B,'[1]Baseline 2025'!$I:$I)/100 -> 204140.23 | L25: =K25*100 -> 20414023 | M25: 3.84 | N25: =(L25*M25)/1000 -> 78389.847 | O25: =12/1000 -> 0.012 | P25: =(O25*L25)/1000 -> 244.96827 | Q25: =1.2/1000 -> 0.0012 | R25: =Q25*L25/1000 -> 24.496827 | S25: 300 | T25: =G25*S25*assumptions!$D$6 -> 79560 | U25: 20 | V25: 0.46527778 | W25: 65429.56 | X25: =W25*0.97 -> 63466.673 | Y25: =X25*assumptions!$C$7 -> 82506.675 | Z25: =W25*0.03 -> 1962.8868 | AA25: =Z25*assumptions!$D$8 -> 2551.7528 | AB25: 896 | AC25: 3 | AD25: 12 | AE25: 3.5 | AF25: 100260 | AG25: 11718 | AH25: 26502 | AI25: 89280 | AJ25: 22320 | AK25: 20925 | AL25: 7650 | AM25: 18895 | AN25: =Y25+AG25+AH25+AI25+AJ25+AK25+AL25+AM25+AA25+AF25 -> 382608.43 | AO25: 228480 | AP25: 70000 | AQ25: =AO25+AP25 -> 298480
B26: 20 MEX | C26: B777-200er | D26: SAF | E26: =156*2 -> 312 | F26: =E26/2 -> 156 | G26: =E26 -> 312 | H26: =_xlfn.XLOOKUP(B26,'[1]Baseline 2025'!$B:$B,'[1]Baseline 2025'!$C:$C) -> 9220 | I26: =E26*H26 -> 2876640 | J26: =_xlfn.XLOOKUP(B26,'[1]Baseline 2025'!$B:$B,'[1]Baseline 2025'!$E:$E) -> Long Haul | K26: =_xlfn.XLOOKUP(B26,'[1]Baseline 2025'!$B:$B,'[1]Baseline 2025'!$I:$I)/100 -> 213446.69 | L26: =K26*100 -> 21344669 | M26: 3.84 | N26: =(L26*M26)/1000 -> 81963.528 | O26: =12/1000 -> 0.012 | P26: =(O26*L26)/1000 -> 256.13603 | Q26: =1.2/1000 -> 0.0012 | R26: =Q26*L26/1000 -> 25.613603 | S26: 300 | T26: =G26*S26*assumptions!$D$6 -> 79560 | U26: 20 | V26: 0.47916667 | W26: 68412.4 | X26: =W26*0.97 -> 66360.028 | Y26: =X26*assumptions!$C$7 -> 86268.036 | Z26: =W26*0.03 -> 2052.372 | AA26: =Z26*assumptions!$D$8 -> 2668.0836 | AB26: 935 | AC26: 3 | AD26: 12 | AE26: 3.5 | AF26: 104830 | AG26: 12075 | AH26: 27105 | AI26: 92000 | AJ26: 23000 | AK26: 21563 | AL26: 7650 | AM26: 19533 | AN26: =Y26+AG26+AH26+AI26+AJ26+AK26+AL26+AM26+AA26+AF26 -> 396692.12 | AO26: 238425 | AP26: 70000 | AQ26: =AO26+AP26 -> 308425
B27: 21 GIG | C27: B777-200er | D27: SAF | E27: =52*2 -> 104 | F27: =E27/2 -> 52 | G27: =E27 -> 104 | H27: =_xlfn.XLOOKUP(B27,'[1]Baseline 2025'!$B:$B,'[1]Baseline 2025'!$C:$C) -> 9536 | I27: =E27*H27 -> 991744 | J27: =_xlfn.XLOOKUP(B27,'[1]Baseline 2025'!$B:$B,'[1]Baseline 2025'!$E:$E) -> Long Haul | K27: =_xlfn.XLOOKUP(B27,'[1]Baseline 2025'!$B:$B,'[1]Baseline 2025'!$I:$I)/100 -> 73587.405 | L27: =K27*100 -> 7358740.5 | M27: 3.84 | N27: =(L27*M27)/1000 -> 28257.563 | O27: =12/1000 -> 0.012 | P27: =(O27*L27)/1000 -> 88.304886 | Q27: =1.2/1000 -> 0.0012 | R27: =Q27*L27/1000 -> 8.8304886 | S27: 300 | T27: =G27*S27*assumptions!$D$6 -> 26520 | U27: 20 | V27: 0.5 | W27: 70757.12 | X27: =W27*0.97 -> 68634.406 | Y27: =X27*assumptions!$C$7 -> 89224.728 | Z27: =W27*0.03 -> 2122.7136 | AA27: =Z27*assumptions!$D$8 -> 2759.5277 | AB27: 979 | AC27: 3 | AD27: 12 | AE27: 3.5 | AF27: 108422 | AG27: 12600 | AH27: 27579 | AI27: 96000 | AJ27: 24000 | AK27: 22500 | AL27: 7650 | AM27: 20249 | AN27: =Y27+AG27+AH27+AI27+AJ27+AK27+AL27+AM27+AA27+AF27 -> 410984.26 | AO27: 249645 | AP27: 70000 | AQ27: =AO27+AP27 -> 319645
B28: 22 CPT | C28: B777-200er | D28: SAF | E28: =156*2 -> 312 | F28: =E28/2 -> 156 | G28: =E28 -> 312 | H28: =_xlfn.XLOOKUP(B28,'[1]Baseline 2025'!$B:$B,'[1]Baseline 2025'!$C:$C) -> 9652 | I28: =E28*H28 -> 3011424 | J28: =_xlfn.XLOOKUP(B28,'[1]Baseline 2025'!$B:$B,'[1]Baseline 2025'!$E:$E) -> Long Haul | K28: =_xlfn.XLOOKUP(B28,'[1]Baseline 2025'!$B:$B,'[1]Baseline 2025'!$I:$I)/100 -> 223447.66 | L28: =K28*100 -> 22344766 | M28: 3.84 | N28: =(L28*M28)/1000 -> 85803.902 | O28: =12/1000 -> 0.012 | P28: =(O28*L28)/1000 -> 268.13719 | Q28: =1.2/1000 -> 0.0012 | R28: =Q28*L28/1000 -> 26.813719 | S28: 300 | T28: =G28*S28*assumptions!$D$6 -> 79560 | U28: 20 | V28: 0.47222222 | W28: 71617.84 | X28: =W28*0.97 -> 69469.305 | Y28: =X28*assumptions!$C$7 -> 90310.096 | Z28: =W28*0.03 -> 2148.5352 | AA28: =Z28*assumptions!$D$8 -> 2793.0958 | AB28: 946 | AC28: 3 | AD28: 12 | AE28: 3.5 | AF28: 109741 | AG28: 11896.5 | AH28: 27753 | AI28: 90640 | AJ28: 22660 | AK28: 21244 | AL28: 7650 | AM28: 19723 | AN28: =Y28+AG28+AH28+AI28+AJ28+AK28+AL28+AM28+AA28+AF28 -> 404410.69 | AO28: 241230 | AP28: 70000 | AQ28: =AO28+AP28 -> 311230
N29: =SUM(N7:N28) -> 631234.43 | P29: =SUM(P7:P28) -> 1972.6076 | R29: =SUM(R7:R28) -> 197.26076
A31: yearly fuel ussage [tons] | D31: yearly costs | F31: yearly revenue
A32: =(E7*W7)/1000 -> 4309.5489 | D32: =E7*AN7 -> 42918966 | F32: =E7*AQ7 -> 38416560
A33: =(E8*W8)/1000 -> 3085.8828 | D33: =E8*AN8 -> 33100344 | F33: =E8*AQ8 -> 29931720
A34: =(E9*W9)/1000 -> 3315.6542 | D34: =E9*AN9 -> 36723458 | F34: =E9*AQ9 -> 33342400
A35: =(E10*W10)/1000 -> 422.13808 | D35: =E10*AN10 -> 12619758 | F35: =E10*AQ10 -> 30093700
A36: =(E11*W11)/1000 -> 1498.8574 | D36: =E11*AN11 -> 21973247 | F36: =E11*AQ11 -> 30557800
A37: =(E12*W12)/1000 -> 533.01612 | D37: =E12*AN12 -> 10287051 | F37: =E12*AQ12 -> 14814800
A38: =(E13*W13)/1000 -> 1005.9176 | D38: =E13*AN13 -> 13318965 | F38: =E13*AQ13 -> 16207100
A39: =(E14*W14)/1000 -> 2631.6836 | D39: =E14*AN14 -> 24532097 | F39: =E14*AQ14 -> 21621600
A40: =(E15*W15)/1000 -> 2468.7062 | D40: =E15*AN15 -> 24703888 | F40: =E15*AQ15 -> 22054760
A41: =(E16*W16)/1000 -> 888.3602 | D41: =E16*AN16 -> 12248860 | F41: =E16*AQ16 -> 15394925
A42: =(E17*W17)/1000 -> 1283.7807 | D42: =E17*AN17 -> 14598377 | F42: =E17*AQ17 -> 15510950
A43: =(E18*W18)/1000 -> 1904.9649 | D43: =E18*AN18 -> 19581906 | F43: =E18*AQ18 -> 17831450
... A53: =(E28*W28)/1000 -> 22344.766 | D53: =E28*AN28 -> 1.2617614e+08 | F53: =E28*AQ28 -> 97103760
A55: sum | D55: sum | F55: sum
A56: =SUM(A32:A53) -> 150484.13 | D56: =SUM(D32:D53) -> 1.041113e+09 | F56: =SUM(F32:F53) -> 919998430

Sheet Scenario 1 2025
A4: 100% SAF
Y5: Crew costs | AF5: Costs | AL5: Revenu
B6: Destination | C6: Aircraft | D6: Fuel type | E6: Frequency [per year] | F6: # retour | G6: # flights | H6: Lookup: Distance [km] | I6: Total distance travelled [km] | J6: Lookup: Flight Type | K6: Lookup: fuel consumption [l/100km] | L6: Conditional: Total fuel consumption [l] | M6: SAF LFEC CO2 per kg [kg/kg] | N6: Total CO2 emmission [kg] (tons) | O6: NOX per KG | P6: Total NOX emmision(Tons) | Q6: Sox per KG | R6: Total Sox emmission(Ton) | S6: Seats | T6: Passengers per year | U6: Available cargo (Tons) | V6: Flight time | W6: Fuel | X6: HEFA | Y6: Pilot | Z6: Cabin crew | AA6: Ticket price | AB6: Freight rate (Euro/KG) | AC6: Crew costs | AD6: Airport & Navigation charges | AE6: Maintenance costs | AF6: Maintenance reserve | AG6: Operational lease | AH6: catering and inflight services | AI6: Insurance and overhead | AJ6: Total costs | AK6: Passenger revenue | AL6: Cargo revenue | AM6: Total revenuee | AN6: marge
B7: 1 ALC | C7: Fokker 100 | D7: SAF | E7: =7*52*2 -> 728 | F7: =E7/2 -> 364 | G7: =E7 -> 728 | H7: =_xlfn.XLOOKUP(B7,'[1]Baseline 2025'!$B:$B,'[1]Baseline 2025'!$C:$C) -> 1613 | I7: =E7*H7 -> 1174264 | J7: =_xlfn.XLOOKUP(B7,'[1]Baseline 2025'!$B:$B,'[1]Baseline 2025'!$E:$E) -> Short Haul | K7: =_xlfn.XLOOKUP(B7,'[1]Baseline 2025'!$B:$B,'[1]Baseline 2025'!$I:$I)/100 -> 43095.489 | L7: =K7*100 -> 4309548.9 | M7: =1.3 -> 1.3 | N7: =(L7*M7)/1000 -> 5602.4135 | O7: =9/1000 -> 0.009 | P7: =(O7*L7)/1000 -> 38.78594 | Q7: =0.03/1000 -> 3e-05 | R7: =Q7*L7/1000 -> 0.12928647 | S7: 100 | T7: =G7*S7*assumptions!$D$6 -> 61880 | U7: 10.9 | V7: 0.11111111 | W7: 5919.71 | X7: =W7*assumptions!$C$8 -> 10655.478 | Y7: 2 | Z7: 3 | AA7: 210 | AB7: 3.5 | AC7: 1201.5 | AD7: 6845 | AE7: 21360 | AF7: 5340 | AG7: 1669 | AH7: 2550 | AI7: 3546 | AJ7: =X7+AC7+AD7+AE7+AF7+AG7+AH7+AI7 -> 53166.978 | AK7: 17850 | AL7: 38150 | AM7: =AK7+AL7 -> 56000 | AN7: =(AM7/AJ7)-1 -> 0.053285368
B8: 2 ARN | C8: Fokker 100 | D8: SAF | E8: =7*52*2 -> 728 | F8: =E8/2 -> 364 | G8: =E8 -> 728 | H8: =_xlfn.XLOOKUP(B8,'[1]Baseline 2025'!$B:$B,'[1]Baseline 2025'!$C:$C) -> 1155 | I8: =E8*H8 -> 840840 | J8: =_xlfn.XLOOKUP(B8,'[1]Baseline 2025'!$B:$B,'[1]Baseline 2025'!$E:$E) -> Short Haul | K8: =_xlfn.XLOOKUP(B8,'[1]Baseline 2025'!$B:$B,'[1]Baseline 2025'!$I:$I)/100 -> 30858.828 | L8: =K8*100 -> 3085882.8 | M8: =1.3 -> 1.3 | N8: =(L8*M8)/1000 -> 4011.6476 | O8: =9/1000 -> 0.009 | P8: =(O8*L8)/1000 -> 27.772945 | Q8: =0.03/1000 -> 3e-05 | R8: =Q8*L8/1000 -> 0.092576484 | S8: 100 | T8: =G8*S8*assumptions!$D$6 -> 61880 | U8: 10.9 | V8: 0.083333333 | W8: 4238.85 | X8: =W8*assumptions!$C$8 -> 7629.93 | Y8: 2 | Z8: 3 | AA8: 126 | AB8: 3 | AC8: 900 | AD8: 6150 | AE8: 16000 | AF8: 4000 | AG8: 1250 | AH8: 2550 | AI8: 2750 | AJ8: =X8+AC8+AD8+AE8+AF8+AG8+AH8+AI8 -> 41229.93 | AK8: 10710 | AL8: 32700 | AM8: =AK8+AL8 -> 43410 | AN8: =(AM8/AJ8)-1 -> 0.052875908
B9: 3 BCN | C9: Fokker 100 | D9: SAF | E9: =7*52*2 -> 728 | F9: =E9/2 -> 364 | G9: =E9 -> 728 | H9: =_xlfn.XLOOKUP(B9,'[1]Baseline 2025'!$B:$B,'[1]Baseline 2025'!$C:$C) -> 1241 | I9: =E9*H9 -> 903448 | J9: =_xlfn.XLOOKUP(B9,'[1]Baseline 2025'!$B:$B,'[1]Baseline 2025'!$E:$E) -> Short Haul | K9: =_xlfn.XLOOKUP(B9,'[1]Baseline 2025'!$B:$B,'[1]Baseline 2025'!$I:$I)/100 -> 33156.542 | L9: =K9*100 -> 3315654.2 | M9: =1.3 -> 1.3 | N9: =(L9*M9)/1000 -> 4310.3504 | O9: =9/1000 -> 0.009 | P9: =(O9*L9)/1000 -> 29.840887 | Q9: =0.03/1000 -> 3e-05 | R9: =Q9*L9/1000 -> 0.099469625 | S9: 100 | T9: =G9*S9*assumptions!$D$6 -> 61880 | U9: 10.9 | V9: 0.097222222 | W9: 4554.47 | X9: =W9*assumptions!$C$8 -> 8198.046 | Y9: 2 | Z9: 3 | AA9: 120 | AB9: 3.5 | AC9: 1048.5 | AD9: 6287 | AE9: 18640 | AF9: 4660 | AG9: 1456 | AH9: 2550 | AI9: 3061 | AJ9: =X9+AC9+AD9+AE9+AF9+AG9+AH9+AI9 -> 45900.546 | AK9: 10200 | AL9: 38150 | AM9: =AK9+AL9 -> 48350 | AN9: =(AM9/AJ9)-1 -> 0.053364376
B10: 4 BRU | C10: Fokker 100 | D10: SAF | E10: =14*52 -> 728 | F10: =E10/2 -> 364 | G10: =E10 -> 728 | H10: =_xlfn.XLOOKUP(B10,'[1]Baseline 2025'!$B:$B,'[1]Baseline 2025'!$C:$C) -> 158 | I10: =E10*H10 -> 115024 | J10: =_xlfn.XLOOKUP(B10,'[1]Baseline 2025'!$B:$B,'[1]Baseline 2025'!$E:$E) -> Short Haul | K10: =_xlfn.XLOOKUP(B10,'[1]Baseline 2025'!$B:$B,'[1]Baseline 2025'!$I:$I)/100 -> 8442.7616 | L10: =K10*100 -> 844276.16 | M10: =1.3 -> 1.3 | N10: =(L10*M10)/1000 -> 1097.559 | O10: =9/1000 -> 0.009 | P10: =(O10*L10)/1000 -> 7.5984854 | Q10: =0.03/1000 -> 3e-05 | R10: =Q10*L10/1000 -> 0.025328285 | S10: 100 | T10: =G10*S10*assumptions!$D$6 -> 61880 | U10: 10.9 | V10: 0.027777778 | W10: 579.86 | X10: =W10*assumptions!$C$8 -> 1043.748 | Y10: 2 | Z10: 3 | AA10: 50 | AB10: 3.5 | AC10: 297 | AD10: 4662 | AE10: 5280 | AF10: 1320 | AG10: 413 | AH10: 2550 | AI10: 1112 | AJ10: =X10+AC10+AD10+AE10+AF10+AG10+AH10+AI10 -> 16677.748 | AK10: 4250 | AL10: 38150 | AM10: =AK10+AL10 -> 42400 | AN10: 0.607
B11: 5 BSL | C11: Fokker 100 | D11: SAF | E11: =7*52*2 -> 728 | F11: =E11/2 -> 364 | G11: =E11 -> 728 | H11: =_xlfn.XLOOKUP(B11,'[1]Baseline 2025'!$B:$B,'[1]Baseline 2025'!$C:$C) -> 561 | I11: =E11*H11 -> 408408 | J11: =_xlfn.XLOOKUP(B11,'[1]Baseline 2025'!$B:$B,'[1]Baseline 2025'!$E:$E) -> Short Haul | K11: =_xlfn.XLOOKUP(B11,'[1]Baseline 2025'!$B:$B,'[1]Baseline 2025'!$I:$I)/100 -> 14988.574 | L11: =K11*100 -> 1498857.4 | M11: =1.3 -> 1.3 | N11: =(L11*M11)/1000 -> 1948.5146 | O11: =9/1000 -> 0.009 | P11: =(O11*L11)/1000 -> 13.489716 | Q11: =0.03/1000 -> 3e-05 | R11: =Q11*L11/1000 -> 0.044965721 | S11: 100 | T11: =G11*S11*assumptions!$D$6 -> 61880 | U11: 10.9 | V11: 0.055555556 | W11: 2058.87 | X11: =W11*assumptions!$C$8 -> 3705.966 | Y11: 2 | Z11: 3 | AA11: 60 | AB11: 3.5 | AC11: 598.5 | AD11: 5267 | AE11: 10640 | AF11: 2660 | AG11: 831 | AH11: 2550 | AI11: 1876 | AJ11: =X11+AC11+AD11+AE11+AF11+AG11+AH11+AI11 -> 28128.466 | AK11: 5100 | AL11: 38150 | AM11: =AK11+AL11 -> 43250 | AN11: =(AM11/AJ11)-1 -> 0.53758829
B12: 6 CDG | C12: Fokker 100 | D12: SAF | E12: =7*52 -> 364 | F12: =E12/2 -> 182 | G12: =E12 -> 364 | H12: =_xlfn.XLOOKUP(B12,'[1]Baseline 2025'!$B:$B,'[1]Baseline 2025'!$C:$C) -> 399 | I12: =E12*H12 -> 145236 | J12: =_xlfn.XLOOKUP(B12,'[1]Baseline 2025'!$B:$B,'[1]Baseline 2025'!$E:$E) -> Short Haul | K12: =_xlfn.XLOOKUP(B12,'[1]Baseline 2025'!$B:$B,'[1]Baseline 2025'!$I:$I)/100 -> 10660.322 | L12: =K12*100 -> 1066032.2 | M12: =1.3 -> 1.3 | N12: =(L12*M12)/1000 -> 1385.8419 | O12: =9/1000 -> 0.009 | P12: =(O12*L12)/1000 -> 9.5942902 | Q12: =0.03/1000 -> 3e-05 | R12: =Q12*L12/1000 -> 0.031980967 | S12: 100 | T12: =G12*S12*assumptions!$D$6 -> 30940 | U12: 10.9 | V12: 0.055555556 | W12: 1464.33 | X12: =W12*assumptions!$C$8 -> 2635.794 | Y12: 2 | Z12: 3 | AA12: 60 | AB12: 3.5 | AC12: 598.5 | AD12: 5024 | AE12: 10640 | AF12: 2660 | AG12: 831 | AH12: 2550 | AI12: 1781 | AJ12: =X12+AC12+AD12+AE12+AF12+AG12+AH12+AI12 -> 26720.294 | AK12: 5100 | AL12: 38150 | AM12: =AK12+AL12 -> 43250 | AN12: =(AM12/AJ12)-1 -> 0.61861991
B13: 7 DUB | C13: Fokker 100 | D13: SAF | E13: =7*52 -> 364 | F13: =E13/2 -> 182 | G13: =E13 -> 364 | H13: =_xlfn.XLOOKUP(B13,'[1]Baseline 2025'!$B:$B,'[1]Baseline 2025'!$C:$C) -> 753 | I13: =E13*H13 -> 274092 | J13: =_xlfn.XLOOKUP(B13,'[1]Baseline 2025'!$B:$B,'[1]Baseline 2025'!$E:$E) -> Short Haul | K13: =_xlfn.XLOOKUP(B13,'[1]Baseline 2025'!$B:$B,'[1]Baseline 2025'!$I:$I)/100 -> 20118.353 | L13: =K13*100 -> 2011835.3 | M13: =1.3 -> 1.3 | N13: =(L13*M13)/1000 -> 2615.3859 | O13: =9/1000 -> 0.009 | P13: =(O13*L13)/1000 -> 18.106518 | Q13: =0.03/1000 -> 3e-05 | R13: =Q13*L13/1000 -> 0.060355058 | S13: 100 | T13: =G13*S13*assumptions!$D$6 -> 30940 | U13: 10.9 | V13: 0.069444444 | W13: 2763.51 | X13: =W13*assumptions!$C$8 -> 4974.318 | Y13: 2 | Z13: 3 | AA13: 67 | AB13: 3.5 | AC13: 747 | AD13: 5555 | AE13: 13280 | AF13: 3320 | AG13: 1038 | AH13: 2550 | AI13: 2248 | AJ13: =X13+AC13+AD13+AE13+AF13+AG13+AH13+AI13 -> 33712.318 | AK13: 5695 | AL13: 38150 | AM13: =AK13+AL13 -> 43845 | AN13: =(AM13/AJ13)-1 -> 0.30056319
B14: 8 FAO | C14: Fokker 100 | D14: SAF | E14: =7*52 -> 364 | F14: =E14/2 -> 182 | G14: =E14 -> 364 | H14: =_xlfn.XLOOKUP(B14,'[1]Baseline 2025'!$B:$B,'[1]Baseline 2025'!$C:$C) -> 1970 | I14: =E14*H14 -> 717080 | J14: =_xlfn.XLOOKUP(B14,'[1]Baseline 2025'!$B:$B,'[1]Baseline 2025'!$E:$E) -> Short Haul | K14: =_xlfn.XLOOKUP(B14,'[1]Baseline 2025'!$B:$B,'[1]Baseline 2025'!$I:$I)/100 -> 52633.672 | L14: =K14*100 -> 5263367.2 | M14: =1.3 -> 1.3 | N14: =(L14*M14)/1000 -> 6842.3774 | O14: =9/1000 -> 0.009 | P14: =(O14*L14)/1000 -> 47.370305 | Q14: =0.03/1000 -> 3e-05 | R14: =Q14*L14/1000 -> 0.15790102 | S14: 100 | T14: =G14*S14*assumptions!$D$6 -> 30940 | U14: 10.9 | V14: 0.125 | W14: 7229.9 | X14: =W14*assumptions!$C$8 -> 13013.82 | Y14: 2 | Z14: 3 | AA14: 285 | AB14: 3.5 | AC14: 1350 | AD14: 7380 | AE14: 24000 | AF14: 6000 | AG14: 1875 | AH14: 2550 | AI14: 4041 | AJ14: =X14+AC14+AD14+AE14+AF14+AG14+AH14+AI14 -> 60209.82 | AK14: 24225 | AL14: 38150 | AM14: =AK14+AL14 -> 62375 | AN14: 0.05
B15: 9 LIS | C15: Fokker 100 | D15: SAF | E15: =7*52 -> 364 | F15: =E15/2 -> 182 | G15: =E15 -> 364 | H15: =_xlfn.XLOOKUP(B15,'[1]Baseline 2025'!$B:$B,'[1]Baseline 2025'!$C:$C) -> 1848 | I15: =E15*H15 -> 672672 | J15: =_xlfn.XLOOKUP(B15,'[1]Baseline 2025'!$B:$B,'[1]Baseline 2025'!$E:$E) -> Short Haul | K15: =_xlfn.XLOOKUP(B15,'[1]Baseline 2025'!$B:$B,'[1]Baseline 2025'!$I:$I)/100 -> 49374.125 | L15: =K15*100 -> 4937412.5 | M15: =1.3 -> 1.3 | N15: =(L15*M15)/1000 -> 6418.6362 | O15: =9/1000 -> 0.009 | P15: =(O15*L15)/1000 -> 44.436712 | Q15: =0.03/1000 -> 3e-05 | R15: =Q15*L15/1000 -> 0.14812237 | S15: 100 | T15: =G15*S15*assumptions!$D$6 -> 30940 | U15: 10.9 | V15: 0.13194444 | W15: 6782.16 | X15: =W15*assumptions!$C$8 -> 12207.888 | Y15: 2 | Z15: 3 | AA15: 308 | AB15: 3.5 | AC15: 1425 | AD15: 7197 | AE15: 25334 | AF15: 6333 | AG15: 1979 | AH15: 2550 | AI15: 4075 | AJ15: =X15+AC15+AD15+AE15+AF15+AG15+AH15+AI15 -> 61100.888 | AK15: 26180 | AL15: 38150 | AM15: =AK15+AL15 -> 64330 | AN15: 0.05
B16: 10 MUC | C16: Fokker 100 | D16: SAF | E16: =7*52 -> 364 | F16: =E16/2 -> 182 | G16: =E16 -> 364 | H16: =_xlfn.XLOOKUP(B16,'[1]Baseline 2025'!$B:$B,'[1]Baseline 2025'!$C:$C) -> 665 | I16: =E16*H16 -> 242060 | J16: =_xlfn.XLOOKUP(B16,'[1]Baseline 2025'!$B:$B,'[1]Baseline 2025'!$E:$E) -> Short Haul | K16: =_xlfn.XLOOKUP(B16,'[1]Baseline 2025'!$B:$B,'[1]Baseline 2025'!$I:$I)/100 -> 17767.204 | L16: =K16*100 -> 1776720.4 | M16: =1.3 -> 1.3 | N16: =(L16*M16)/1000 -> 2309.7365 | O16: =9/1000 -> 0.009 | P16: =(O16*L16)/1000 -> 15.990484 | Q16: =0.03/1000 -> 3e-05 | R16: =Q16*L16/1000 -> 0.053301612 | S16: 100 | T16: =G16*S16*assumptions!$D$6 -> 30940 | U16: 10.9 | V16: 0.059027778 | W16: 2440.55 | X16: =W16*assumptions!$C$8 -> 4392.99 | Y16: 2 | Z16: 3 | AA16: 65 | AB16: 3.5 | AC16: 639 | AD16: 5738 | AE16: 11360 | AF16: 2840 | AG16: 888 | AH16: 2550 | AI16: 1999 | AJ16: =X16+AC16+AD16+AE16+AF16+AG16+AH16+AI16 -> 30406.99 | AK16: 5525 | AL16: 38150 | AM16: =AK16+AL16 -> 43675 | AN16: =(AM16/AJ16)-1 -> 0.43634737
B17: 11 OSL | C17: Fokker 100 | D17: SAF | E17: =7*52 -> 364 | F17: =E17/2 -> 182 | G17: =E17 -> 364 | H17: =_xlfn.XLOOKUP(B17,'[1]Baseline 2025'!$B:$B,'[1]Baseline 2025'!$C:$C) -> 961 | I17: =E17*H17 -> 349804 | J17: =_xlfn.XLOOKUP(B17,'[1]Baseline 2025'!$B:$B,'[1]Baseline 2025'!$E:$E) -> Short Haul | K17: =_xlfn.XLOOKUP(B17,'[1]Baseline 2025'!$B:$B,'[1]Baseline 2025'!$I:$I)/100 -> 25675.614 | L17: =K17*100 -> 2567561.4 | M17: =1.3 -> 1.3 | N17: =(L17*M17)/1000 -> 3337.8298 | O17: =9/1000 -> 0.009 | P17: =(O17*L17)/1000 -> 23.108052 | Q17: =0.03/1000 -> 3e-05 | R17: =Q17*L17/1000 -> 0.077026841 | S17: 100 | T17: =G17*S17*assumptions!$D$6 -> 30940 | U17: 10.9 | V17: 0.072916667 | W17: 3526.87 | X17: =W17*assumptions!$C$8 -> 6348.366 | Y17: 2 | Z17: 3 | AA17: 70 | AB17: 3.5 | AC17: 787.5 | AD17: 5867 | AE17: 14000 | AF17: 3500 | AG17: 1094 | AH17: 2550 | AI17: 2440 | AJ17: =X17+AC17+AD17+AE17+AF17+AG17+AH17+AI17 -> 36586.866 | AK17: 5950 | AL17: 38150 | AM17: =AK17+AL17 -> 44100 | AN17: =(AM17/AJ17)-1 -> 0.20535058
B18: 12 PMI | C18: Fokker 100 | D18: SAF | E18: =7*52 -> 364 | F18: =E18/2 -> 182 | G18: =E18 -> 364 | H18: =_xlfn.XLOOKUP(B18,'[1]Baseline 2025'!$B:$B,'[1]Baseline 2025'!$C:$C) -> 1426 | I18: =E18*H18 -> 519064 | J18: =_xlfn.XLOOKUP(B18,'[1]Baseline 2025'!$B:$B,'[1]Baseline 2025'!$E:$E) -> Short Haul | K18: =_xlfn.XLOOKUP(B18,'[1]Baseline 2025'!$B:$B,'[1]Baseline 2025'!$I:$I)/100 -> 38099.298 | L18: =K18*100 -> 3809929.8 | M18: =1.3 -> 1.3 | N18: =(L18*M18)/1000 -> 4952.9087 | O18: =9/1000 -> 0.009 | P18: =(O18*L18)/1000 -> 34.289368 | Q18: =0.03/1000 -> 3e-05 | R18: =Q18*L18/1000 -> 0.11429789 | S18: 100 | T18: =G18*S18*assumptions!$D$6 -> 30940 | U18: 10.9 | V18: 0.10069444 | W18: 5233.42 | X18: =W18*assumptions!$C$8 -> 9420.156 | Y18: 2 | Z18: 3 | AA18: 170 | AB18: 3.5 | AC18: 1089 | AD18: 6564 | AE18: 19360 | AF18: 4840 | AG18: 1513 | AH18: 2550 | AI18: 3239 | AJ18: =X18+AC18+AD18+AE18+AF18+AG18+AH18+AI18 -> 48575.156 | AK18: 14450 | AL18: 38150 | AM18: =AK18+AL18 -> 52600 | AN18: =(AM18/AJ18)-1 -> 0.082858077
B19: 13 VIE | C19: Fokker 100 | D19: SAF | E19: =7*52 -> 364 | F19: =E19/2 -> 182 | G19: =E19 -> 364 | H19: =_xlfn.XLOOKUP(B19,'[1]Baseline 2025'!$B:$B,'[1]Baseline 2025'!$C:$C) -> 962 | I19: =E19*H19 -> 350168 | J19: =_xlfn.XLOOKUP(B19,'[1]Baseline 2025'!$B:$B,'[1]Baseline 2025'!$E:$E) -> Short Haul | K19: =_xlfn.XLOOKUP(B19,'[1]Baseline 2025'!$B:$B,'[1]Baseline 2025'!$I:$I)/100 -> 25702.331 | L19: =K19*100 -> 2570233.1 | M19: =1.3 -> 1.3 | N19: =(L19*M19)/1000 -> 3341.3031 | O19: =9/1000 -> 0.009 | P19: =(O19*L19)/1000 -> 23.132098 | Q19: =0.03/1000 -> 3e-05 | R19: =Q19*L19/1000 -> 0.077106994 | S19: 100 | T19: =G19*S19*assumptions!$D$6 -> 30940 | U19: 10.9 | V19: 0.072916667 | W19: 3530.54 | X19: =W19*assumptions!$C$8 -> 6354.972 | Y19: 2 | Z19: 3 | AA19: 80.6 | AB19: 3.5 | AC19: 787.5 | AD19: 5868 | AE19: 14000 | AF19: 3500 | AG19: 1094 | AH19: 2550 | AI19: 2441 | AJ19: =X19+AC19+AD19+AE19+AF19+AG19+AH19+AI19 -> 36595.472 | AK19: 6851 | AL19: 38150 | AM19: =AK19+AL19 -> 45001 | AN19: =(AM19/AJ19)-1 -> 0.22968765
B20: 14 WAW | C20: Fokker 100 | D20: SAF | E20: =7*52 -> 364 | F20: =E20/2 -> 182 | G20: =E20 -> 364 | H20: =_xlfn.XLOOKUP(B20,'[1]Baseline 2025'!$B:$B,'[1]Baseline 2025'!$C:$C) -> 1105 | I20: =E20*H20 -> 402220 | J20: =_xlfn.XLOOKUP(B20,'[1]Baseline 2025'!$B:$B,'[1]Baseline 2025'!$E:$E) -> Short Haul | K20: =_xlfn.XLOOKUP(B20,'[1]Baseline 2025'!$B:$B,'[1]Baseline 2025'!$I:$I)/100 -> 29522.948 | L20: =K20*100 -> 2952294.8 | M20: =1.3 -> 1.3 | N20: =(L20*M20)/1000 -> 3837.9832 | O20: =9/1000 -> 0.009 | P20: =(O20*L20)/1000 -> 26.570653 | Q20: =0.03/1000 -> 3e-05 | R20: =Q20*L20/1000 -> 0.088568844 | S20: 100 | T20: =G20*S20*assumptions!$D$6 -> 30940 | U20: 10.9 | V20: 0.079861111 | W20: 4055.35 | X20: =W20*assumptions!$C$8 -> 7299.63 | Y20: 2 | Z20: 3 | AA20: 87.75 | AB20: 3.5 | AC20: 859.5 | AD20: 6083 | AE20: 15280 | AF20: 3820 | AG20: 1194 | AH20: 2550 | AI20: 2650 | AJ20: =X20+AC20+AD20+AE20+AF20+AG20+AH20+AI20 -> 39736.13 | AK20: 7458.75 | AL20: 38150 | AM20: =AK20+AL20 -> 45608.75 | AN20: =(AM20/AJ20)-1 -> 0.14779044
B21: 15 ZRH | C21: Fokker 100 | D21: SAF | E21: =14*52*2 -> 1456 | F21: =E21/2 -> 728 | G21: =E21 -> 1456 | H21: =_xlfn.XLOOKUP(B21,'[1]Baseline 2025'!$B:$B,'[1]Baseline 2025'!$C:$C) -> 603 | I21: =E21*H21 -> 877968 | J21: =_xlfn.XLOOKUP(B21,'[1]Baseline 2025'!$B:$B,'[1]Baseline 2025'!$E:$E) -> Short Haul | K21: =_xlfn.XLOOKUP(B21,'[1]Baseline 2025'!$B:$B,'[1]Baseline 2025'!$I:$I)/100 -> 32221.426 | L21: =K21*100 -> 3222142.6 | M21: =1.3 -> 1.3 | N21: =(L21*M21)/1000 -> 4188.7853 | O21: =9/1000 -> 0.009 | P21: =(O21*L21)/1000 -> 28.999283 | Q21: =0.03/1000 -> 3e-05 | R21: =Q21*L21/1000 -> 0.096664277 | S21: 100 | T21: =G21*S21*assumptions!$D$6 -> 123760 | U21: 10.9 | V21: 0.059027778 | W21: 2213.01 | X21: =W21*assumptions!$C$8 -> 3983.418 | Y21: 2 | Z21: 3 | AA21: 65 | AB21: 3.5 | AC21: 634.5 | AD21: 5330 | AE21: 11280 | AF21: 2820 | AG21: 881 | AH21: 2550 | AI21: 1964 | AJ21: =X21+AC21+AD21+AE21+AF21+AG21+AH21+AI21 -> 29442.918 | AK21: 4250 | AL21: 38150 | AM21: =AK21+AL21 -> 42400 | AN21: =(AM21/AJ21)-1 -> 0.44007466
B22: 16 BKK | C22: B777-200er | D22: SAF | E22: =3*52*2 -> 312 | F22: =E22/2 -> 156 | G22: =E22 -> 312 | H22: =_xlfn.XLOOKUP(B22,'[1]Baseline 2025'!$B:$B,'[1]Baseline 2025'!$C:$C) -> 9217 | I22: =E22*H22 -> 2875704 | J22: =_xlfn.XLOOKUP(B22,'[1]Baseline 2025'!$B:$B,'[1]Baseline 2025'!$E:$E) -> Long Haul | K22: =_xlfn.XLOOKUP(B22,'[1]Baseline 2025'!$B:$B,'[1]Baseline 2025'!$I:$I)/100 -> 213377.24 | L22: =K22*100 -> 21337724 | M22: =1.3 -> 1.3 | N22: =(L22*M22)/1000 -> 27739.041 | O22: =9/1000 -> 0.009 | P22: =(O22*L22)/1000 -> 192.03951 | Q22: =0.03/1000 -> 3e-05 | R22: =Q22*L22/1000 -> 0.64013171 | S22: 300 | T22: =G22*S22*assumptions!$D$6 -> 79560 | U22: 20 | V22: 0.46875 | W22: 68390.14 | X22: =W22*assumptions!$C$8 -> 123102.25 | Y22: 3 | Z22: 12 | AA22: 1200 | AB22: 3.5 | AC22: 11812.5 | AD22: 27101 | AE22: 90000 | AF22: 22500 | AG22: 21094 | AH22: 7650 | AI22: 21743 | AJ22: =X22+AC22+AD22+AE22+AF22+AG22+AH22+AI22 -> 325002.75 | AK22: 273360 | AL22: 70000 | AM22: =AK22+AL22 -> 343360 | AN22: =(AM22/AJ22)-1 -> 0.056483362
B23: 17 MFM | C23: B777-200er | D23: SAF | E23: =3*52*2 -> 312 | F23: =E23/2 -> 156 | G23: =E23 -> 312 | H23: =_xlfn.XLOOKUP(B23,'[1]Baseline 2025'!$B:$B,'[1]Baseline 2025'!$C:$C) -> 9285 | I23: =E23*H23 -> 2896920 | J23: =_xlfn.XLOOKUP(B23,'[1]Baseline 2025'!$B:$B,'[1]Baseline 2025'!$E:$E) -> Long Haul | K23: =_xlfn.XLOOKUP(B23,'[1]Baseline 2025'!$B:$B,'[1]Baseline 2025'!$I:$I)/100 -> 214951.46 | L23: =K23*100 -> 21495146 | M23: =1.3 -> 1.3 | N23: =(L23*M23)/1000 -> 27943.69 | O23: =9/1000 -> 0.009 | P23: =(O23*L23)/1000 -> 193.45632 | Q23: =0.03/1000 -> 3e-05 | R23: =Q23*L23/1000 -> 0.64485439 | S23: 300 | T23: =G23*S23*assumptions!$D$6 -> 79560 | U23: 20 | V23: 0.46875 | W23: 68894.7 | X23: =W23*assumptions!$C$8 -> 124010.46 | Y23: 3 | Z23: 12 | AA23: 1072 | AB23: 3.5 | AC23: 11812.5 | AD23: 27203 | AE23: 90000 | AF23: 22500 | AG23: 21094 | AH23: 7650 | AI23: 21743 | AJ23: =X23+AC23+AD23+AE23+AF23+AG23+AH23+AI23 -> 326012.96 | AK23: 273360 | AL23: 70000 | AM23: =AK23+AL23 -> 343360 | AN23: =(AM23/AJ23)-1 -> 0.053209664
B24: 18 HAN | C24: B777-200er | D24: SAF | E24: =52*2 -> 104 | F24: =E24/2 -> 52 | G24: =E24 -> 104 | H24: =_xlfn.XLOOKUP(B24,'[1]Baseline 2025'!$B:$B,'[1]Baseline 2025'!$C:$C) -> 8886 | I24: =E24*H24 -> 924144 | J24: =_xlfn.XLOOKUP(B24,'[1]Baseline 2025'!$B:$B,'[1]Baseline 2025'!$E:$E) -> Long Haul | K24: =_xlfn.XLOOKUP(B24,'[1]Baseline 2025'!$B:$B,'[1]Baseline 2025'!$I:$I)/100 -> 68571.485 | L24: =K24*100 -> 6857148.5 | M24: =1.3 -> 1.3 | N24: =(L24*M24)/1000 -> 8914.293 | O24: =9/1000 -> 0.009 | P24: =(O24*L24)/1000 -> 61.714336 | Q24: =0.03/1000 -> 3e-05 | R24: =Q24*L24/1000 -> 0.20571445 | S24: 300 | T24: =G24*S24*assumptions!$D$6 -> 26520 | U24: 20 | V24: 0.45833333 | W24: 65934.12 | X24: =W24*assumptions!$C$8 -> 118681.42 | Y24: 3 | Z24: 12 | AA24: 1031 | AB24: 3.5 | AC24: 11550 | AD24: 26604 | AE24: 88000 | AF24: 22000 | AG24: 20625 | AH24: 7650 | AI24: 21087 | AJ24: =X24+AC24+AD24+AE24+AF24+AG24+AH24+AI24 -> 316197.42 | AK24: 262905 | AL24: 70000 | AM24: =AK24+AL24 -> 332905 | AN24: =(AM24/AJ24)-1 -> 0.052839091
B25: 19 PTY | C25: B777-200er | D25: SAF | E25: =156*2 -> 312 | F25: =E25/2 -> 156 | G25: =E25 -> 312 | H25: =_xlfn.XLOOKUP(B25,'[1]Baseline 2025'!$B:$B,'[1]Baseline 2025'!$C:$C) -> 8818 | I25: =E25*H25 -> 2751216 | J25: =_xlfn.XLOOKUP(B25,'[1]Baseline 2025'!$B:$B,'[1]Baseline 2025'!$E:$E) -> Long Haul | K25: =_xlfn.XLOOKUP(B25,'[1]Baseline 2025'!$B:$B,'[1]Baseline 2025'!$I:$I)/100 -> 204140.23 | L25: =K25*100 -> 20414023 | M25: =1.3 -> 1.3 | N25: =(L25*M25)/1000 -> 26538.23 | O25: =9/1000 -> 0.009 | P25: =(O25*L25)/1000 -> 183.7262 | Q25: =0.03/1000 -> 3e-05 | R25: =Q25*L25/1000 -> 0.61242068 | S25: 300 | T25: =G25*S25*assumptions!$D$6 -> 79560 | U25: 20 | V25: 0.46527778 | W25: 65429.56 | X25: =W25*assumptions!$C$8 -> 117773.21 | Y25: 3 | Z25: 12 | AA25: 1036 | AB25: 3.5 | AC25: 11728.5 | AD25: 26502 | AE25: 89360 | AF25: 22340 | AG25: 20944 | AH25: 7650 | AI25: 21172 | AJ25: =X25+AC25+AD25+AE25+AF25+AG25+AH25+AI25 -> 317469.71 | AK25: 264180 | AL25: 70000 | AM25: =AK25+AL25 -> 334180 | AN25: =(AM25/AJ25)-1 -> 0.052635863
B26: 20 MEX | C26: B777-200er | D26: SAF | E26: =156*2 -> 312 | F26: =E26/2 -> 156 | G26: =E26 -> 312 | H26: =_xlfn.XLOOKUP(B26,'[1]Baseline 2025'!$B:$B,'[1]Baseline 2025'!$C:$C) -> 9220 | I26: =E26*H26 -> 2876640 | J26: =_xlfn.XLOOKUP(B26,'[1]Baseline 2025'!$B:$B,'[1]Baseline 2025'!$E:$E) -> Long Haul | K26: =_xlfn.XLOOKUP(B26,'[1]Baseline 2025'!$B:$B,'[1]Baseline 2025'!$I:$I)/100 -> 213446.69 | L26: =K26*100 -> 21344669 | M26: =1.3 -> 1.3 | N26: =(L26*M26)/1000 -> 27748.069 | O26: =9/1000 -> 0.009 | P26: =(O26*L26)/1000 -> 192.10202 | Q26: =0.03/1000 -> 3e-05 | R26: =Q26*L26/1000 -> 0.64034006 | S26: 300 | T26: =G26*S26*assumptions!$D$6 -> 79560 | U26: 20 | V26: 0.47916667 | W26: 68412.4 | X26: =W26*assumptions!$C$8 -> 123142.32 | Y26: 3 | Z26: 12 | AA26: 1081 | AB26: 3.5 | AC26: 12075 | AD26: 27105 | AE26: 92000 | AF26: 23000 | AG26: 21563 | AH26: 7650 | AI26: 21903 | AJ26: =X26+AC26+AD26+AE26+AF26+AG26+AH26+AI26 -> 328438.32 | AK26: 275655 | AL26: 70000 | AM26: =AK26+AL26 -> 345655 | AN26: =(AM26/AJ26)-1 -> 0.052419827
B27: 21 GIG | C27: B777-200er | D27: SAF | E27: =52*2 -> 104 | F27: =E27/2 -> 52 | G27: =E27 -> 104 | H27: =_xlfn.XLOOKUP(B27,'[1]Baseline 2025'!$B:$B,'[1]Baseline 2025'!$C:$C) -> 9536 | I27: =E27*H27 -> 991744 | J27: =_xlfn.XLOOKUP(B27,'[1]Baseline 2025'!$B:$B,'[1]Baseline 2025'!$E:$E) -> Long Haul | K27: =_xlfn.XLOOKUP(B27,'[1]Baseline 2025'!$B:$B,'[1]Baseline 2025'!$I:$I)/100 -> 73587.405 | L27: =K27*100 -> 7358740.5 | M27: =1.3 -> 1.3 | N27: =(L27*M27)/1000 -> 9566.3626 | O27: =9/1000 -> 0.009 | P27: =(O27*L27)/1000 -> 66.228664 | Q27: =0.03/1000 -> 3e-05 | R27: =Q27*L27/1000 -> 0.22076221 | S27: 300 | T27: =G27*S27*assumptions!$D$6 -> 26520 | U27: 20 | V27: 0.5 | W27: 70757.12 | X27: =W27*assumptions!$C$8 -> 127362.82 | Y27: 3 | Z27: 12 | AA27: 1130 | AB27: 3.5 | AC27: 12600 | AD27: 27579 | AE27: 96000 | AF27: 24000 | AG27: 22500 | AH27: 7650 | AI27: 22701 | AJ27: =X27+AC27+AD27+AE27+AF27+AG27+AH27+AI27 -> 340392.82 | AK27: 288150 | AL27: 70000 | AM27: =AK27+AL27 -> 358150 | AN27: 0.05
B28: 22 CPT | C28: B777-200er | D28: SAF | E28: =156*2 -> 312 | F28: =E28/2 -> 156 | G28: =E28 -> 312 | H28: =_xlfn.XLOOKUP(B28,'[1]Baseline 2025'!$B:$B,'[1]Baseline 2025'!$C:$C) -> 9652 | I28: =E28*H28 -> 3011424 | J28: =_xlfn.XLOOKUP(B28,'[1]Baseline 2025'!$B:$B,'[1]Baseline 2025'!$E:$E) -> Long Haul | K28: =_xlfn.XLOOKUP(B28,'[1]Baseline 2025'!$B:$B,'[1]Baseline 2025'!$I:$I)/100 -> 223447.66 | L28: =K28*100 -> 22344766 | M28: =1.3 -> 1.3 | N28: =(L28*M28)/1000 -> 29048.196 | O28: =9/1000 -> 0.009 | P28: =(O28*L28)/1000 -> 201.10289 | Q28: =0.03/1000 -> 3e-05 | R28: =Q28*L28/1000 -> 0.67034298 | S28: 300 | T28: =G28*S28*assumptions!$D$6 -> 79560 | U28: 20 | V28: 0.47222222 | W28: 71617.84 | X28: =W28*assumptions!$C$8 -> 128912.11 | Y28: 3 | Z28: 12 | AA28: 1100 | AB28: 3.5 | AC28: 11896.5 | AD28: 27753 | AE28: 90640 | AF28: 22660 | AG28: 21244 | AH28: 7650 | AI28: 22205 | AJ28: =X28+AC28+AD28+AE28+AF28+AG28+AH28+AI28 -> 332960.61 | AK28: 280500 | AL28: 70000 | AM28: =AK28+AL28 -> 350500 | AN28: =(AM28/AJ28)-1 -> 0.052677066
N29: =SUM(N7:N28) -> 213699.15 | P29: =SUM(P7:P28) -> 1479.4557 | R29: =SUM(R7:R28) -> 4.931519
A30: yearly fuel ussage [tons] | D30: yearly costs | F30: yearly revenue
A31: =(E7*W7)/1000 -> 4309.5489 | D31: =E7*AJ7 -> 38705560 | F31: =E7*AM7 -> 40768000
A32: =(E8*W8)/1000 -> 3085.8828 | D32: =E8*AJ8 -> 30015389 | F32: =E8*AM8 -> 31602480 | AA32: =(249/308) -> 0.80844156
A33: =(E9*W9)/1000 -> 3315.6542 | D33: =E9*AJ9 -> 33415597 | F33: =E9*AM9 -> 35198800
A34: =(E10*W10)/1000 -> 422.13808 | D34: =E10*AJ10 -> 12141401 | F34: =E10*AM10 -> 30867200
A35: =(E11*W11)/1000 -> 1498.8574 | D35: =E11*AJ11 -> 20477523 | F35: =E11*AM11 -> 31486000
A36: =(E12*W12)/1000 -> 533.01612 | D36: =E12*AJ12 -> 9726187 | F36: =E12*AM12 -> 15743000
A37: =(E13*W13)/1000 -> 1005.9176 | D37: =E13*AJ13 -> 12271284 | F37: =E13*AM13 -> 15959580
A38: =(E14*W14)/1000 -> 2631.6836 | D38: =E14*AJ14 -> 21916374 | F38: =E14*AM14 -> 22704500
A39: =(E15*W15)/1000 -> 2468.7062 | D39: =E15*AJ15 -> 22240723 | F39: =E15*AM15 -> 23416120
A40: =(E16*W16)/1000 -> 888.3602 | D40: =E16*AJ16 -> 11068144 | F40: =E16*AM16 -> 15897700
A41: =(E17*W17)/1000 -> 1283.7807 | D41: =E17*AJ17 -> 13317619 | F41: =E17*AM17 -> 16052400
A42: =(E18*W18)/1000 -> 1904.9649 | D42: =E18*AJ18 -> 17681357 | F42: =E18*AM18 -> 19146400
A43: =(E19*W19)/1000 -> 1285.1166 | D43: =E19*AJ19 -> 13320752 | F43: =E19*AM19 -> 16380364
A44: =(E20*W20)/1000 -> 1476.1474 | D44: =E20*AJ20 -> 14463951 | F44: =E20*AM20 -> 16601585
... A52: =(E28*W28)/1000 -> 22344.766 | D52: =E28*AJ28 -> 1.0388371e+08 | F52: =E28*AM28 -> 109356000
A54: sum | D54: sum | F54: sum
A55: =SUM(A31:A52) -> 150484.13 | D55: =SUM(D31:D52) -> 8.9044005e+08 | F55: =SUM(F31:F52) -> 1001149409

Sheet Scenario 1 2050
A4: 100% SAF
Y5: Crew costs | AG5: Costs | AM5: Revenu
B6: Destination | C6: Aircraft | D6: Fuel type | E6: Frequency [per year] | F6: # retour | G6: # flights | H6: Lookup: Distance [km] | I6: Total distance travelled [km] | J6: Lookup: Flight Type | K6: Lookup: fuel consumption [l/100km] | L6: Conditional: Total fuel consumption [l] | M6: SAF LFEC CO2 per kg [kg/kg] | N6: Total CO2 emmission [kg] (tons) | O6: NOX per KG | P6: Total NOX emmision(Tons) | Q6: Sox per KG | R6: Total Sox emmission(Ton) | S6: Seats | T6: Passengers per year | U6: Available cargo (Tons) | V6: Flight time | W6: Fuel | X6: HEFA | Y6: Pilot | Z6: Cabin crew | AA6: Ticket price | AB6: Freight rate (Euro/KG) | AC6: CO2 Price(KG/TON) | AD6: Crew costs | AE6: Airport & Navigation charges | AF6: Maintenance costs | AG6: Maintenance reserve | AH6: Operational lease | AI6: catering and inflight services | AJ6: Insurance and overhead | AK6: Total costs | AL6: Passenger revenue | AM6: Cargo revenue | AN6: Total revenuee
B7: 1 ALC | C7: Fokker 100 | D7: SAF | E7: =7*52*2 -> 728 | F7: =E7/2 -> 364 | G7: =E7 -> 728 | H7: =_xlfn.XLOOKUP(B7,'[1]Baseline 2025'!$B:$B,'[1]Baseline 2025'!$C:$C) -> 1613 | I7: =E7*H7 -> 1174264 | J7: =_xlfn.XLOOKUP(B7,'[1]Baseline 2025'!$B:$B,'[1]Baseline 2025'!$E:$E) -> Short Haul | K7: =_xlfn.XLOOKUP(B7,'[1]Baseline 2025'!$B:$B,'[1]Baseline 2025'!$I:$I)/100 -> 43095.489 | L7: =K7*100 -> 4309548.9 | M7: =1.3 -> 1.3 | N7: =(L7*M7)/1000 -> 5602.4135 | O7: =9/1000 -> 0.009 | P7: =(O7*L7)/1000 -> 38.78594 | Q7: =0.03/1000 -> 3e-05 | R7: =Q7*L7/1000 -> 0.12928647 | S7: 100 | T7: =G7*S7*assumptions!$D$6 -> 61880 | U7: 10.9 | V7: 0.11111111 | W7: 5919.71 | X7: =W7*assumptions!$D$8 -> 7695.623 | Y7: 2 | Z7: 3 | AA7: 210 | AB7: 3.5 | AC7: 1859 | AD7: 1201.5 | AE7: 6845 | AF7: 21360 | AG7: 5340 | AH7: 1669 | AI7: 2550 | AJ7: 3546 | AK7: =X7+AD7+AE7+AF7+AG7+AH7+AI7+AJ7+AC7 -> 52066.123 | AL7: 17850 | AM7: 38150 | AN7: =AL7+AM7 -> 56000
B8: 2 ARN | C8: Fokker 100 | D8: SAF | E8: =7*52*2 -> 728 | F8: =E8/2 -> 364 | G8: =E8 -> 728 | H8: =_xlfn.XLOOKUP(B8,'[1]Baseline 2025'!$B:$B,'[1]Baseline 2025'!$C:$C) -> 1155 | I8: =E8*H8 -> 840840 | J8: =_xlfn.XLOOKUP(B8,'[1]Baseline 2025'!$B:$B,'[1]Baseline 2025'!$E:$E) -> Short Haul | K8: =_xlfn.XLOOKUP(B8,'[1]Baseline 2025'!$B:$B,'[1]Baseline 2025'!$I:$I)/100 -> 30858.828 | L8: =K8*100 -> 3085882.8 | M8: =1.3 -> 1.3 | N8: =(L8*M8)/1000 -> 4011.6476 | O8: =9/1000 -> 0.009 | P8: =(O8*L8)/1000 -> 27.772945 | Q8: =0.03/1000 -> 3e-05 | R8: =Q8*L8/1000 -> 0.092576484 | S8: 100 | T8: =G8*S8*assumptions!$D$6 -> 61880 | U8: 10.9 | V8: 0.083333333 | W8: 4238.85 | X8: =W8*assumptions!$D$8 -> 5510.505 | Y8: 2 | Z8: 3 | AA8: 126 | AB8: 3 | AC8: 1331 | AD8: 900 | AE8: 6158 | AF8: 16000 | AG8: 4000 | AH8: 1250 | AI8: 2550 | AJ8: 2750 | AK8: =X8+AD8+AE8+AF8+AG8+AH8+AI8+AJ8+AC8 -> 40449.505 | AL8: 10710 | AM8: 32700 | AN8: =AL8+AM8 -> 43410
B9: 3 BCN | C9: Fokker 100 | D9: SAF | E9: =7*52*2 -> 728 | F9: =E9/2 -> 364 | G9: =E9 -> 728 | H9: =_xlfn.XLOOKUP(B9,'[1]Baseline 2025'!$B:$B,'[1]Baseline 2025'!$C:$C) -> 1241 | I9: =E9*H9 -> 903448 | J9: =_xlfn.XLOOKUP(B9,'[1]Baseline 2025'!$B:$B,'[1]Baseline 2025'!$E:$E) -> Short Haul | K9: =_xlfn.XLOOKUP(B9,'[1]Baseline 2025'!$B:$B,'[1]Baseline 2025'!$I:$I)/100 -> 33156.542 | L9: =K9*100 -> 3315654.2 | M9: =1.3 -> 1.3 | N9: =(L9*M9)/1000 -> 4310.3504 | O9: =9/1000 -> 0.009 | P9: =(O9*L9)/1000 -> 29.840887 | Q9: =0.03/1000 -> 3e-05 | R9: =Q9*L9/1000 -> 0.099469625 | S9: 100 | T9: =G9*S9*assumptions!$D$6 -> 61880 | U9: 10.9 | V9: 0.097222222 | W9: 4554.47 | X9: =W9*assumptions!$D$8 -> 5920.811 | Y9: 2 | Z9: 3 | AA9: 120 | AB9: 3.5 | AC9: 1430 | AD9: 1048.5 | AE9: 6287 | AF9: 18640 | AG9: 4660 | AH9: 1456 | AI9: 2550 | AJ9: 3061 | AK9: =X9+AD9+AE9+AF9+AG9+AH9+AI9+AJ9+AC9 -> 45053.311 | AL9: 10200 | AM9: 38150 | AN9: =AL9+AM9 -> 48350
B10: 4 BRU | C10: Fokker 100 | D10: SAF | E10: =14*52 -> 728 | F10: =E10/2 -> 364 | G10: =E10 -> 728 | H10: =_xlfn.XLOOKUP(B10,'[1]Baseline 2025'!$B:$B,'[1]Baseline 2025'!$C:$C) -> 158 | I10: =E10*H10 -> 115024 | J10: =_xlfn.XLOOKUP(B10,'[1]Baseline 2025'!$B:$B,'[1]Baseline 2025'!$E:$E) -> Short Haul | K10: =_xlfn.XLOOKUP(B10,'[1]Baseline 2025'!$B:$B,'[1]Baseline 2025'!$I:$I)/100 -> 8442.7616 | L10: =K10*100 -> 844276.16 | M10: =1.3 -> 1.3 | N10: =(L10*M10)/1000 -> 1097.559 | O10: =9/1000 -> 0.009 | P10: =(O10*L10)/1000 -> 7.5984854 | Q10: =0.03/1000 -> 3e-05 | R10: =Q10*L10/1000 -> 0.025328285 | S10: 100 | T10: =G10*S10*assumptions!$D$6 -> 61880 | U10: 10.9 | V10: 0.027777778 | W10: 579.86 | X10: =W10*assumptions!$D$8 -> 753.818 | Y10: 2 | Z10: 3 | AA10: 50 | AB10: 3.5 | AC10: 182 | AD10: 302 | AE10: 4662 | AF10: 5360 | AG10: 1340 | AH10: 419 | AI10: 2550 | AJ10: 1120 | AK10: =X10+AD10+AE10+AF10+AG10+AH10+AI10+AJ10+AC10 -> 16688.818 | AL10: 4250 | AM10: 38150 | AN10: =AL10+AM10 -> 42400
B11: 5 BSL | C11: Fokker 100 | D11: SAF | E11: =7*52*2 -> 728 | F11: =E11/2 -> 364 | G11: =E11 -> 728 | H11: =_xlfn.XLOOKUP(B11,'[1]Baseline 2025'!$B:$B,'[1]Baseline 2025'!$C:$C) -> 561 | I11: =E11*H11 -> 408408 | J11: =_xlfn.XLOOKUP(B11,'[1]Baseline 2025'!$B:$B,'[1]Baseline 2025'!$E:$E) -> Short Haul | K11: =_xlfn.XLOOKUP(B11,'[1]Baseline 2025'!$B:$B,'[1]Baseline 2025'!$I:$I)/100 -> 14988.574 | L11: =K11*100 -> 1498857.4 | M11: =1.3 -> 1.3 | N11: =(L11*M11)/1000 -> 1948.5146 | O11: =9/1000 -> 0.009 | P11: =(O11*L11)/1000 -> 13.489716 | Q11: =0.03/1000 -> 3e-05 | R11: =Q11*L11/1000 -> 0.044965721 | S11: 100 | T11: =G11*S11*assumptions!$D$6 -> 61880 | U11: 10.9 | V11: 0.055555556 | W11: 2058.87 | X11: =W11*assumptions!$D$8 -> 2676.531 | Y11: 2 | Z11: 3 | AA11: 60 | AB11: 3.5 | AC11: 647 | AD11: 598.5 | AE11: 5267 | AF11: 10640 | AG11: 2660 | AH11: 831 | AI11: 2550 | AJ11: 1876 | AK11: =X11+AD11+AE11+AF11+AG11+AH11+AI11+AJ11+AC11 -> 27746.031 | AL11: 5100 | AM11: 38150 | AN11: =AL11+AM11 -> 43250
B12: 6 CDG | C12: Fokker 100 | D12: SAF | E12: =7*52 -> 364 | F12: =E12/2 -> 182 | G12: =E12 -> 364 | H12: =_xlfn.XLOOKUP(B12,'[1]Baseline 2025'!$B:$B,'[1]Baseline 2025'!$C:$C) -> 399 | I12: =E12*H12 -> 145236 | J12: =_xlfn.XLOOKUP(B12,'[1]Baseline 2025'!$B:$B,'[1]Baseline 2025'!$E:$E) -> Short Haul | K12: =_xlfn.XLOOKUP(B12,'[1]Baseline 2025'!$B:$B,'[1]Baseline 2025'!$I:$I)/100 -> 10660.322 | L12: =K12*100 -> 1066032.2 | M12: =1.3 -> 1.3 | N12: =(L12*M12)/1000 -> 1385.8419 | O12: =9/1000 -> 0.009 | P12: =(O12*L12)/1000 -> 9.5942902 | Q12: =0.03/1000 -> 3e-05 | R12: =Q12*L12/1000 -> 0.031980967 | S12: 100 | T12: =G12*S12*assumptions!$D$6 -> 30940 | U12: 10.9 | V12: 0.055555556 | W12: 1464.33 | X12: =W12*assumptions!$D$8 -> 1903.629 | Y12: 2 | Z12: 3 | AA12: 60 | AB12: 3.5 | AC12: 460 | AD12: 598.5 | AE12: 5024 | AF12: 10640 | AG12: 2660 | AH12: 831 | AI12: 2550 | AJ12: 1781 | AK12: =X12+AD12+AE12+AF12+AG12+AH12+AI12+AJ12+AC12 -> 26448.129 | AL12: 5100 | AM12: 38150 | AN12: =AL12+AM12 -> 43250
B13: 7 DUB | C13: Fokker 100 | D13: SAF | E13: =7*52 -> 364 | F13: =E13/2 -> 182 | G13: =E13 -> 364 | H13: =_xlfn.XLOOKUP(B13,'[1]Baseline 2025'!$B:$B,'[1]Baseline 2025'!$C:$C) -> 753 | I13: =E13*H13 -> 274092 | J13: =_xlfn.XLOOKUP(B13,'[1]Baseline 2025'!$B:$B,'[1]Baseline 2025'!$E:$E) -> Short Haul | K13: =_xlfn.XLOOKUP(B13,'[1]Baseline 2025'!$B:$B,'[1]Baseline 2025'!$I:$I)/100 -> 20118.353 | L13: =K13*100 -> 2011835.3 | M13: =1.3 -> 1.3 | N13: =(L13*M13)/1000 -> 2615.3859 | O13: =9/1000 -> 0.009 | P13: =(O13*L13)/1000 -> 18.106518 | Q13: =0.03/1000 -> 3e-05 | R13: =Q13*L13/1000 -> 0.060355058 | S13: 100 | T13: =G13*S13*assumptions!$D$6 -> 30940 | U13: 10.9 | V13: 0.069444444 | W13: 2763.51 | X13: =W13*assumptions!$D$8 -> 3592.563 | Y13: 2 | Z13: 3 | AA13: 67 | AB13: 3.5 | AC13: 868 | AD13: 480 | AE13: 5555 | AF13: 8534 | AG13: 2133 | AH13: 667 | AI13: 2550 | AJ13: 1779 | AK13: =X13+AD13+AE13+AF13+AG13+AH13+AI13+AJ13+AC13 -> 26158.563 | AL13: 5695 | AM13: 38150 | AN13: =AL13+AM13 -> 43845
B14: 8 FAO | C14: Fokker 100 | D14: SAF | E14: =7*52 -> 364 | F14: =E14/2 -> 182 | G14: =E14 -> 364 | H14: =_xlfn.XLOOKUP(B14,'[1]Baseline 2025'!$B:$B,'[1]Baseline 2025'!$C:$C) -> 1970 | I14: =E14*H14 -> 717080 | J14: =_xlfn.XLOOKUP(B14,'[1]Baseline 2025'!$B:$B,'[1]Baseline 2025'!$E:$E) -> Short Haul | K14: =_xlfn.XLOOKUP(B14,'[1]Baseline 2025'!$B:$B,'[1]Baseline 2025'!$I:$I)/100 -> 52633.672 | L14: =K14*100 -> 5263367.2 | M14: =1.3 -> 1.3 | N14: =(L14*M14)/1000 -> 6842.3774 | O14: =9/1000 -> 0.009 | P14: =(O14*L14)/1000 -> 47.370305 | Q14: =0.03/1000 -> 3e-05 | R14: =Q14*L14/1000 -> 0.15790102 | S14: 100 | T14: =G14*S14*assumptions!$D$6 -> 30940 | U14: 10.9 | V14: 0.125 | W14: 7229.9 | X14: =W14*assumptions!$D$8 -> 9398.87 | Y14: 2 | Z14: 3 | AA14: 285 | AB14: 3.5 | AC14: 2270 | AD14: 1350 | AE14: 7380 | AF14: 24000 | AG14: 6000 | AH14: 1875 | AI14: 2550 | AJ14: 4014 | AK14: =X14+AD14+AE14+AF14+AG14+AH14+AI14+AJ14+AC14 -> 58837.87 | AL14: 24225 | AM14: 38150 | AN14: =AL14+AM14 -> 62375
B15: 9 LIS | C15: Fokker 100 | D15: SAF | E15: =7*52 -> 364 | F15: =E15/2 -> 182 | G15: =E15 -> 364 | H15: =_xlfn.XLOOKUP(B15,'[1]Baseline 2025'!$B:$B,'[1]Baseline 2025'!$C:$C) -> 1848 | I15: =E15*H15 -> 672672 | J15: =_xlfn.XLOOKUP(B15,'[1]Baseline 2025'!$B:$B,'[1]Baseline 2025'!$E:$E) -> Short Haul | K15: =_xlfn.XLOOKUP(B15,'[1]Baseline 2025'!$B:$B,'[1]Baseline 2025'!$I:$I)/100 -> 49374.125 | L15: =K15*100 -> 4937412.5 | M15: =1.3 -> 1.3 | N15: =(L15*M15)/1000 -> 6418.6362 | O15: =9/1000 -> 0.009 | P15: =(O15*L15)/1000 -> 44.436712 | Q15: =0.03/1000 -> 3e-05 | R15: =Q15*L15/1000 -> 0.14812237 | S15: 100 | T15: =G15*S15*assumptions!$D$6 -> 30940 | U15: 10.9 | V15: 0.13194444 | W15: 6782.16 | X15: =W15*assumptions!$D$8 -> 8816.808 | Y15: 2 | Z15: 3 | AA15: 308 | AB15: 3.5 | AC15: 2130 | AD15: 1425 | AE15: 7197 | AF15: 25334 | AG15: 6333 | AH15: 1979 | AI15: 2550 | AJ15: 4075 | AK15: =X15+AD15+AE15+AF15+AG15+AH15+AI15+AJ15+AC15 -> 59839.808 | AL15: 26180 | AM15: 38150 | AN15: =AL15+AM15 -> 64330
B16: 10 MUC | C16: Fokker 100 | D16: SAF | E16: =7*52 -> 364 | F16: =E16/2 -> 182 | G16: =E16 -> 364 | H16: =_xlfn.XLOOKUP(B16,'[1]Baseline 2025'!$B:$B,'[1]Baseline 2025'!$C:$C) -> 665 | I16: =E16*H16 -> 242060 | J16: =_xlfn.XLOOKUP(B16,'[1]Baseline 2025'!$B:$B,'[1]Baseline 2025'!$E:$E) -> Short Haul | K16: =_xlfn.XLOOKUP(B16,'[1]Baseline 2025'!$B:$B,'[1]Baseline 2025'!$I:$I)/100 -> 17767.204 | L16: =K16*100 -> 1776720.4 | M16: =1.3 -> 1.3 | N16: =(L16*M16)/1000 -> 2309.7365 | O16: =9/1000 -> 0.009 | P16: =(O16*L16)/1000 -> 15.990484 | Q16: =0.03/1000 -> 3e-05 | R16: =Q16*L16/1000 -> 0.053301612 | S16: 100 | T16: =G16*S16*assumptions!$D$6 -> 30940 | U16: 10.9 | V16: 0.059027778 | W16: 2440.55 | X16: =W16*assumptions!$D$8 -> 3172.715 | Y16: 2 | Z16: 3 | AA16: 65 | AB16: 3.5 | AC16: 766 | AD16: 639 | AE16: 5423 | AF16: 11360 | AG16: 2840 | AH16: 888 | AI16: 2550 | AJ16: 2007 | AK16: =X16+AD16+AE16+AF16+AG16+AH16+AI16+AJ16+AC16 -> 29645.715 | AL16: 5525 | AM16: 38150 | AN16: =AL16+AM16 -> 43675
B17: 11 OSL | C17: Fokker 100 | D17: SAF | E17: =7*52 -> 364 | F17: =E17/2 -> 182 | G17: =E17 -> 364 | H17: =_xlfn.XLOOKUP(B17,'[1]Baseline 2025'!$B:$B,'[1]Baseline 2025'!$C:$C) -> 961 | I17: =E17*H17 -> 349804 | J17: =_xlfn.XLOOKUP(B17,'[1]Baseline 2025'!$B:$B,'[1]Baseline 2025'!$E:$E) -> Short Haul | K17: =_xlfn.XLOOKUP(B17,'[1]Baseline 2025'!$B:$B,'[1]Baseline 2025'!$I:$I)/100 -> 25675.614 | L17: =K17*100 -> 2567561.4 | M17: =1.3 -> 1.3 | N17: =(L17*M17)/1000 -> 3337.8298 | O17: =9/1000 -> 0.009 | P17: =(O17*L17)/1000 -> 23.108052 | Q17: =0.03/1000 -> 3e-05 | R17: =Q17*L17/1000 -> 0.077026841 | S17: 100 | T17: =G17*S17*assumptions!$D$6 -> 30940 | U17: 10.9 | V17: 0.072916667 | W17: 3526.87 | X17: =W17*assumptions!$D$8 -> 4584.931 | Y17: 2 | Z17: 3 | AA17: 70 | AB17: 3.5 | AC17: 1107 | AD17: 787.5 | AE17: 5867 | AF17: 14000 | AG17: 3500 | AH17: 1094 | AI17: 2550 | AJ17: 2440 | AK17: =X17+AD17+AE17+AF17+AG17+AH17+AI17+AJ17+AC17 -> 35930.431 | AL17: 5950 | AM17: 38150 | AN17: =AL17+AM17 -> 44100
B18: 12 PMI | C18: Fokker 100 | D18: SAF | E18: =7*52 -> 364 | F18: =E18/2 -> 182 | G18: =E18 -> 364 | H18: =_xlfn.XLOOKUP(B18,'[1]Baseline 2025'!$B:$B,'[1]Baseline 2025'!$C:$C) -> 1426 | I18: =E18*H18 -> 519064 | J18: =_xlfn.XLOOKUP(B18,'[1]Baseline 2025'!$B:$B,'[1]Baseline 2025'!$E:$E) -> Short Haul | K18: =_xlfn.XLOOKUP(B18,'[1]Baseline 2025'!$B:$B,'[1]Baseline 2025'!$I:$I)/100 -> 38099.298 | L18: =K18*100 -> 3809929.8 | M18: =1.3 -> 1.3 | N18: =(L18*M18)/1000 -> 4952.9087 | O18: =9/1000 -> 0.009 | P18: =(O18*L18)/1000 -> 34.289368 | Q18: =0.03/1000 -> 3e-05 | R18: =Q18*L18/1000 -> 0.11429789 | S18: 100 | T18: =G18*S18*assumptions!$D$6 -> 30940 | U18: 10.9 | V18: 0.10069444 | W18: 5233.42 | X18: =W18*assumptions!$D$8 -> 6803.446 | Y18: 2 | Z18: 3 | AA18: 170 | AB18: 3.5 | AC18: 1643 | AD18: 1089 | AE18: 6564 | AF18: 19360 | AG18: 4840 | AH18: 1513 | AI18: 2550 | AJ18: 3239 | AK18: =X18+AD18+AE18+AF18+AG18+AH18+AI18+AJ18+AC18 -> 47601.446 | AL18: 14450 | AM18: 38150 | AN18: =AL18+AM18 -> 52600
B19: 13 VIE | C19: Fokker 100 | D19: SAF | E19: =7*52 -> 364 | F19: =E19/2 -> 182 | G19: =E19 -> 364 | H19: =_xlfn.XLOOKUP(B19,'[1]Baseline 2025'!$B:$B,'[1]Baseline 2025'!$C:$C) -> 962 | I19: =E19*H19 -> 350168 | J19: =_xlfn.XLOOKUP(B19,'[1]Baseline 2025'!$B:$B,'[1]Baseline 2025'!$E:$E) -> Short Haul | K19: =_xlfn.XLOOKUP(B19,'[1]Baseline 2025'!$B:$B,'[1]Baseline 2025'!$I:$I)/100 -> 25702.331 | L19: =K19*100 -> 2570233.1 | M19: =1.3 -> 1.3 | N19: =(L19*M19)/1000 -> 3341.3031 | O19: =9/1000 -> 0.009 | P19: =(O19*L19)/1000 -> 23.132098 | Q19: =0.03/1000 -> 3e-05 | R19: =Q19*L19/1000 -> 0.077106994 | S19: 100 | T19: =G19*S19*assumptions!$D$6 -> 30940 | U19: 10.9 | V19: 0.072916667 | W19: 3530.54 | X19: =W19*assumptions!$D$8 -> 4589.702 | Y19: 2 | Z19: 3 | AA19: 80.6 | AB19: 3.5 | AC19: 1109 | AD19: 787.5 | AE19: 5868 | AF19: 14000 | AG19: 3500 | AH19: 1094 | AI19: 2550 | AJ19: 2441 | AK19: =X19+AD19+AE19+AF19+AG19+AH19+AI19+AJ19+AC19 -> 35939.202 | AL19: 6851 | AM19: 38150 | AN19: =AL19+AM19 -> 45001
B20: 14 WAW | C20: Fokker 100 | D20: SAF | E20: =7*52 -> 364 | F20: =E20/2 -> 182 | G20: =E20 -> 364 | H20: =_xlfn.XLOOKUP(B20,'[1]Baseline 2025'!$B:$B,'[1]Baseline 2025'!$C:$C) -> 1105 | I20: =E20*H20 -> 402220 | J20: =_xlfn.XLOOKUP(B20,'[1]Baseline 2025'!$B:$B,'[1]Baseline 2025'!$E:$E) -> Short Haul | K20: =_xlfn.XLOOKUP(B20,'[1]Baseline 2025'!$B:$B,'[1]Baseline 2025'!$I:$I)/100 -> 29522.948 | L20: =K20*100 -> 2952294.8 | M20: =1.3 -> 1.3 | N20: =(L20*M20)/1000 -> 3837.9832 | O20: =9/1000 -> 0.009 | P20: =(O20*L20)/1000 -> 26.570653 | Q20: =0.03/1000 -> 3e-05 | R20: =Q20*L20/1000 -> 0.088568844 | S20: 100 | T20: =G20*S20*assumptions!$D$6 -> 30940 | U20: 10.9 | V20: 0.079861111 | W20: 4055.35 | X20: =W20*assumptions!$D$8 -> 5271.955 | Y20: 2 | Z20: 3 | AA20: 87.75 | AB20: 3.5 | AC20: 1273 | AD20: 864 | AE20: 6083 | AF20: 15360 | AG20: 3840 | AH20: 1200 | AI20: 2550 | AJ20: 2658 | AK20: =X20+AD20+AE20+AF20+AG20+AH20+AI20+AJ20+AC20 -> 39099.955 | AL20: 7458.75 | AM20: 38150 | AN20: =AL20+AM20 -> 45608.75
B21: 15 ZRH | C21: Fokker 100 | D21: SAF | E21: =14*52*2 -> 1456 | F21: =E21/2 -> 728 | G21: =E21 -> 1456 | H21: =_xlfn.XLOOKUP(B21,'[1]Baseline 2025'!$B:$B,'[1]Baseline 2025'!$C:$C) -> 603 | I21: =E21*H21 -> 877968 | J21: =_xlfn.XLOOKUP(B21,'[1]Baseline 2025'!$B:$B,'[1]Baseline 2025'!$E:$E) -> Short Haul | K21: =_xlfn.XLOOKUP(B21,'[1]Baseline 2025'!$B:$B,'[1]Baseline 2025'!$I:$I)/100 -> 32221.426 | L21: =K21*100 -> 3222142.6 | M21: =1.3 -> 1.3 | N21: =(L21*M21)/1000 -> 4188.7853 | O21: =9/1000 -> 0.009 | P21: =(O21*L21)/1000 -> 28.999283 | Q21: =0.03/1000 -> 3e-05 | R21: =Q21*L21/1000 -> 0.096664277 | S21: 100 | T21: =G21*S21*assumptions!$D$6 -> 123760 | U21: 10.9 | V21: 0.059027778 | W21: 2213.01 | X21: =W21*assumptions!$D$8 -> 2876.913 | Y21: 2 | Z21: 3 | AA21: 65 | AB21: 3.5 | AC21: 695 | AD21: 639 | AE21: 5330 | AF21: 11360 | AG21: 2840 | AH21: 888 | AI21: 2550 | AJ21: 1971 | AK21: =X21+AD21+AE21+AF21+AG21+AH21+AI21+AJ21+AC21 -> 29149.913 | AL21: 4250 | AM21: 38150 | AN21: =AL21+AM21 -> 42400
B22: 16 BKK | C22: B777-200er | D22: SAF | E22: =3*52*2 -> 312 | F22: =E22/2 -> 156 | G22: =E22 -> 312 | H22: =_xlfn.XLOOKUP(B22,'[1]Baseline 2025'!$B:$B,'[1]Baseline 2025'!$C:$C) -> 9217 | I22: =E22*H22 -> 2875704 | J22: =_xlfn.XLOOKUP(B22,'[1]Baseline 2025'!$B:$B,'[1]Baseline 2025'!$E:$E) -> Long Haul | K22: =_xlfn.XLOOKUP(B22,'[1]Baseline 2025'!$B:$B,'[1]Baseline 2025'!$I:$I)/100 -> 213377.24 | L22: =K22*100 -> 21337724 | M22: =1.3 -> 1.3 | N22: =(L22*M22)/1000 -> 27739.041 | O22: =9/1000 -> 0.009 | P22: =(O22*L22)/1000 -> 192.03951 | Q22: =0.03/1000 -> 3e-05 | R22: =Q22*L22/1000 -> 0.64013171 | S22: 300 | T22: =G22*S22*assumptions!$D$6 -> 79560 | U22: 20 | V22: 0.46875 | W22: 68390.14 | X22: =W22*assumptions!$D$8 -> 88907.182 | Y22: 3 | Z22: 12 | AA22: 1072 | AB22: 3.5 | AC22: 21474 | AD22: 11812.5 | AE22: 27101 | AF22: 90000 | AG22: 22500 | AH22: 21094 | AI22: 7650 | AJ22: 21670 | AK22: =X22+AD22+AE22+AF22+AG22+AH22+AI22+AJ22+AC22 -> 312208.68 | AL22: 273360 | AM22: 70000 | AN22: =AL22+AM22 -> 343360
B23: 17 MFM | C23: B777-200er | D23: SAF | E23: =3*52*2 -> 312 | F23: =E23/2 -> 156 | G23: =E23 -> 312 | H23: =_xlfn.XLOOKUP(B23,'[1]Baseline 2025'!$B:$B,'[1]Baseline 2025'!$C:$C) -> 9285 | I23: =E23*H23 -> 2896920 | J23: =_xlfn.XLOOKUP(B23,'[1]Baseline 2025'!$B:$B,'[1]Baseline 2025'!$E:$E) -> Long Haul | K23: =_xlfn.XLOOKUP(B23,'[1]Baseline 2025'!$B:$B,'[1]Baseline 2025'!$I:$I)/100 -> 214951.46 | L23: =K23*100 -> 21495146 | M23: =1.3 -> 1.3 | N23: =(L23*M23)/1000 -> 27943.69 | O23: =9/1000 -> 0.009 | P23: =(O23*L23)/1000 -> 193.45632 | Q23: =0.03/1000 -> 3e-05 | R23: =Q23*L23/1000 -> 0.64485439 | S23: 300 | T23: =G23*S23*assumptions!$D$6 -> 79560 | U23: 20 | V23: 0.46875 | W23: 68894.7 | X23: =W23*assumptions!$D$8 -> 89563.11 | Y23: 3 | Z23: 12 | AA23: 1072 | AB23: 3.5 | AC23: 21633 | AD23: 11812.5 | AE23: 27203 | AF23: 90000 | AG23: 22500 | AH23: 21094 | AI23: 7650 | AJ23: 21743 | AK23: =X23+AD23+AE23+AF23+AG23+AH23+AI23+AJ23+AC23 -> 313198.61 | AL23: 273360 | AM23: 70000 | AN23: =AL23+AM23 -> 343360
B24: 18 HAN | C24: B777-200er | D24: SAF | E24: =52*2 -> 104 | F24: =E24/2 -> 52 | G24: =E24 -> 104 | H24: =_xlfn.XLOOKUP(B24,'[1]Baseline 2025'!$B:$B,'[1]Baseline 2025'!$C:$C) -> 8886 | I24: =E24*H24 -> 924144 | J24: =_xlfn.XLOOKUP(B24,'[1]Baseline 2025'!$B:$B,'[1]Baseline 2025'!$E:$E) -> Long Haul | K24: =_xlfn.XLOOKUP(B24,'[1]Baseline 2025'!$B:$B,'[1]Baseline 2025'!$I:$I)/100 -> 68571.485 | L24: =K24*100 -> 6857148.5 | M24: =1.3 -> 1.3 | N24: =(L24*M24)/1000 -> 8914.293 | O24: =9/1000 -> 0.009 | P24: =(O24*L24)/1000 -> 61.714336 | Q24: =0.03/1000 -> 3e-05 | R24: =Q24*L24/1000 -> 0.20571445 | S24: 300 | T24: =G24*S24*assumptions!$D$6 -> 26520 | U24: 20 | V24: 0.45833333 | W24: 65934.12 | X24: =W24*assumptions!$D$8 -> 85714.356 | Y24: 3 | Z24: 12 | AA24: 1031 | AB24: 3.5 | AC24: 20703 | AD24: 11550 | AE24: 26604 | AF24: 88000 | AG24: 22000 | AH24: 20625 | AI24: 7650 | AJ24: 21087 | AK24: =X24+AD24+AE24+AF24+AG24+AH24+AI24+AJ24+AC24 -> 303933.36 | AL24: 262905 | AM24: 70000 | AN24: =AL24+AM24 -> 332905
B25: 19 PTY | C25: B777-200er | D25: SAF | E25: =156*2 -> 312 | F25: =E25/2 -> 156 | G25: =E25 -> 312 | H25: =_xlfn.XLOOKUP(B25,'[1]Baseline 2025'!$B:$B,'[1]Baseline 2025'!$C:$C) -> 8818 | I25: =E25*H25 -> 2751216 | J25: =_xlfn.XLOOKUP(B25,'[1]Baseline 2025'!$B:$B,'[1]Baseline 2025'!$E:$E) -> Long Haul | K25: =_xlfn.XLOOKUP(B25,'[1]Baseline 2025'!$B:$B,'[1]Baseline 2025'!$I:$I)/100 -> 204140.23 | L25: =K25*100 -> 20414023 | M25: =1.3 -> 1.3 | N25: =(L25*M25)/1000 -> 26538.23 | O25: =9/1000 -> 0.009 | P25: =(O25*L25)/1000 -> 183.7262 | Q25: =0.03/1000 -> 3e-05 | R25: =Q25*L25/1000 -> 0.61242068 | S25: 300 | T25: =G25*S25*assumptions!$D$6 -> 79560 | U25: 20 | V25: 0.46527778 | W25: 65429.56 | X25: =W25*assumptions!$D$8 -> 85058.428 | Y25: 3 | Z25: 12 | AA25: 1036 | AB25: 3.5 | AC25: 20545 | AD25: 11728.5 | AE25: 26502 | AF25: 89360 | AG25: 22340 | AH25: 20944 | AI25: 7650 | AJ25: 21172 | AK25: =X25+AD25+AE25+AF25+AG25+AH25+AI25+AJ25+AC25 -> 305299.93 | AL25: 264180 | AM25: 70000 | AN25: =AL25+AM25 -> 334180
B26: 20 MEX | C26: B777-200er | D26: SAF | E26: =156*2 -> 312 | F26: =E26/2 -> 156 | G26: =E26 -> 312 | H26: =_xlfn.XLOOKUP(B26,'[1]Baseline 2025'!$B:$B,'[1]Baseline 2025'!$C:$C) -> 9220 | I26: =E26*H26 -> 2876640 | J26: =_xlfn.XLOOKUP(B26,'[1]Baseline 2025'!$B:$B,'[1]Baseline 2025'!$E:$E) -> Long Haul | K26: =_xlfn.XLOOKUP(B26,'[1]Baseline 2025'!$B:$B,'[1]Baseline 2025'!$I:$I)/100 -> 213446.69 | L26: =K26*100 -> 21344669 | M26: =1.3 -> 1.3 | N26: =(L26*M26)/1000 -> 27748.069 | O26: =9/1000 -> 0.009 | P26: =(O26*L26)/1000 -> 192.10202 | Q26: =0.03/1000 -> 3e-05 | R26: =Q26*L26/1000 -> 0.64034006 | S26: 300 | T26: =G26*S26*assumptions!$D$6 -> 79560 | U26: 20 | V26: 0.47916667 | W26: 68412.4 | X26: =W26*assumptions!$D$8 -> 88936.12 | Y26: 3 | Z26: 12 | AA26: 1081 | AB26: 3.5 | AC26: 21481 | AD26: 12075 | AE26: 27105 | AF26: 92000 | AG26: 23000 | AH26: 21563 | AI26: 7650 | AJ26: 21903 | AK26: =X26+AD26+AE26+AF26+AG26+AH26+AI26+AJ26+AC26 -> 315713.12 | AL26: 275655 | AM26: 70000 | AN26: =AL26+AM26 -> 345655
B27: 21 GIG | C27: B777-200er | D27: SAF | E27: =52*2 -> 104 | F27: =E27/2 -> 52 | G27: =E27 -> 104 | H27: =_xlfn.XLOOKUP(B27,'[1]Baseline 2025'!$B:$B,'[1]Baseline 2025'!$C:$C) -> 9536 | I27: =E27*H27 -> 991744 | J27: =_xlfn.XLOOKUP(B27,'[1]Baseline 2025'!$B:$B,'[1]Baseline 2025'!$E:$E) -> Long Haul | K27: =_xlfn.XLOOKUP(B27,'[1]Baseline 2025'!$B:$B,'[1]Baseline 2025'!$I:$I)/100 -> 73587.405 | L27: =K27*100 -> 7358740.5 | M27: =1.3 -> 1.3 | N27: =(L27*M27)/1000 -> 9566.3626 | O27: =9/1000 -> 0.009 | P27: =(O27*L27)/1000 -> 66.228664 | Q27: =0.03/1000 -> 3e-05 | R27: =Q27*L27/1000 -> 0.22076221 | S27: 300 | T27: =G27*S27*assumptions!$D$6 -> 26520 | U27: 20 | V27: 0.5 | W27: 70757.12 | X27: =W27*assumptions!$D$8 -> 91984.256 | Y27: 3 | Z27: 12 | AA27: 1130 | AB27: 3.5 | AC27: 22218 | AD27: 12600 | AE27: 27579 | AF27: 96000 | AG27: 24000 | AH27: 22500 | AI27: 7650 | AJ27: 22701 | AK27: =X27+AD27+AE27+AF27+AG27+AH27+AI27+AJ27+AC27 -> 327232.26 | AL27: 288150 | AM27: 70000 | AN27: =AL27+AM27 -> 358150
B28: 22 CPT | C28: B777-200er | D28: SAF | E28: =156*2 -> 312 | F28: =E28/2 -> 156 | G28: =E28 -> 312 | H28: =_xlfn.XLOOKUP(B28,'[1]Baseline 2025'!$B:$B,'[1]Baseline 2025'!$C:$C) -> 9652 | I28: =E28*H28 -> 3011424 | J28: =_xlfn.XLOOKUP(B28,'[1]Baseline 2025'!$B:$B,'[1]Baseline 2025'!$E:$E) -> Long Haul | K28: =_xlfn.XLOOKUP(B28,'[1]Baseline 2025'!$B:$B,'[1]Baseline 2025'!$I:$I)/100 -> 223447.66 | L28: =K28*100 -> 22344766 | M28: =1.3 -> 1.3 | N28: =(L28*M28)/1000 -> 29048.196 | O28: =9/1000 -> 0.009 | P28: =(O28*L28)/1000 -> 201.10289 | Q28: =0.03/1000 -> 3e-05 | R28: =Q28*L28/1000 -> 0.67034298 | S28: 300 | T28: =G28*S28*assumptions!$D$6 -> 79560 | U28: 20 | V28: 0.47222222 | W28: 71617.84 | X28: =W28*assumptions!$D$8 -> 93103.192 | Y28: 3 | Z28: 12 | AA28: 1100 | AB28: 3.5 | AC28: 22488 | AD28: 11896.5 | AE28: 27753 | AF28: 90640 | AG28: 22660 | AH28: 21244 | AI28: 7650 | AJ28: 22205 | AK28: =X28+AD28+AE28+AF28+AG28+AH28+AI28+AJ28+AC28 -> 319639.69 | AL28: 280500 | AM28: 70000 | AN28: =AL28+AM28 -> 350500
N29: =SUM(N7:N28) -> 213699.15 | P29: =SUM(P7:P28) -> 1479.4557 | R29: =SUM(R7:R28) -> 4.931519

Sheet Scenario 2 2025
A4: Hybrid
AB5: Crew costs | AI5: Costs | AO5: Revenue
B6: Destination | C6: Aircraft | D6: Fuel type | E6: Frequency [per year] | F6: # retour | G6: # flights | H6: Lookup: Distance [km] | I6: Total distance travelled [km] | J6: Lookup: Flight Type | K6: Lookup: fuel consumption [l/100km] | L6: Conditional: Total fuel consumption [l] | M6: SAF LFEC CO2 per kg [kg/kg] | N6: Total CO2 emmission (tons) | O6: NOX per KG | P6: Total NOX emmision(Tons) | Q6: Sox per KG | R6: Total Sox emmission(Ton) | S6: Seats | T6: Passengers per year | U6: Available cargo (Tons) | V6: Flight time | W6: Fuel | X6: Fuel HEFA | Y6: HEFA Costs | Z6: Fuel Equivalent Electrics | AA6: Electricity costs | AB6: Pilot | AC6: Cabin crew | AD6: Ticket price | AE6: Freight rate (Euro/KG) | AF6: Crew costs | AG6: Airport & Navigation charges | AH6: Maintenance costs | AI6: Maintenance reserve | AJ6: Operational lease | AK6: catering and inflight services | AL6: Insurance and overhead | AM6: Total costs | AN6: Passenger revenue | AO6: Cargo revenue | AP6: Total revenuee | AQ6: marge
B7: 1 ALC | C7: Fokker 100 | D7: SAF | E7: =7*52*2 -> 728 | F7: =E7/2 -> 364 | G7: =E7 -> 728 | H7: =_xlfn.XLOOKUP(B7,'[1]Baseline 2025'!$B:$B,'[1]Baseline 2025'!$C:$C) -> 1613 | I7: =E7*H7 -> 1174264 | J7: =_xlfn.XLOOKUP(B7,'[1]Baseline 2025'!$B:$B,'[1]Baseline 2025'!$E:$E) -> Short Haul | K7: =_xlfn.XLOOKUP(B7,'[1]Baseline 2025'!$B:$B,'[1]Baseline 2025'!$I:$I)/100 -> 43095.489 | L7: =(K7*100)*0.65 -> 2801206.8 | M7: =1.3 -> 1.3 | N7: =(L7*M7)/1000 -> 3641.5688 | O7: =9/1000 -> 0.009 | P7: =(O7*L7)/1000 -> 25.210861 | Q7: =0.03/1000 -> 3e-05 | R7: =(Q7*L7)/1000 -> 0.084036203 | S7: 100 | T7: =G7*S7*assumptions!$D$6 -> 61880 | U7: 10.9 | V7: 0.11111111 | W7: 5919.71 | X7: =W7*0.65 -> 3847.8115 | Y7: =X7*assumptions!$C$8 -> 6926.0607 | Z7: =(W7*0.35)*43/3600 -> 24.747677 | AA7: =Z7*assumptions!$C$11 -> 2351.0293 | AB7: 2 | AC7: 3 | AD7: 190 | AE7: 3.5 | AF7: 1197 | AG7: 6845 | AH7: 21360 | AI7: 5340 | AJ7: 1669 | AK7: 2550 | AL7: 3440 | AM7: =Y7+AF7+AG7+AH7+AI7+AJ7+AK7+AL7+AA7 -> 51678.09 | AN7: 16150 | AO7: 38150 | AP7: =AN7+AO7 -> 54300 | AQ7: =(AP7/AM7)-1 -> 0.050735428
B8: 2 ARN | C8: Fokker 100 | D8: SAF | E8: =7*52*2 -> 728 | F8: =E8/2 -> 364 | G8: =E8 -> 728 | H8: =_xlfn.XLOOKUP(B8,'[1]Baseline 2025'!$B:$B,'[1]Baseline 2025'!$C:$C) -> 1155 | I8: =E8*H8 -> 840840 | J8: =_xlfn.XLOOKUP(B8,'[1]Baseline 2025'!$B:$B,'[1]Baseline 2025'!$E:$E) -> Short Haul | K8: =_xlfn.XLOOKUP(B8,'[1]Baseline 2025'!$B:$B,'[1]Baseline 2025'!$I:$I)/100 -> 30858.828 | L8: =(K8*100)*0.65 -> 2005823.8 | M8: =1.3 -> 1.3 | N8: =(L8*M8)/1000 -> 2607.571 | O8: =9/1000 -> 0.009 | P8: =(O8*L8)/1000 -> 18.052414 | Q8: =0.03/1000 -> 3e-05 | R8: =(Q8*L8)/1000 -> 0.060174715 | S8: 100 | T8: =G8*S8*assumptions!$D$6 -> 61880 | U8: 10.9 | V8: 0.083333333 | W8: 4238.85 | X8: =W8*0.65 -> 2755.2525 | Y8: =X8*assumptions!$C$8 -> 4959.4545 | Z8: =(W8*0.35)*43/3600 -> 17.720748 | AA8: =Z8*assumptions!$C$11 -> 1683.4711 | AB8: 2 | AC8: 3 | AD8: 117 | AE8: 3 | AF8: 900 | AG8: 6158 | AH8: 16000 | AI8: 4000 | AJ8: 1250 | AK8: 2550 | AL8: 2680 | AM8: =Y8+AF8+AG8+AH8+AI8+AJ8+AK8+AL8+AA8 -> 40180.926 | AN8: 9960.3 | AO8: 32700 | AP8: =AN8+AO8 -> 42660.3 | AQ8: =(AP8/AM8)-1 -> 0.06170526
B9: 3 BCN | C9: Fokker 100 | D9: SAF | E9: =7*52*2 -> 728 | F9: =E9/2 -> 364 | G9: =E9 -> 728 | H9: =_xlfn.XLOOKUP(B9,'[1]Baseline 2025'!$B:$B,'[1]Baseline 2025'!$C:$C) -> 1241 | I9: =E9*H9 -> 903448 | J9: =_xlfn.XLOOKUP(B9,'[1]Baseline 2025'!$B:$B,'[1]Baseline 2025'!$E:$E) -> Short Haul | K9: =_xlfn.XLOOKUP(B9,'[1]Baseline 2025'!$B:$B,'[1]Baseline 2025'!$I:$I)/100 -> 33156.542 | L9: =(K9*100)*0.65 -> 2155175.2 | M9: =1.3 -> 1.3 | N9: =(L9*M9)/1000 -> 2801.7278 | O9: =9/1000 -> 0.009 | P9: =(O9*L9)/1000 -> 19.396577 | Q9: =0.03/1000 -> 3e-05 | R9: =(Q9*L9)/1000 -> 0.064655256 | S9: 100 | T9: =G9*S9*assumptions!$D$6 -> 61880 | U9: 10.9 | V9: 0.097222222 | W9: 4554.47 | X9: =W9*0.65 -> 2960.4055 | Y9: =X9*assumptions!$C$8 -> 5328.7299 | Z9: =(W9*0.35)*43/3600 -> 19.040215 | AA9: =Z9*assumptions!$C$11 -> 1808.8204 | AB9: 2 | AC9: 3 | AD9: 111.6 | AE9: 3.5 | AF9: 1048.5 | AG9: 6287 | AH9: 18640 | AI9: 4660 | AJ9: 1456 | AK9: 2550 | AL9: 2985 | AM9: =Y9+AF9+AG9+AH9+AI9+AJ9+AK9+AL9+AA9 -> 44764.05 | AN9: 9486 | AO9: 38150 | AP9: =AN9+AO9 -> 47636 | AQ9: =(AP9/AM9)-1 -> 0.064157503
B10: 4 BRU | C10: Fokker 100 | D10: SAF | E10: =14*52 -> 728 | F10: =E10/2 -> 364 | G10: =E10 -> 728 | H10: =_xlfn.XLOOKUP(B10,'[1]Baseline 2025'!$B:$B,'[1]Baseline 2025'!$C:$C) -> 158 | I10: =E10*H10 -> 115024 | J10: =_xlfn.XLOOKUP(B10,'[1]Baseline 2025'!$B:$B,'[1]Baseline 2025'!$E:$E) -> Short Haul | K10: =_xlfn.XLOOKUP(B10,'[1]Baseline 2025'!$B:$B,'[1]Baseline 2025'!$I:$I)/100 -> 8442.7616 | L10: =(K10*100)*0.65 -> 548779.5 | M10: =1.3 -> 1.3 | N10: =(L10*M10)/1000 -> 713.41336 | O10: =9/1000 -> 0.009 | P10: =(O10*L10)/1000 -> 4.9390155 | Q10: =0.03/1000 -> 3e-05 | R10: =(Q10*L10)/1000 -> 0.016463385 | S10: 100 | T10: =G10*S10*assumptions!$D$6 -> 61880 | U10: 10.9 | V10: 0.027777778 | W10: 579.86 | X10: =W10*0.65 -> 376.909 | Y10: =X10*assumptions!$C$8 -> 678.4362 | Z10: =(W10*0.35)*43/3600 -> 2.4241369 | AA10: =Z10*assumptions!$C$11 -> 230.29301 | AB10: 2 | AC10: 3 | AD10: 46.5 | AE10: 3.5 | AF10: 297 | AG10: 4662 | AH10: 5280 | AI10: 1320 | AJ10: 413 | AK10: 2550 | AL10: 1103 | AM10: =Y10+AF10+AG10+AH10+AI10+AJ10+AK10+AL10+AA10 -> 16533.729 | AN10: 3952.5 | AO10: 38150 | AP10: =AN10+AO10 -> 42102.5 | AQ10: 0.607
B11: 5 BSL | C11: Fokker 100 | D11: SAF | E11: =7*52*2 -> 728 | F11: =E11/2 -> 364 | G11: =E11 -> 728 | H11: =_xlfn.XLOOKUP(B11,'[1]Baseline 2025'!$B:$B,'[1]Baseline 2025'!$C:$C) -> 561 | I11: =E11*H11 -> 408408 | J11: =_xlfn.XLOOKUP(B11,'[1]Baseline 2025'!$B:$B,'[1]Baseline 2025'!$E:$E) -> Short Haul | K11: =_xlfn.XLOOKUP(B11,'[1]Baseline 2025'!$B:$B,'[1]Baseline 2025'!$I:$I)/100 -> 14988.574 | L11: =(K11*100)*0.65 -> 974257.28 | M11: =1.3 -> 1.3 | N11: =(L11*M11)/1000 -> 1266.5345 | O11: =9/1000 -> 0.009 | P11: =(O11*L11)/1000 -> 8.7683156 | Q11: =0.03/1000 -> 3e-05 | R11: =(Q11*L11)/1000 -> 0.029227719 | S11: 100 | T11: =G11*S11*assumptions!$D$6 -> 61880 | U11: 10.9 | V11: 0.055555556 | W11: 2058.87 | X11: =W11*0.65 -> 1338.2655 | Y11: =X11*assumptions!$C$8 -> 2408.8779 | Z11: =(W11*0.35)*43/3600 -> 8.6072204 | AA11: =Z11*assumptions!$C$11 -> 817.68594 | AB11: 2 | AC11: 3 | AD11: 56 | AE11: 3.5 | AF11: 598.5 | AG11: 5267 | AH11: 10640 | AI11: 2660 | AJ11: 831 | AK11: 2550 | AL11: 1842 | AM11: =Y11+AF11+AG11+AH11+AI11+AJ11+AK11+AL11+AA11 -> 27615.064 | AN11: 4760 | AO11: 38150 | AP11: =AN11+AO11 -> 42910 | AQ11: =(AP11/AM11)-1 -> 0.55386206
B12: 6 CDG | C12: Fokker 100 | D12: SAF | E12: =7*52 -> 364 | F12: =E12/2 -> 182 | G12: =E12 -> 364 | H12: =_xlfn.XLOOKUP(B12,'[1]Baseline 2025'!$B:$B,'[1]Baseline 2025'!$C:$C) -> 399 | I12: =E12*H12 -> 145236 | J12: =_xlfn.XLOOKUP(B12,'[1]Baseline 2025'!$B:$B,'[1]Baseline 2025'!$E:$E) -> Short Haul | K12: =_xlfn.XLOOKUP(B12,'[1]Baseline 2025'!$B:$B,'[1]Baseline 2025'!$I:$I)/100 -> 10660.322 | L12: =(K12*100)*0.65 -> 692920.96 | M12: =1.3 -> 1.3 | N12: =(L12*M12)/1000 -> 900.79724 | O12: =9/1000 -> 0.009 | P12: =(O12*L12)/1000 -> 6.2362886 | Q12: =0.03/1000 -> 3e-05 | R12: =(Q12*L12)/1000 -> 0.020787629 | S12: 100 | T12: =G12*S12*assumptions!$D$6 -> 30940 | U12: 10.9 | V12: 0.055555556 | W12: 1464.33 | X12: =W12*0.65 -> 951.8145 | Y12: =X12*assumptions!$C$8 -> 1713.2661 | Z12: =(W12*0.35)*43/3600 -> 6.1217129 | AA12: =Z12*assumptions!$C$11 -> 581.56273 | AB12: 2 | AC12: 3 | AD12: 50 | AE12: 3.5 | AF12: 598.5 | AG12: 5024 | AH12: 10640 | AI12: 2660 | AJ12: 831 | AK12: 2550 | AL12: 1757 | AM12: =Y12+AF12+AG12+AH12+AI12+AJ12+AK12+AL12+AA12 -> 26355.329 | AN12: 4250 | AO12: 38150 | AP12: =AN12+AO12 -> 42400 | AQ12: =(AP12/AM12)-1 -> 0.60878281
B13: 7 DUB | C13: Fokker 100 | D13: SAF | E13: =7*52 -> 364 | F13: =E13/2 -> 182 | G13: =E13 -> 364 | H13: =_xlfn.XLOOKUP(B13,'[1]Baseline 2025'!$B:$B,'[1]Baseline 2025'!$C:$C) -> 753 | I13: =E13*H13 -> 274092 | J13: =_xlfn.XLOOKUP(B13,'[1]Baseline 2025'!$B:$B,'[1]Baseline 2025'!$E:$E) -> Short Haul | K13: =_xlfn.XLOOKUP(B13,'[1]Baseline 2025'!$B:$B,'[1]Baseline 2025'!$I:$I)/100 -> 20118.353 | L13: =(K13*100)*0.65 -> 1307692.9 | M13: =1.3 -> 1.3 | N13: =(L13*M13)/1000 -> 1700.0008 | O13: =9/1000 -> 0.009 | P13: =(O13*L13)/1000 -> 11.769236 | Q13: =0.03/1000 -> 3e-05 | R13: =(Q13*L13)/1000 -> 0.039230788 | S13: 100 | T13: =G13*S13*assumptions!$D$6 -> 30940 | U13: 10.9 | V13: 0.069444444 | W13: 2763.51 | X13: =W13*0.65 -> 1796.2815 | Y13: =X13*assumptions!$C$8 -> 3233.3067 | Z13: =(W13*0.35)*43/3600 -> 11.553007 | AA13: =Z13*assumptions!$C$11 -> 1097.5357 | AB13: 2 | AC13: 3 | AD13: 62 | AE13: 3.5 | AF13: 747 | AG13: 5555 | AH13: 13280 | AI13: 3320 | AJ13: 1038 | AK13: 2550 | AL13: 2202 | AM13: =Y13+AF13+AG13+AH13+AI13+AJ13+AK13+AL13+AA13 -> 33022.842 | AN13: 5270 | AO13: 38150 | AP13: =AN13+AO13 -> 43420 | AQ13: =(AP13/AM13)-1 -> 0.31484745
B14: 8 FAO | C14: Fokker 100 | D14: SAF | E14: =7*52 -> 364 | F14: =E14/2 -> 182 | G14: =E14 -> 364 | H14: =_xlfn.XLOOKUP(B14,'[1]Baseline 2025'!$B:$B,'[1]Baseline 2025'!$C:$C) -> 1970 | I14: =E14*H14 -> 717080 | J14: =_xlfn.XLOOKUP(B14,'[1]Baseline 2025'!$B:$B,'[1]Baseline 2025'!$E:$E) -> Short Haul | K14: =_xlfn.XLOOKUP(B14,'[1]Baseline 2025'!$B:$B,'[1]Baseline 2025'!$I:$I)/100 -> 52633.672 | L14: =(K14*100)*0.65 -> 3421188.7 | M14: =1.3 -> 1.3 | N14: =(L14*M14)/1000 -> 4447.5453 | O14: =9/1000 -> 0.009 | P14: =(O14*L14)/1000 -> 30.790698 | Q14: =0.03/1000 -> 3e-05 | R14: =(Q14*L14)/1000 -> 0.10263566 | S14: 100 | T14: =G14*S14*assumptions!$D$6 -> 30940 | U14: 10.9 | V14: 0.125 | W14: 7229.9 | X14: =W14*0.65 -> 4699.435 | Y14: =X14*assumptions!$C$8 -> 8458.983 | Z14: =(W14*0.35)*43/3600 -> 30.224999 | AA14: =Z14*assumptions!$C$11 -> 2871.3749 | AB14: 2 | AC14: 3 | AD14: 275 | AE14: 3.5 | AF14: 1350 | AG14: 7380 | AH14: 24000 | AI14: 6000 | AJ14: 1875 | AK14: 2550 | AL14: 3893 | AM14: =Y14+AF14+AG14+AH14+AI14+AJ14+AK14+AL14+AA14 -> 58378.358 | AN14: 23375 | AO14: 38150 | AP14: =AN14+AO14 -> 61525 | AQ14: =(AP14/AM14)-1 -> 0.053900833
B15: 9 LIS | C15: Fokker 100 | D15: SAF | E15: =7*52 -> 364 | F15: =E15/2 -> 182 | G15: =E15 -> 364 | H15: =_xlfn.XLOOKUP(B15,'[1]Baseline 2025'!$B:$B,'[1]Baseline 2025'!$C:$C) -> 1848 | I15: =E15*H15 -> 672672 | J15: =_xlfn.XLOOKUP(B15,'[1]Baseline 2025'!$B:$B,'[1]Baseline 2025'!$E:$E) -> Short Haul | K15: =_xlfn.XLOOKUP(B15,'[1]Baseline 2025'!$B:$B,'[1]Baseline 2025'!$I:$I)/100 -> 49374.125 | L15: =(K15*100)*0.65 -> 3209318.1 | M15: =1.3 -> 1.3 | N15: =(L15*M15)/1000 -> 4172.1135 | O15: =9/1000 -> 0.009 | P15: =(O15*L15)/1000 -> 28.883863 | Q15: =0.03/1000 -> 3e-05 | R15: =(Q15*L15)/1000 -> 0.096279543 | S15: 100 | T15: =G15*S15*assumptions!$D$6 -> 30940 | U15: 10.9 | V15: 0.13194444 | W15: 6782.16 | X15: =W15*0.65 -> 4408.404 | Y15: =X15*assumptions!$C$8 -> 7935.1272 | Z15: =(W15*0.35)*43/3600 -> 28.353197 | AA15: =Z15*assumptions!$C$11 -> 2693.5537 | AB15: 2 | AC15: 3 | AD15: 287 | AE15: 3.5 | AF15: 1425 | AG15: 7197 | AH15: 25333.6 | AI15: 6333.4 | AJ15: 1979 | AK15: 2550 | AL15: 3962 | AM15: =Y15+AF15+AG15+AH15+AI15+AJ15+AK15+AL15+AA15 -> 59408.681 | AN15: 24395 | AO15: 38150 | AP15: =AN15+AO15 -> 62545 | AQ15: =(AP15/AM15)-1 -> 0.05279227
B16: 10 MUC | C16: Fokker 100 | D16: SAF | E16: =7*52 -> 364 | F16: =E16/2 -> 182 | G16: =E16 -> 364 | H16: =_xlfn.XLOOKUP(B16,'[1]Baseline 2025'!$B:$B,'[1]Baseline 2025'!$C:$C) -> 665 | I16: =E16*H16 -> 242060 | J16: =_xlfn.XLOOKUP(B16,'[1]Baseline 2025'!$B:$B,'[1]Baseline 2025'!$E:$E) -> Short Haul | K16: =_xlfn.XLOOKUP(B16,'[1]Baseline 2025'!$B:$B,'[1]Baseline 2025'!$I:$I)/100 -> 17767.204 | L16: =(K16*100)*0.65 -> 1154868.3 | M16: =1.3 -> 1.3 | N16: =(L16*M16)/1000 -> 1501.3287 | O16: =9/1000 -> 0.009 | P16: =(O16*L16)/1000 -> 10.393814 | Q16: =0.03/1000 -> 3e-05 | R16: =(Q16*L16)/1000 -> 0.034646048 | S16: 100 | T16: =G16*S16*assumptions!$D$6 -> 30940 | U16: 10.9 | V16: 0.059027778 | W16: 2440.55 | X16: =W16*0.65 -> 1586.3575 | Y16: =X16*assumptions!$C$8 -> 2855.4435 | Z16: =(W16*0.35)*43/3600 -> 10.202855 | AA16: =Z16*assumptions!$C$11 -> 969.27121 | AB16: 2 | AC16: 3 | AD16: 60 | AE16: 3.5 | AF16: 639 | AG16: 5423 | AH16: 11360 | AI16: 2840 | AJ16: 888 | AK16: 2550 | AL16: 1967 | AM16: =Y16+AF16+AG16+AH16+AI16+AJ16+AK16+AL16+AA16 -> 29491.715 | AN16: 5138.25 | AO16: 38150 | AP16: =AN16+AO16 -> 43288.25 | AQ16: =(AP16/AM16)-1 -> 0.46781055
B17: 11 OSL | C17: Fokker 100 | D17: SAF | E17: =7*52 -> 364 | F17: =E17/2 -> 182 | G17: =E17 -> 364 | H17: =_xlfn.XLOOKUP(B17,'[1]Baseline 2025'!$B:$B,'[1]Baseline 2025'!$C:$C) -> 961 | I17: =E17*H17 -> 349804 | J17: =_xlfn.XLOOKUP(B17,'[1]Baseline 2025'!$B:$B,'[1]Baseline 2025'!$E:$E) -> Short Haul | K17: =_xlfn.XLOOKUP(B17,'[1]Baseline 2025'!$B:$B,'[1]Baseline 2025'!$I:$I)/100 -> 25675.614 | L17: =(K17*100)*0.65 -> 1668914.9 | M17: =1.3 -> 1.3 | N17: =(L17*M17)/1000 -> 2169.5893 | O17: =9/1000 -> 0.009 | P17: =(O17*L17)/1000 -> 15.020234 | Q17: =0.03/1000 -> 3e-05 | R17: =(Q17*L17)/1000 -> 0.050067447 | S17: 100 | T17: =G17*S17*assumptions!$D$6 -> 30940 | U17: 10.9 | V17: 0.072916667 | W17: 3526.87 | X17: =W17*0.65 -> 2292.4655 | Y17: =X17*assumptions!$C$8 -> 4126.4379 | Z17: =(W17*0.35)*43/3600 -> 14.744276 | AA17: =Z17*assumptions!$C$11 -> 1400.7062 | AB17: 2 | AC17: 3 | AD17: 65 | AE17: 3.5 | AF17: 787.5 | AG17: 5867 | AH17: 14000 | AI17: 3500 | AJ17: 1094 | AK17: 2550 | AL17: 2381 | AM17: =Y17+AF17+AG17+AH17+AI17+AJ17+AK17+AL17+AA17 -> 35706.644 | AN17: 5525 | AO17: 38150 | AP17: =AN17+AO17 -> 43675 | AQ17: =(AP17/AM17)-1 -> 0.22316171
B18: 12 PMI | C18: Fokker 100 | D18: SAF | E18: =7*52 -> 364 | F18: =E18/2 -> 182 | G18: =E18 -> 364 | H18: =_xlfn.XLOOKUP(B18,'[1]Baseline 2025'!$B:$B,'[1]Baseline 2025'!$C:$C) -> 1426 | I18: =E18*H18 -> 519064 | J18: =_xlfn.XLOOKUP(B18,'[1]Baseline 2025'!$B:$B,'[1]Baseline 2025'!$E:$E) -> Short Haul | K18: =_xlfn.XLOOKUP(B18,'[1]Baseline 2025'!$B:$B,'[1]Baseline 2025'!$I:$I)/100 -> 38099.298 | L18: =(K18*100)*0.65 -> 2476454.3 | M18: =1.3 -> 1.3 | N18: =(L18*M18)/1000 -> 3219.3906 | O18: =9/1000 -> 0.009 | P18: =(O18*L18)/1000 -> 22.288089 | Q18: =0.03/1000 -> 3e-05 | R18: =(Q18*L18)/1000 -> 0.07429363 | S18: 100 | T18: =G18*S18*assumptions!$D$6 -> 30940 | U18: 10.9 | V18: 0.10069444 | W18: 5233.42 | X18: =W18*0.65 -> 3401.723 | Y18: =X18*assumptions!$C$8 -> 6123.1014 | Z18: =(W18*0.35)*43/3600 -> 21.878603 | AA18: =Z18*assumptions!$C$11 -> 2078.4673 | AB18: 2 | AC18: 3 | AD18: 137 | AE18: 3.5 | AF18: 1089 | AG18: 6564 | AH18: 19360 | AI18: 4840 | AJ18: 1513 | AK18: 2550 | AL18: 3152 | AM18: =Y18+AF18+AG18+AH18+AI18+AJ18+AK18+AL18+AA18 -> 47269.569 | AN18: 11645 | AO18: 38150 | AP18: =AN18+AO18 -> 49795 | AQ18: =(AP18/AM18)-1 -> 0.053426155
B19: 13 VIE | C19: Fokker 100 | D19: SAF | E19: =7*52 -> 364 | F19: =E19/2 -> 182 | G19: =E19 -> 364 | H19: =_xlfn.XLOOKUP(B19,'[1]Baseline 2025'!$B:$B,'[1]Baseline 2025'!$C:$C) -> 962 | I19: =E19*H19 -> 350168 | J19: =_xlfn.XLOOKUP(B19,'[1]Baseline 2025'!$B:$B,'[1]Baseline 2025'!$E:$E) -> Short Haul | K19: =_xlfn.XLOOKUP(B19,'[1]Baseline 2025'!$B:$B,'[1]Baseline 2025'!$I:$I)/100 -> 25702.331 | L19: =(K19*100)*0.65 -> 1670651.5 | M19: =1.3 -> 1.3 | N19: =(L19*M19)/1000 -> 2171.847 | O19: =9/1000 -> 0.009 | P19: =(O19*L19)/1000 -> 15.035864 | Q19: =0.03/1000 -> 3e-05 | R19: =(Q19*L19)/1000 -> 0.050119546 | S19: 100 | T19: =G19*S19*assumptions!$D$6 -> 30940 | U19: 10.9 | V19: 0.072916667 | W19: 3530.54 | X19: =W19*0.65 -> 2294.851 | Y19: =X19*assumptions!$C$8 -> 4130.7318 | Z19: =(W19*0.35)*43/3600 -> 14.759619 | AA19: =Z19*assumptions!$C$11 -> 1402.1638 | AB19: 2 | AC19: 3 | AD19: 68.2 | AE19: 3.5 | AF19: 787.5 | AG19: 5868 | AH19: 14000 | AI19: 3500 | AJ19: 1094 | AK19: 2550 | AL19: 2382 | AM19: =Y19+AF19+AG19+AH19+AI19+AJ19+AK19+AL19+AA19 -> 35714.396 | AN19: 5780 | AO19: 38150 | AP19: =AN19+AO19 -> 43930 | AQ19: =(AP19/AM19)-1 -> 0.23003622
B20: 14 WAW | C20: Fokker 100 | D20: SAF | E20: =7*52 -> 364 | F20: =E20/2 -> 182 | G20: =E20 -> 364 | H20: =_xlfn.XLOOKUP(B20,'[1]Baseline 2025'!$B:$B,'[1]Baseline 2025'!$C:$C) -> 1105 | I20: =E20*H20 -> 402220 | J20: =_xlfn.XLOOKUP(B20,'[1]Baseline 2025'!$B:$B,'[1]Baseline 2025'!$E:$E) -> Short Haul | K20: =_xlfn.XLOOKUP(B20,'[1]Baseline 2025'!$B:$B,'[1]Baseline 2025'!$I:$I)/100 -> 29522.948 | L20: =(K20*100)*0.65 -> 1918991.6 | M20: =1.3 -> 1.3 | N20: =(L20*M20)/1000 -> 2494.6891 | O20: =9/1000 -> 0.009 | P20: =(O20*L20)/1000 -> 17.270925 | Q20: =0.03/1000 -> 3e-05 | R20: =(Q20*L20)/1000 -> 0.057569749 | S20: 100 | T20: =G20*S20*assumptions!$D$6 -> 30940 | U20: 10.9 | V20: 0.079861111 | W20: 4055.35 | X20: =W20*0.65 -> 2635.9775 | Y20: =X20*assumptions!$C$8 -> 4744.7595 | Z20: =(W20*0.35)*43/3600 -> 16.953616 | AA20: =Z20*assumptions!$C$11 -> 1610.5935 | AB20: 2 | AC20: 3 | AD20: 74.25 | AE20: 3.5 | AF20: 859.5 | AG20: 6083 | AH20: 15280 | AI20: 3820 | AJ20: 1194 | AK20: 2550 | AL20: 2765 | AM20: =Y20+AF20+AG20+AH20+AI20+AJ20+AK20+AL20+AA20 -> 38906.853 | AN20: 6311.25 | AO20: 38150 | AP20: =AN20+AO20 -> 44461.25 | AQ20: =(AP20/AM20)-1 -> 0.1427614
B21: 15 ZRH | C21: Fokker 100 | D21: SAF | E21: =14*52*2 -> 1456 | F21: =E21/2 -> 728 | G21: =E21 -> 1456 | H21: =_xlfn.XLOOKUP(B21,'[1]Baseline 2025'!$B:$B,'[1]Baseline 2025'!$C:$C) -> 603 | I21: =E21*H21 -> 877968 | J21: =_xlfn.XLOOKUP(B21,'[1]Baseline 2025'!$B:$B,'[1]Baseline 2025'!$E:$E) -> Short Haul | K21: =_xlfn.XLOOKUP(B21,'[1]Baseline 2025'!$B:$B,'[1]Baseline 2025'!$I:$I)/100 -> 32221.426 | L21: =(K21*100)*0.65 -> 2094392.7 | M21: =1.3 -> 1.3 | N21: =(L21*M21)/1000 -> 2722.7105 | O21: =9/1000 -> 0.009 | P21: =(O21*L21)/1000 -> 18.849534 | Q21: =0.03/1000 -> 3e-05 | R21: =(Q21*L21)/1000 -> 0.06283178 | S21: 100 | T21: =G21*S21*assumptions!$D$6 -> 123760 | U21: 10.9 | V21: 0.059027778 | W21: 2213.01 | X21: =W21*0.65 -> 1438.4565 | Y21: =X21*assumptions!$C$8 -> 2589.2217 | Z21: =(W21*0.35)*43/3600 -> 9.2516112 | AA21: =Z21*assumptions!$C$11 -> 878.90307 | AB21: 2 | AC21: 3 | AD21: 55 | AE21: 3.5 | AF21: 634.5 | AG21: 5330 | AH21: 11280 | AI21: 2820 | AJ21: 881 | AK21: 2550 | AL21: 1927 | AM21: =Y21+AF21+AG21+AH21+AI21+AJ21+AK21+AL21+AA21 -> 28890.625 | AN21: 4675 | AO21: 38150 | AP21: =AN21+AO21 -> 42825 | AQ21: =(AP21/AM21)-1 -> 0.48231478
B22: 16 BKK | C22: B777-200er | D22: SAF | E22: =3*52*2 -> 312 | F22: =E22/2 -> 156 | G22: =E22 -> 312 | H22: =_xlfn.XLOOKUP(B22,'[1]Baseline 2025'!$B:$B,'[1]Baseline 2025'!$C:$C) -> 9217 | I22: =E22*H22 -> 2875704 | J22: =_xlfn.XLOOKUP(B22,'[1]Baseline 2025'!$B:$B,'[1]Baseline 2025'!$E:$E) -> Long Haul | K22: =_xlfn.XLOOKUP(B22,'[1]Baseline 2025'!$B:$B,'[1]Baseline 2025'!$I:$I)/100 -> 213377.24 | L22: =(K22*100)*0.65 -> 13869520 | M22: =1.3 -> 1.3 | N22: =(L22*M22)/1000 -> 18030.377 | O22: =9/1000 -> 0.009 | P22: =(O22*L22)/1000 -> 124.82568 | Q22: =0.03/1000 -> 3e-05 | R22: =(Q22*L22)/1000 -> 0.41608561 | S22: 300 | T22: =G22*S22*assumptions!$D$6 -> 79560 | U22: 20 | V22: 0.46875 | W22: 68390.14 | X22: =W22*0.65 -> 44453.591 | Y22: =X22*assumptions!$C$8 -> 80016.464 | Z22: =(W22*0.35)*43/3600 -> 285.90878 | AA22: =Z22*assumptions!$C$11 -> 27161.334 | AB22: 3 | AC22: 12 | AD22: 997 | AE22: 3.5 | AF22: 11812.5 | AG22: 27101 | AH22: 90000 | AI22: 22500 | AJ22: 21094 | AK22: 7650 | AL22: 20532 | AM22: =Y22+AF22+AG22+AH22+AI22+AJ22+AK22+AL22+AA22 -> 307867.3 | AN22: 254235 | AO22: 70000 | AP22: =AN22+AO22 -> 324235 | AQ22: =(AP22/AM22)-1 -> 0.053164796
B23: 17 MFM | C23: B777-200er | D23: SAF | E23: =3*52*2 -> 312 | F23: =E23/2 -> 156 | G23: =E23 -> 312 | H23: =_xlfn.XLOOKUP(B23,'[1]Baseline 2025'!$B:$B,'[1]Baseline 2025'!$C:$C) -> 9285 | I23: =E23*H23 -> 2896920 | J23: =_xlfn.XLOOKUP(B23,'[1]Baseline 2025'!$B:$B,'[1]Baseline 2025'!$E:$E) -> Long Haul | K23: =_xlfn.XLOOKUP(B23,'[1]Baseline 2025'!$B:$B,'[1]Baseline 2025'!$I:$I)/100 -> 214951.46 | L23: =(K23*100)*0.65 -> 13971845 | M23: =1.3 -> 1.3 | N23: =(L23*M23)/1000 -> 18163.399 | O23: =9/1000 -> 0.009 | P23: =(O23*L23)/1000 -> 125.74661 | Q23: =0.03/1000 -> 3e-05 | R23: =(Q23*L23)/1000 -> 0.41915535 | S23: 300 | T23: =G23*S23*assumptions!$D$6 -> 79560 | U23: 20 | V23: 0.46875 | W23: 68894.7 | X23: =W23*0.65 -> 44781.555 | Y23: =X23*assumptions!$C$8 -> 80606.799 | Z23: =(W23*0.35)*43/3600 -> 288.01812 | AA23: =Z23*assumptions!$C$11 -> 27361.721 | AB23: 3 | AC23: 12 | AD23: 1000 | AE23: 3.5 | AF23: 11812.5 | AG23: 27203 | AH23: 90000 | AI23: 22500 | AJ23: 21094 | AK23: 7650 | AL23: 20596 | AM23: =Y23+AF23+AG23+AH23+AI23+AJ23+AK23+AL23+AA23 -> 308824.02 | AN23: 255000 | AO23: 70000 | AP23: =AN23+AO23 -> 325000 | AQ23: =(AP23/AM23)-1 -> 0.052379279
B24: 18 HAN | C24: B777-200er | D24: SAF | E24: =52*2 -> 104 | F24: =E24/2 -> 52 | G24: =E24 -> 104 | H24: =_xlfn.XLOOKUP(B24,'[1]Baseline 2025'!$B:$B,'[1]Baseline 2025'!$C:$C) -> 8886 | I24: =E24*H24 -> 924144 | J24: =_xlfn.XLOOKUP(B24,'[1]Baseline 2025'!$B:$B,'[1]Baseline 2025'!$E:$E) -> Long Haul | K24: =_xlfn.XLOOKUP(B24,'[1]Baseline 2025'!$B:$B,'[1]Baseline 2025'!$I:$I)/100 -> 68571.485 | L24: =(K24*100)*0.65 -> 4457146.5 | M24: =1.3 -> 1.3 | N24: =(L24*M24)/1000 -> 5794.2905 | O24: =9/1000 -> 0.009 | P24: =(O24*L24)/1000 -> 40.114319 | Q24: =0.03/1000 -> 3e-05 | R24: =(Q24*L24)/1000 -> 0.1337144 | S24: 300 | T24: =G24*S24*assumptions!$D$6 -> 26520 | U24: 20 | V24: 0.45833333 | W24: 65934.12 | X24: =W24*0.65 -> 42857.178 | Y24: =X24*assumptions!$C$8 -> 77142.92 | Z24: =(W24*0.35)*43/3600 -> 275.64125 | AA24: =Z24*assumptions!$C$11 -> 26185.919 | AB24: 3 | AC24: 12 | AD24: 963 | AE24: 3.5 | AF24: 11550 | AG24: 26604 | AH24: 88000 | AI24: 22000 | AJ24: 20625 | AK24: 7650 | AL24: 19990 | AM24: =Y24+AF24+AG24+AH24+AI24+AJ24+AK24+AL24+AA24 -> 299747.84 | AN24: 245565 | AO24: 70000 | AP24: =AN24+AO24 -> 315565 | AQ24: =(AP24/AM24)-1 -> 0.052768223
B25: 19 PTY | C25: B777-200er | D25: SAF | E25: =156*2 -> 312 | F25: =E25/2 -> 156 | G25: =E25 -> 312 | H25: =_xlfn.XLOOKUP(B25,'[1]Baseline 2025'!$B:$B,'[1]Baseline 2025'!$C:$C) -> 8818 | I25: =E25*H25 -> 2751216 | J25: =_xlfn.XLOOKUP(B25,'[1]Baseline 2025'!$B:$B,'[1]Baseline 2025'!$E:$E) -> Long Haul | K25: =_xlfn.XLOOKUP(B25,'[1]Baseline 2025'!$B:$B,'[1]Baseline 2025'!$I:$I)/100 -> 204140.23 | L25: =(K25*100)*0.65 -> 13269115 | M25: =1.3 -> 1.3 | N25: =(L25*M25)/1000 -> 17249.849 | O25: =9/1000 -> 0.009 | P25: =(O25*L25)/1000 -> 119.42203 | Q25: =0.03/1000 -> 3e-05 | R25: =(Q25*L25)/1000 -> 0.39807344 | S25: 300 | T25: =G25*S25*assumptions!$D$6 -> 79560 | U25: 20 | V25: 0.46527778 | W25: 65429.56 | X25: =W25*0.65 -> 42529.214 | Y25: =X25*assumptions!$C$8 -> 76552.585 | Z25: =(W25*0.35)*43/3600 -> 273.53191 | AA25: =Z25*assumptions!$C$11 -> 25985.532 | AB25: 3 | AC25: 12 | AD25: 969 | AE25: 3.5 | AF25: 11728.5 | AG25: 26502 | AH25: 89360 | AI25: 22340 | AJ25: 20944 | AK25: 7650 | AL25: 20084 | AM25: =Y25+AF25+AG25+AH25+AI25+AJ25+AK25+AL25+AA25 -> 301146.62 | AN25: 247095 | AO25: 70000 | AP25: =AN25+AO25 -> 317095 | AQ25: =(AP25/AM25)-1 -> 0.052958866
B26: 20 MEX | C26: B777-200er | D26: SAF | E26: =156*2 -> 312 | F26: =E26/2 -> 156 | G26: =E26 -> 312 | H26: =_xlfn.XLOOKUP(B26,'[1]Baseline 2025'!$B:$B,'[1]Baseline 2025'!$C:$C) -> 9220 | I26: =E26*H26 -> 2876640 | J26: =_xlfn.XLOOKUP(B26,'[1]Baseline 2025'!$B:$B,'[1]Baseline 2025'!$E:$E) -> Long Haul | K26: =_xlfn.XLOOKUP(B26,'[1]Baseline 2025'!$B:$B,'[1]Baseline 2025'!$I:$I)/100 -> 213446.69 | L26: =(K26*100)*0.65 -> 13874035 | M26: =1.3 -> 1.3 | N26: =(L26*M26)/1000 -> 18036.245 | O26: =9/1000 -> 0.009 | P26: =(O26*L26)/1000 -> 124.86631 | Q26: =0.03/1000 -> 3e-05 | R26: =(Q26*L26)/1000 -> 0.41622104 | S26: 300 | T26: =G26*S26*assumptions!$D$6 -> 79560 | U26: 20 | V26: 0.47916667 | W26: 68412.4 | X26: =W26*0.65 -> 44468.06 | Y26: =X26*assumptions!$C$8 -> 80042.508 | Z26: =(W26*0.35)*43/3600 -> 286.00184 | AA26: =Z26*assumptions!$C$11 -> 27170.175 | AB26: 3 | AC26: 12 | AD26: 1011 | AE26: 3.5 | AF26: 12075 | AG26: 27105 | AH26: 92000 | AI26: 23000 | AJ26: 21563 | AK26: 7650 | AL26: 20766 | AM26: =Y26+AF26+AG26+AH26+AI26+AJ26+AK26+AL26+AA26 -> 311371.68 | AN26: 257805 | AO26: 70000 | AP26: =AN26+AO26 -> 327805 | AQ26: =(AP26/AM26)-1 -> 0.052777173
B27: 21 GIG | C27: B777-200er | D27: SAF | E27: =52*2 -> 104 | F27: =E27/2 -> 52 | G27: =E27 -> 104 | H27: =_xlfn.XLOOKUP(B27,'[1]Baseline 2025'!$B:$B,'[1]Baseline 2025'!$C:$C) -> 9536 | I27: =E27*H27 -> 991744 | J27: =_xlfn.XLOOKUP(B27,'[1]Baseline 2025'!$B:$B,'[1]Baseline 2025'!$E:$E) -> Long Haul | K27: =_xlfn.XLOOKUP(B27,'[1]Baseline 2025'!$B:$B,'[1]Baseline 2025'!$I:$I)/100 -> 73587.405 | L27: =(K27*100)*0.65 -> 4783181.3 | M27: =1.3 -> 1.3 | N27: =(L27*M27)/1000 -> 6218.1357 | O27: =9/1000 -> 0.009 | P27: =(O27*L27)/1000 -> 43.048632 | Q27: =0.03/1000 -> 3e-05 | R27: =(Q27*L27)/1000 -> 0.14349544 | S27: 300 | T27: =G27*S27*assumptions!$D$6 -> 26520 | U27: 20 | V27: 0.5 | W27: 70757.12 | X27: =W27*0.65 -> 45992.128 | Y27: =X27*assumptions!$C$8 -> 82785.83 | Z27: =(W27*0.35)*43/3600 -> 295.80407 | AA27: =Z27*assumptions!$C$11 -> 28101.387 | AB27: 3 | AC27: 12 | AD27: 1058 | AE27: 3.5 | AF27: 12600 | AG27: 27579 | AH27: 96000 | AI27: 24000 | AJ27: 22500 | AK27: 7650 | AL27: 21523 | AM27: =Y27+AF27+AG27+AH27+AI27+AJ27+AK27+AL27+AA27 -> 322739.22 | AN27: 269790 | AO27: 70000 | AP27: =AN27+AO27 -> 339790 | AQ27: =(AP27/AM27)-1 -> 0.052831456
B28: 22 CPT | C28: B777-200er | D28: SAF | E28: =156*2 -> 312 | F28: =E28/2 -> 156 | G28: =E28 -> 312 | H28: =_xlfn.XLOOKUP(B28,'[1]Baseline 2025'!$B:$B,'[1]Baseline 2025'!$C:$C) -> 9652 | I28: =E28*H28 -> 3011424 | J28: =_xlfn.XLOOKUP(B28,'[1]Baseline 2025'!$B:$B,'[1]Baseline 2025'!$E:$E) -> Long Haul | K28: =_xlfn.XLOOKUP(B28,'[1]Baseline 2025'!$B:$B,'[1]Baseline 2025'!$I:$I)/100 -> 223447.66 | L28: =(K28*100)*0.65 -> 14524098 | M28: =1.3 -> 1.3 | N28: =(L28*M28)/1000 -> 18881.327 | O28: =9/1000 -> 0.009 | P28: =(O28*L28)/1000 -> 130.71688 | Q28: =0.03/1000 -> 3e-05 | R28: =(Q28*L28)/1000 -> 0.43572294 | S28: 300 | T28: =G28*S28*assumptions!$D$6 -> 79560 | U28: 20 | V28: 0.47222222 | W28: 71617.84 | X28: =W28*0.65 -> 46551.596 | Y28: =X28*assumptions!$C$8 -> 83792.873 | Z28: =(W28*0.35)*43/3600 -> 299.40236 | AA28: =Z28*assumptions!$C$11 -> 28443.224 | AB28: 3 | AC28: 12 | AD28: 1026 | AE28: 3.5 | AF28: 11896.5 | AG28: 27753 | AH28: 90640 | AI28: 22660 | AJ28: 21244 | AK28: 7650 | AL28: 21011 | AM28: =Y28+AF28+AG28+AH28+AI28+AJ28+AK28+AL28+AA28 -> 315090.6 | AN28: 261630 | AO28: 70000 | AP28: =AN28+AO28 -> 331630 | AQ28: =(AP28/AM28)-1 -> 0.052490945
N29: =SUM(N7:N28) -> 138904.45 | P29: =SUM(P7:P28) -> 961.6462 | R29: =SUM(R7:R28) -> 3.2054873
A32: yearly fuel ussage [tons] | D32: yearly energy ussage [kW] | G32: yearly costs | I32: yearly revenue
A33: =(E7*X7)/1000 -> 2801.2068 | D33: =E7*Z7 -> 18016.309 | G33: =E7*AM7 -> 37621649 | I33: =E7*AP7 -> 39530400
A34: =(E8*X8)/1000 -> 2005.8238 | D34: =E8*Z8 -> 12900.704 | G34: =E8*AM8 -> 29251714 | I34: =E8*AP8 -> 31056698
A35: =(E9*X9)/1000 -> 2155.1752 | D35: =E9*Z9 -> 13861.276 | G35: =E9*AM9 -> 32588229 | I35: =E9*AP9 -> 34679008
A36: =(E10*X10)/1000 -> 274.38975 | D36: =E10*Z10 -> 1764.7717 | G36: =E10*AM10 -> 12036555 | I36: =E10*AP10 -> 30650620
A37: =(E11*X11)/1000 -> 974.25728 | D37: =E11*Z11 -> 6266.0565 | G37: =E11*AM11 -> 20103766 | I37: =E11*AP11 -> 31238480
A38: =(E12*X12)/1000 -> 346.46048 | D38: =E12*Z12 -> 2228.3035 | G38: =E12*AM12 -> 9593339.7 | I38: =E12*AP12 -> 15433600
A39: =(E13*X13)/1000 -> 653.84647 | D39: =E13*Z13 -> 4205.2946 | G39: =E13*AM13 -> 12020315 | I39: =E13*AP13 -> 15804880
A40: =(E14*X14)/1000 -> 1710.5943 | D40: =E14*Z14 -> 11001.899 | G40: =E14*AM14 -> 21249722 | I40: =E14*AP14 -> 22395100
A41: =(E15*X15)/1000 -> 1604.6591 | D41: =E15*Z15 -> 10320.564 | G41: =E15*AM15 -> 21624760 | I41: =E15*AP15 -> 22766380
A42: =(E16*X16)/1000 -> 577.43413 | D42: =E16*Z16 -> 3713.8392 | G42: =E16*AM16 -> 10734984 | I42: =E16*AP16 -> 15756923
A43: =(E17*X17)/1000 -> 834.45744 | D43: =E17*Z17 -> 5366.9165 | G43: =E17*AM17 -> 12997218 | I43: =E17*AP17 -> 15897700
A44: =(E18*X18)/1000 -> 1238.2272 | D44: =E18*Z18 -> 7963.8115 | G44: =E18*AM18 -> 17206123 | I44: =E18*AP18 -> 18125380
... A54: =(E28*X28)/1000 -> 14524.098 | D54: =E28*Z28 -> 93413.536 | G54: =E28*AM28 -> 98308266 | I54: =E28*AP28 -> 103468560
A56: sum | D56: sum | G56: sum | I56: sum
A57: =SUM(A33:A54) -> 97814.687 | D57: =SUM(D33:D54) -> 629107.28 | G57: =SUM(G33:G54) -> 8.5281558e+08 | I57: =SUM(I33:I54) -> 9.6325838e+08

Sheet Scenario 2 2050
A4: Hybrid
AB5: Crew costs | AJ5: Costs | AP5: Revenue
B6: Destination | C6: Aircraft | D6: Fuel type | E6: Frequency [per year] | F6: # retour | G6: # flights | H6: Lookup: Distance [km] | I6: Total distance travelled [km] | J6: Lookup: Flight Type | K6: Lookup: fuel consumption [l/100km] | L6: Conditional: Total fuel consumption [l] | M6: SAF LFEC CO2 per kg [kg/kg] | N6: Total CO2 emmission [kg] (tons) | O6: NOX per KG | P6: Total NOX emmision(Tons) | Q6: Sox per KG | R6: Total Sox emmission(Ton) | S6: Seats | T6: Passengers per year | U6: Available cargo (Tons) | V6: Flight time | W6: Fuel | X6: Fuel HEFA | Y6: HEFA Costs | Z6: Fuel Equivalent Electrics | AA6: Electricity costs | AB6: Pilot | AC6: Cabin crew | AD6: Ticket price | AE6: Freight rate (Euro/KG) | AF6: CO2 Price(KG/TON) | AG6: Crew costs | AH6: Airport & Navigation charges | AI6: Maintenance costs | AJ6: Maintenance reserve | AK6: Operational lease | AL6: catering and inflight services | AM6: Insurance and overhead | AN6: Total costs | AO6: Passenger revenue | AP6: Cargo revenue | AQ6: Total revenuee
B7: 1 ALC | C7: Fokker 100 | D7: SAF | E7: =7*52*2 -> 728 | F7: =E7/2 -> 364 | G7: =E7 -> 728 | H7: =_xlfn.XLOOKUP(B7,'[1]Baseline 2025'!$B:$B,'[1]Baseline 2025'!$C:$C) -> 1613 | I7: =E7*H7 -> 1174264 | J7: =_xlfn.XLOOKUP(B7,'[1]Baseline 2025'!$B:$B,'[1]Baseline 2025'!$E:$E) -> Short Haul | K7: =_xlfn.XLOOKUP(B7,'[1]Baseline 2025'!$B:$B,'[1]Baseline 2025'!$I:$I)/100 -> 43095.489 | L7: =(K7*100)*0.65 -> 2801206.8 | M7: =1.3 -> 1.3 | N7: =(L7*M7)/1000 -> 3641.5688 | O7: =9/1000 -> 0.009 | P7: =(O7*L7)/1000 -> 25.210861 | Q7: =0.03/1000 -> 3e-05 | R7: =(Q7*L7)/1000 -> 0.084036203 | S7: 100 | T7: =G7*S7*assumptions!$D$6 -> 61880 | U7: 10.9 | V7: 0.11111111 | W7: 5919.71 | X7: =W7*0.65 -> 3847.8115 | Y7: =X7*assumptions!$D$8 -> 5002.155 | Z7: =(W7*0.35)*43/3600 -> 24.747677 | AA7: =Z7*assumptions!$C$11 -> 2351.0293 | AB7: 2 | AC7: 3 | AD7: 190 | AE7: 3.5 | AF7: 1208 | AG7: 1202 | AH7: 6845 | AI7: 21360 | AJ7: 5340 | AK7: 1669 | AL7: 2550 | AM7: 3447 | AN7: =Y7+AG7+AH7+AI7+AJ7+AK7+AL7+AM7+AA7+AF7 -> 50974.184 | AO7: 16150 | AP7: 38150 | AQ7: =AO7+AP7 -> 54300
B8: 2 ARN | C8: Fokker 100 | D8: SAF | E8: =7*52*2 -> 728 | F8: =E8/2 -> 364 | G8: =E8 -> 728 | H8: =_xlfn.XLOOKUP(B8,'[1]Baseline 2025'!$B:$B,'[1]Baseline 2025'!$C:$C) -> 1155 | I8: =E8*H8 -> 840840 | J8: =_xlfn.XLOOKUP(B8,'[1]Baseline 2025'!$B:$B,'[1]Baseline 2025'!$E:$E) -> Short Haul | K8: =_xlfn.XLOOKUP(B8,'[1]Baseline 2025'!$B:$B,'[1]Baseline 2025'!$I:$I)/100 -> 30858.828 | L8: =(K8*100)*0.65 -> 2005823.8 | M8: =1.3 -> 1.3 | N8: =(L8*M8)/1000 -> 2607.571 | O8: =9/1000 -> 0.009 | P8: =(O8*L8)/1000 -> 18.052414 | Q8: =0.03/1000 -> 3e-05 | R8: =(Q8*L8)/1000 -> 0.060174715 | S8: 100 | T8: =G8*S8*assumptions!$D$6 -> 61880 | U8: 10.9 | V8: 0.083333333 | W8: 4238.85 | X8: =W8*0.65 -> 2755.2525 | Y8: =X8*assumptions!$D$8 -> 3581.8283 | Z8: =(W8*0.35)*43/3600 -> 17.720748 | AA8: =Z8*assumptions!$C$11 -> 1683.4711 | AB8: 2 | AC8: 3 | AD8: 117 | AE8: 3 | AF8: 865 | AG8: 900 | AH8: 6158 | AI8: 16000 | AJ8: 4000 | AK8: 1250 | AL8: 2550 | AM8: 2680 | AN8: =Y8+AG8+AH8+AI8+AJ8+AK8+AL8+AM8+AA8+AF8 -> 39668.299 | AO8: 9960.3 | AP8: 32700 | AQ8: =AO8+AP8 -> 42660.3
B9: 3 BCN | C9: Fokker 100 | D9: SAF | E9: =7*52*2 -> 728 | F9: =E9/2 -> 364 | G9: =E9 -> 728 | H9: =_xlfn.XLOOKUP(B9,'[1]Baseline 2025'!$B:$B,'[1]Baseline 2025'!$C:$C) -> 1241 | I9: =E9*H9 -> 903448 | J9: =_xlfn.XLOOKUP(B9,'[1]Baseline 2025'!$B:$B,'[1]Baseline 2025'!$E:$E) -> Short Haul | K9: =_xlfn.XLOOKUP(B9,'[1]Baseline 2025'!$B:$B,'[1]Baseline 2025'!$I:$I)/100 -> 33156.542 | L9: =(K9*100)*0.65 -> 2155175.2 | M9: =1.3 -> 1.3 | N9: =(L9*M9)/1000 -> 2801.7278 | O9: =9/1000 -> 0.009 | P9: =(O9*L9)/1000 -> 19.396577 | Q9: =0.03/1000 -> 3e-05 | R9: =(Q9*L9)/1000 -> 0.064655256 | S9: 100 | T9: =G9*S9*assumptions!$D$6 -> 61880 | U9: 10.9 | V9: 0.097222222 | W9: 4554.47 | X9: =W9*0.65 -> 2960.4055 | Y9: =X9*assumptions!$D$8 -> 3848.5272 | Z9: =(W9*0.35)*43/3600 -> 19.040215 | AA9: =Z9*assumptions!$C$11 -> 1808.8204 | AB9: 2 | AC9: 3 | AD9: 111.6 | AE9: 3.5 | AF9: 929 | AG9: 1048.5 | AH9: 6287 | AI9: 18640 | AJ9: 4660 | AK9: 1456 | AL9: 2550 | AM9: 2985 | AN9: =Y9+AG9+AH9+AI9+AJ9+AK9+AL9+AM9+AA9+AF9 -> 44212.848 | AO9: 9486 | AP9: 38150 | AQ9: =AO9+AP9 -> 47636
B10: 4 BRU | C10: Fokker 100 | D10: SAF | E10: =14*52 -> 728 | F10: =E10/2 -> 364 | G10: =E10 -> 728 | H10: =_xlfn.XLOOKUP(B10,'[1]Baseline 2025'!$B:$B,'[1]Baseline 2025'!$C:$C) -> 158 | I10: =E10*H10 -> 115024 | J10: =_xlfn.XLOOKUP(B10,'[1]Baseline 2025'!$B:$B,'[1]Baseline 2025'!$E:$E) -> Short Haul | K10: =_xlfn.XLOOKUP(B10,'[1]Baseline 2025'!$B:$B,'[1]Baseline 2025'!$I:$I)/100 -> 8442.7616 | L10: =(K10*100)*0.65 -> 548779.5 | M10: =1.3 -> 1.3 | N10: =(L10*M10)/1000 -> 713.41336 | O10: =9/1000 -> 0.009 | P10: =(O10*L10)/1000 -> 4.9390155 | Q10: =0.03/1000 -> 3e-05 | R10: =(Q10*L10)/1000 -> 0.016463385 | S10: 100 | T10: =G10*S10*assumptions!$D$6 -> 61880 | U10: 10.9 | V10: 0.027777778 | W10: 579.86 | X10: =W10*0.65 -> 376.909 | Y10: =X10*assumptions!$D$8 -> 489.9817 | Z10: =(W10*0.35)*43/3600 -> 2.4241369 | AA10: =Z10*assumptions!$C$11 -> 230.29301 | AB10: 2 | AC10: 3 | AD10: 46.5 | AE10: 3.5 | AF10: 118 | AG10: 302 | AH10: 4662 | AI10: 5360 | AJ10: 1340 | AK10: 419 | AL10: 2550 | AM10: 1110 | AN10: =Y10+AG10+AH10+AI10+AJ10+AK10+AL10+AM10+AA10+AF10 -> 16581.275 | AO10: 3952.5 | AP10: 38150 | AQ10: =AO10+AP10 -> 42102.5
B11: 5 BSL | C11: Fokker 100 | D11: SAF | E11: =7*52*2 -> 728 | F11: =E11/2 -> 364 | G11: =E11 -> 728 | H11: =_xlfn.XLOOKUP(B11,'[1]Baseline 2025'!$B:$B,'[1]Baseline 2025'!$C:$C) -> 561 | I11: =E11*H11 -> 408408 | J11: =_xlfn.XLOOKUP(B11,'[1]Baseline 2025'!$B:$B,'[1]Baseline 2025'!$E:$E) -> Short Haul | K11: =_xlfn.XLOOKUP(B11,'[1]Baseline 2025'!$B:$B,'[1]Baseline 2025'!$I:$I)/100 -> 14988.574 | L11: =(K11*100)*0.65 -> 974257.28 | M11: =1.3 -> 1.3 | N11: =(L11*M11)/1000 -> 1266.5345 | O11: =9/1000 -> 0.009 | P11: =(O11*L11)/1000 -> 8.7683156 | Q11: =0.03/1000 -> 3e-05 | R11: =(Q11*L11)/1000 -> 0.029227719 | S11: 100 | T11: =G11*S11*assumptions!$D$6 -> 61880 | U11: 10.9 | V11: 0.055555556 | W11: 2058.87 | X11: =W11*0.65 -> 1338.2655 | Y11: =X11*assumptions!$D$8 -> 1739.7451 | Z11: =(W11*0.35)*43/3600 -> 8.6072204 | AA11: =Z11*assumptions!$C$11 -> 817.68594 | AB11: 2 | AC11: 3 | AD11: 56 | AE11: 3.5 | AF11: 420 | AG11: 598.5 | AH11: 5267 | AI11: 10640 | AJ11: 2660 | AK11: 831 | AL11: 2550 | AM11: 1842 | AN11: =Y11+AG11+AH11+AI11+AJ11+AK11+AL11+AM11+AA11+AF11 -> 27365.931 | AO11: 4760 | AP11: 38150 | AQ11: =AO11+AP11 -> 42910
B12: 6 CDG | C12: Fokker 100 | D12: SAF | E12: =7*52 -> 364 | F12: =E12/2 -> 182 | G12: =E12 -> 364 | H12: =_xlfn.XLOOKUP(B12,'[1]Baseline 2025'!$B:$B,'[1]Baseline 2025'!$C:$C) -> 399 | I12: =E12*H12 -> 145236 | J12: =_xlfn.XLOOKUP(B12,'[1]Baseline 2025'!$B:$B,'[1]Baseline 2025'!$E:$E) -> Short Haul | K12: =_xlfn.XLOOKUP(B12,'[1]Baseline 2025'!$B:$B,'[1]Baseline 2025'!$I:$I)/100 -> 10660.322 | L12: =(K12*100)*0.65 -> 692920.96 | M12: =1.3 -> 1.3 | N12: =(L12*M12)/1000 -> 900.79724 | O12: =9/1000 -> 0.009 | P12: =(O12*L12)/1000 -> 6.2362886 | Q12: =0.03/1000 -> 3e-05 | R12: =(Q12*L12)/1000 -> 0.020787629 | S12: 100 | T12: =G12*S12*assumptions!$D$6 -> 30940 | U12: 10.9 | V12: 0.055555556 | W12: 1464.33 | X12: =W12*0.65 -> 951.8145 | Y12: =X12*assumptions!$D$8 -> 1237.3589 | Z12: =(W12*0.35)*43/3600 -> 6.1217129 | AA12: =Z12*assumptions!$C$11 -> 581.56273 | AB12: 2 | AC12: 3 | AD12: 50 | AE12: 3.5 | AF12: 299 | AG12: 598.5 | AH12: 5024 | AI12: 10640 | AJ12: 2660 | AK12: 831 | AL12: 2550 | AM12: 1757 | AN12: =Y12+AG12+AH12+AI12+AJ12+AK12+AL12+AM12+AA12+AF12 -> 26178.422 | AO12: 4250 | AP12: 38150 | AQ12: =AO12+AP12 -> 42400
B13: 7 DUB | C13: Fokker 100 | D13: SAF | E13: =7*52 -> 364 | F13: =E13/2 -> 182 | G13: =E13 -> 364 | H13: =_xlfn.XLOOKUP(B13,'[1]Baseline 2025'!$B:$B,'[1]Baseline 2025'!$C:$C) -> 753 | I13: =E13*H13 -> 274092 | J13: =_xlfn.XLOOKUP(B13,'[1]Baseline 2025'!$B:$B,'[1]Baseline 2025'!$E:$E) -> Short Haul | K13: =_xlfn.XLOOKUP(B13,'[1]Baseline 2025'!$B:$B,'[1]Baseline 2025'!$I:$I)/100 -> 20118.353 | L13: =(K13*100)*0.65 -> 1307692.9 | M13: =1.3 -> 1.3 | N13: =(L13*M13)/1000 -> 1700.0008 | O13: =9/1000 -> 0.009 | P13: =(O13*L13)/1000 -> 11.769236 | Q13: =0.03/1000 -> 3e-05 | R13: =(Q13*L13)/1000 -> 0.039230788 | S13: 100 | T13: =G13*S13*assumptions!$D$6 -> 30940 | U13: 10.9 | V13: 0.069444444 | W13: 2763.51 | X13: =W13*0.65 -> 1796.2815 | Y13: =X13*assumptions!$D$8 -> 2335.166 | Z13: =(W13*0.35)*43/3600 -> 11.553007 | AA13: =Z13*assumptions!$C$11 -> 1097.5357 | AB13: 2 | AC13: 3 | AD13: 62 | AE13: 3.5 | AF13: 564 | AG13: 747 | AH13: 5555 | AI13: 13280 | AJ13: 3320 | AK13: 1038 | AL13: 2550 | AM13: 2202 | AN13: =Y13+AG13+AH13+AI13+AJ13+AK13+AL13+AM13+AA13+AF13 -> 32688.702 | AO13: 5270 | AP13: 38150 | AQ13: =AO13+AP13 -> 43420
B14: 8 FAO | C14: Fokker 100 | D14: SAF | E14: =7*52 -> 364 | F14: =E14/2 -> 182 | G14: =E14 -> 364 | H14: =_xlfn.XLOOKUP(B14,'[1]Baseline 2025'!$B:$B,'[1]Baseline 2025'!$C:$C) -> 1970 | I14: =E14*H14 -> 717080 | J14: =_xlfn.XLOOKUP(B14,'[1]Baseline 2025'!$B:$B,'[1]Baseline 2025'!$E:$E) -> Short Haul | K14: =_xlfn.XLOOKUP(B14,'[1]Baseline 2025'!$B:$B,'[1]Baseline 2025'!$I:$I)/100 -> 52633.672 | L14: =(K14*100)*0.65 -> 3421188.7 | M14: =1.3 -> 1.3 | N14: =(L14*M14)/1000 -> 4447.5453 | O14: =9/1000 -> 0.009 | P14: =(O14*L14)/1000 -> 30.790698 | Q14: =0.03/1000 -> 3e-05 | R14: =(Q14*L14)/1000 -> 0.10263566 | S14: 100 | T14: =G14*S14*assumptions!$D$6 -> 30940 | U14: 10.9 | V14: 0.125 | W14: 7229.9 | X14: =W14*0.65 -> 4699.435 | Y14: =X14*assumptions!$D$8 -> 6109.2655 | Z14: =(W14*0.35)*43/3600 -> 30.224999 | AA14: =Z14*assumptions!$C$11 -> 2871.3749 | AB14: 2 | AC14: 3 | AD14: 275 | AE14: 3.5 | AF14: 1475 | AG14: 1350 | AH14: 7380 | AI14: 24000 | AJ14: 6000 | AK14: 1875 | AL14: 2550 | AM14: 3893 | AN14: =Y14+AG14+AH14+AI14+AJ14+AK14+AL14+AM14+AA14+AF14 -> 57503.64 | AO14: 23375 | AP14: 38150 | AQ14: =AO14+AP14 -> 61525
B15: 9 LIS | C15: Fokker 100 | D15: SAF | E15: =7*52 -> 364 | F15: =E15/2 -> 182 | G15: =E15 -> 364 | H15: =_xlfn.XLOOKUP(B15,'[1]Baseline 2025'!$B:$B,'[1]Baseline 2025'!$C:$C) -> 1848 | I15: =E15*H15 -> 672672 | J15: =_xlfn.XLOOKUP(B15,'[1]Baseline 2025'!$B:$B,'[1]Baseline 2025'!$E:$E) -> Short Haul | K15: =_xlfn.XLOOKUP(B15,'[1]Baseline 2025'!$B:$B,'[1]Baseline 2025'!$I:$I)/100 -> 49374.125 | L15: =(K15*100)*0.65 -> 3209318.1 | M15: =1.3 -> 1.3 | N15: =(L15*M15)/1000 -> 4172.1135 | O15: =9/1000 -> 0.009 | P15: =(O15*L15)/1000 -> 28.883863 | Q15: =0.03/1000 -> 3e-05 | R15: =(Q15*L15)/1000 -> 0.096279543 | S15: 100 | T15: =G15*S15*assumptions!$D$6 -> 30940 | U15: 10.9 | V15: 0.13194444 | W15: 6782.16 | X15: =W15*0.65 -> 4408.404 | Y15: =X15*assumptions!$D$8 -> 5730.9252 | Z15: =(W15*0.35)*43/3600 -> 28.353197 | AA15: =Z15*assumptions!$C$11 -> 2693.5537 | AB15: 2 | AC15: 3 | AD15: 287 | AE15: 3.5 | AF15: 1384 | AG15: 1425 | AH15: 7197 | AI15: 25333.6 | AJ15: 6333.4 | AK15: 1979 | AL15: 2550 | AM15: 3962 | AN15: =Y15+AG15+AH15+AI15+AJ15+AK15+AL15+AM15+AA15+AF15 -> 58588.479 | AO15: 24395 | AP15: 38150 | AQ15: =AO15+AP15 -> 62545
B16: 10 MUC | C16: Fokker 100 | D16: SAF | E16: =7*52 -> 364 | F16: =E16/2 -> 182 | G16: =E16 -> 364 | H16: =_xlfn.XLOOKUP(B16,'[1]Baseline 2025'!$B:$B,'[1]Baseline 2025'!$C:$C) -> 665 | I16: =E16*H16 -> 242060 | J16: =_xlfn.XLOOKUP(B16,'[1]Baseline 2025'!$B:$B,'[1]Baseline 2025'!$E:$E) -> Short Haul | K16: =_xlfn.XLOOKUP(B16,'[1]Baseline 2025'!$B:$B,'[1]Baseline 2025'!$I:$I)/100 -> 17767.204 | L16: =(K16*100)*0.65 -> 1154868.3 | M16: =1.3 -> 1.3 | N16: =(L16*M16)/1000 -> 1501.3287 | O16: =9/1000 -> 0.009 | P16: =(O16*L16)/1000 -> 10.393814 | Q16: =0.03/1000 -> 3e-05 | R16: =(Q16*L16)/1000 -> 0.034646048 | S16: 100 | T16: =G16*S16*assumptions!$D$6 -> 30940 | U16: 10.9 | V16: 0.059027778 | W16: 2440.55 | X16: =W16*0.65 -> 1586.3575 | Y16: =X16*assumptions!$D$8 -> 2062.2647 | Z16: =(W16*0.35)*43/3600 -> 10.202855 | AA16: =Z16*assumptions!$C$11 -> 969.27121 | AB16: 2 | AC16: 3 | AD16: 60 | AE16: 3.5 | AF16: 498 | AG16: 639 | AH16: 5423 | AI16: 11360 | AJ16: 2840 | AK16: 888 | AL16: 2550 | AM16: 1967 | AN16: =Y16+AG16+AH16+AI16+AJ16+AK16+AL16+AM16+AA16+AF16 -> 29196.536 | AO16: 5138.25 | AP16: 38150 | AQ16: =AO16+AP16 -> 43288.25
B17: 11 OSL | C17: Fokker 100 | D17: SAF | E17: =7*52 -> 364 | F17: =E17/2 -> 182 | G17: =E17 -> 364 | H17: =_xlfn.XLOOKUP(B17,'[1]Baseline 2025'!$B:$B,'[1]Baseline 2025'!$C:$C) -> 961 | I17: =E17*H17 -> 349804 | J17: =_xlfn.XLOOKUP(B17,'[1]Baseline 2025'!$B:$B,'[1]Baseline 2025'!$E:$E) -> Short Haul | K17: =_xlfn.XLOOKUP(B17,'[1]Baseline 2025'!$B:$B,'[1]Baseline 2025'!$I:$I)/100 -> 25675.614 | L17: =(K17*100)*0.65 -> 1668914.9 | M17: =1.3 -> 1.3 | N17: =(L17*M17)/1000 -> 2169.5893 | O17: =9/1000 -> 0.009 | P17: =(O17*L17)/1000 -> 15.020234 | Q17: =0.03/1000 -> 3e-05 | R17: =(Q17*L17)/1000 -> 0.050067447 | S17: 100 | T17: =G17*S17*assumptions!$D$6 -> 30940 | U17: 10.9 | V17: 0.072916667 | W17: 3526.87 | X17: =W17*0.65 -> 2292.4655 | Y17: =X17*assumptions!$D$8 -> 2980.2051 | Z17: =(W17*0.35)*43/3600 -> 14.744276 | AA17: =Z17*assumptions!$C$11 -> 1400.7062 | AB17: 2 | AC17: 3 | AD17: 65 | AE17: 3.5 | AF17: 720 | AG17: 787.5 | AH17: 5867 | AI17: 14000 | AJ17: 3500 | AK17: 1094 | AL17: 2550 | AM17: 2381 | AN17: =Y17+AG17+AH17+AI17+AJ17+AK17+AL17+AM17+AA17+AF17 -> 35280.411 | AO17: 5525 | AP17: 38150 | AQ17: =AO17+AP17 -> 43675
B18: 12 PMI | C18: Fokker 100 | D18: SAF | E18: =7*52 -> 364 | F18: =E18/2 -> 182 | G18: =E18 -> 364 | H18: =_xlfn.XLOOKUP(B18,'[1]Baseline 2025'!$B:$B,'[1]Baseline 2025'!$C:$C) -> 1426 | I18: =E18*H18 -> 519064 | J18: =_xlfn.XLOOKUP(B18,'[1]Baseline 2025'!$B:$B,'[1]Baseline 2025'!$E:$E) -> Short Haul | K18: =_xlfn.XLOOKUP(B18,'[1]Baseline 2025'!$B:$B,'[1]Baseline 2025'!$I:$I)/100 -> 38099.298 | L18: =(K18*100)*0.65 -> 2476454.3 | M18: =1.3 -> 1.3 | N18: =(L18*M18)/1000 -> 3219.3906 | O18: =9/1000 -> 0.009 | P18: =(O18*L18)/1000 -> 22.288089 | Q18: =0.03/1000 -> 3e-05 | R18: =(Q18*L18)/1000 -> 0.07429363 | S18: 100 | T18: =G18*S18*assumptions!$D$6 -> 30940 | U18: 10.9 | V18: 0.10069444 | W18: 5233.42 | X18: =W18*0.65 -> 3401.723 | Y18: =X18*assumptions!$D$8 -> 4422.2399 | Z18: =(W18*0.35)*43/3600 -> 21.878603 | AA18: =Z18*assumptions!$C$11 -> 2078.4673 | AB18: 2 | AC18: 3 | AD18: 137 | AE18: 3.5 | AF18: 1068 | AG18: 1089 | AH18: 6564 | AI18: 19360 | AJ18: 4840 | AK18: 1513 | AL18: 2550 | AM18: 3152 | AN18: =Y18+AG18+AH18+AI18+AJ18+AK18+AL18+AM18+AA18+AF18 -> 46636.707 | AO18: 11645 | AP18: 38150 | AQ18: =AO18+AP18 -> 49795
B19: 13 VIE | C19: Fokker 100 | D19: SAF | E19: =7*52 -> 364 | F19: =E19/2 -> 182 | G19: =E19 -> 364 | H19: =_xlfn.XLOOKUP(B19,'[1]Baseline 2025'!$B:$B,'[1]Baseline 2025'!$C:$C) -> 962 | I19: =E19*H19 -> 350168 | J19: =_xlfn.XLOOKUP(B19,'[1]Baseline 2025'!$B:$B,'[1]Baseline 2025'!$E:$E) -> Short Haul | K19: =_xlfn.XLOOKUP(B19,'[1]Baseline 2025'!$B:$B,'[1]Baseline 2025'!$I:$I)/100 -> 25702.331 | L19: =(K19*100)*0.65 -> 1670651.5 | M19: =1.3 -> 1.3 | N19: =(L19*M19)/1000 -> 2171.847 | O19: =9/1000 -> 0.009 | P19: =(O19*L19)/1000 -> 15.035864 | Q19: =0.03/1000 -> 3e-05 | R19: =(Q19*L19)/1000 -> 0.050119546 | S19: 100 | T19: =G19*S19*assumptions!$D$6 -> 30940 | U19: 10.9 | V19: 0.072916667 | W19: 3530.54 | X19: =W19*0.65 -> 2294.851 | Y19: =X19*assumptions!$D$8 -> 2983.3063 | Z19: =(W19*0.35)*43/3600 -> 14.759619 | AA19: =Z19*assumptions!$C$11 -> 1402.1638 | AB19: 2 | AC19: 3 | AD19: 68.2 | AE19: 3.5 | AF19: 721 | AG19: 787.5 | AH19: 5868 | AI19: 14000 | AJ19: 3500 | AK19: 1094 | AL19: 2550 | AM19: 2382 | AN19: =Y19+AG19+AH19+AI19+AJ19+AK19+AL19+AM19+AA19+AF19 -> 35287.97 | AO19: 5780 | AP19: 38150 | AQ19: =AO19+AP19 -> 43930
B20: 14 WAW | C20: Fokker 100 | D20: SAF | E20: =7*52 -> 364 | F20: =E20/2 -> 182 | G20: =E20 -> 364 | H20: =_xlfn.XLOOKUP(B20,'[1]Baseline 2025'!$B:$B,'[1]Baseline 2025'!$C:$C) -> 1105 | I20: =E20*H20 -> 402220 | J20: =_xlfn.XLOOKUP(B20,'[1]Baseline 2025'!$B:$B,'[1]Baseline 2025'!$E:$E) -> Short Haul | K20: =_xlfn.XLOOKUP(B20,'[1]Baseline 2025'!$B:$B,'[1]Baseline 2025'!$I:$I)/100 -> 29522.948 | L20: =(K20*100)*0.65 -> 1918991.6 | M20: =1.3 -> 1.3 | N20: =(L20*M20)/1000 -> 2494.6891 | O20: =9/1000 -> 0.009 | P20: =(O20*L20)/1000 -> 17.270925 | Q20: =0.03/1000 -> 3e-05 | R20: =(Q20*L20)/1000 -> 0.057569749 | S20: 100 | T20: =G20*S20*assumptions!$D$6 -> 30940 | U20: 10.9 | V20: 0.079861111 | W20: 4055.35 | X20: =W20*0.65 -> 2635.9775 | Y20: =X20*assumptions!$D$8 -> 3426.7708 | Z20: =(W20*0.35)*43/3600 -> 16.953616 | AA20: =Z20*assumptions!$C$11 -> 1610.5935 | AB20: 2 | AC20: 3 | AD20: 74.25 | AE20: 3.5 | AF20: 828 | AG20: 864 | AH20: 6083 | AI20: 15360 | AJ20: 3840 | AK20: 1200 | AL20: 2550 | AM20: 2590 | AN20: =Y20+AG20+AH20+AI20+AJ20+AK20+AL20+AM20+AA20+AF20 -> 38352.364 | AO20: 6311.25 | AP20: 38150 | AQ20: =AO20+AP20 -> 44461.25
B21: 15 ZRH | C21: Fokker 100 | D21: SAF | E21: =14*52*2 -> 1456 | F21: =E21/2 -> 728 | G21: =E21 -> 1456 | H21: =_xlfn.XLOOKUP(B21,'[1]Baseline 2025'!$B:$B,'[1]Baseline 2025'!$C:$C) -> 603 | I21: =E21*H21 -> 877968 | J21: =_xlfn.XLOOKUP(B21,'[1]Baseline 2025'!$B:$B,'[1]Baseline 2025'!$E:$E) -> Short Haul | K21: =_xlfn.XLOOKUP(B21,'[1]Baseline 2025'!$B:$B,'[1]Baseline 2025'!$I:$I)/100 -> 32221.426 | L21: =(K21*100)*0.65 -> 2094392.7 | M21: =1.3 -> 1.3 | N21: =(L21*M21)/1000 -> 2722.7105 | O21: =9/1000 -> 0.009 | P21: =(O21*L21)/1000 -> 18.849534 | Q21: =0.03/1000 -> 3e-05 | R21: =(Q21*L21)/1000 -> 0.06283178 | S21: 100 | T21: =G21*S21*assumptions!$D$6 -> 123760 | U21: 10.9 | V21: 0.059027778 | W21: 2213.01 | X21: =W21*0.65 -> 1438.4565 | Y21: =X21*assumptions!$D$8 -> 1869.9935 | Z21: =(W21*0.35)*43/3600 -> 9.2516112 | AA21: =Z21*assumptions!$C$11 -> 878.90307 | AB21: 2 | AC21: 3 | AD21: 55 | AE21: 3.5 | AF21: 452 | AG21: 639 | AH21: 5330 | AI21: 11360 | AJ21: 2840 | AK21: 888 | AL21: 2550 | AM21: 1935 | AN21: =Y21+AG21+AH21+AI21+AJ21+AK21+AL21+AM21+AA21+AF21 -> 28742.897 | AO21: 4675 | AP21: 38150 | AQ21: =AO21+AP21 -> 42825
B22: 16 BKK | C22: B777-200er | D22: SAF | E22: =3*52*2 -> 312 | F22: =E22/2 -> 156 | G22: =E22 -> 312 | H22: =_xlfn.XLOOKUP(B22,'[1]Baseline 2025'!$B:$B,'[1]Baseline 2025'!$C:$C) -> 9217 | I22: =E22*H22 -> 2875704 | J22: =_xlfn.XLOOKUP(B22,'[1]Baseline 2025'!$B:$B,'[1]Baseline 2025'!$E:$E) -> Long Haul | K22: =_xlfn.XLOOKUP(B22,'[1]Baseline 2025'!$B:$B,'[1]Baseline 2025'!$I:$I)/100 -> 213377.24 | L22: =(K22*100)*0.65 -> 13869520 | M22: =1.3 -> 1.3 | N22: =(L22*M22)/1000 -> 18030.377 | O22: =9/1000 -> 0.009 | P22: =(O22*L22)/1000 -> 124.82568 | Q22: =0.03/1000 -> 3e-05 | R22: =(Q22*L22)/1000 -> 0.41608561 | S22: 300 | T22: =G22*S22*assumptions!$D$6 -> 79560 | U22: 20 | V22: 0.46875 | W22: 68390.14 | X22: =W22*0.65 -> 44453.591 | Y22: =X22*assumptions!$D$8 -> 57789.668 | Z22: =(W22*0.35)*43/3600 -> 285.90878 | AA22: =Z22*assumptions!$C$11 -> 27161.334 | AB22: 3 | AC22: 12 | AD22: 997 | AE22: 3.5 | AF22: 13959 | AG22: 11812.5 | AH22: 27101 | AI22: 90000 | AJ22: 22500 | AK22: 21094 | AL22: 7650 | AM22: 20532 | AN22: =Y22+AG22+AH22+AI22+AJ22+AK22+AL22+AM22+AA22+AF22 -> 299599.5 | AO22: 254235 | AP22: 70000 | AQ22: =AO22+AP22 -> 324235
B23: 17 MFM | C23: B777-200er | D23: SAF | E23: =3*52*2 -> 312 | F23: =E23/2 -> 156 | G23: =E23 -> 312 | H23: =_xlfn.XLOOKUP(B23,'[1]Baseline 2025'!$B:$B,'[1]Baseline 2025'!$C:$C) -> 9285 | I23: =E23*H23 -> 2896920 | J23: =_xlfn.XLOOKUP(B23,'[1]Baseline 2025'!$B:$B,'[1]Baseline 2025'!$E:$E) -> Long Haul | K23: =_xlfn.XLOOKUP(B23,'[1]Baseline 2025'!$B:$B,'[1]Baseline 2025'!$I:$I)/100 -> 214951.46 | L23: =(K23*100)*0.65 -> 13971845 | M23: =1.3 -> 1.3 | N23: =(L23*M23)/1000 -> 18163.399 | O23: =9/1000 -> 0.009 | P23: =(O23*L23)/1000 -> 125.74661 | Q23: =0.03/1000 -> 3e-05 | R23: =(Q23*L23)/1000 -> 0.41915535 | S23: 300 | T23: =G23*S23*assumptions!$D$6 -> 79560 | U23: 20 | V23: 0.46875 | W23: 68894.7 | X23: =W23*0.65 -> 44781.555 | Y23: =X23*assumptions!$D$8 -> 58216.022 | Z23: =(W23*0.35)*43/3600 -> 288.01812 | AA23: =Z23*assumptions!$C$11 -> 27361.721 | AB23: 3 | AC23: 12 | AD23: 1000 | AE23: 3.5 | AF23: 14062 | AG23: 11812.5 | AH23: 27203 | AI23: 90000 | AJ23: 22500 | AK23: 21094 | AL23: 7650 | AM23: 20596 | AN23: =Y23+AG23+AH23+AI23+AJ23+AK23+AL23+AM23+AA23+AF23 -> 300495.24 | AO23: 255000 | AP23: 70000 | AQ23: =AO23+AP23 -> 325000
B24: 18 HAN | C24: B777-200er | D24: SAF | E24: =52*2 -> 104 | F24: =E24/2 -> 52 | G24: =E24 -> 104 | H24: =_xlfn.XLOOKUP(B24,'[1]Baseline 2025'!$B:$B,'[1]Baseline 2025'!$C:$C) -> 8886 | I24: =E24*H24 -> 924144 | J24: =_xlfn.XLOOKUP(B24,'[1]Baseline 2025'!$B:$B,'[1]Baseline 2025'!$E:$E) -> Long Haul | K24: =_xlfn.XLOOKUP(B24,'[1]Baseline 2025'!$B:$B,'[1]Baseline 2025'!$I:$I)/100 -> 68571.485 | L24: =(K24*100)*0.65 -> 4457146.5 | M24: =1.3 -> 1.3 | N24: =(L24*M24)/1000 -> 5794.2905 | O24: =9/1000 -> 0.009 | P24: =(O24*L24)/1000 -> 40.114319 | Q24: =0.03/1000 -> 3e-05 | R24: =(Q24*L24)/1000 -> 0.1337144 | S24: 300 | T24: =G24*S24*assumptions!$D$6 -> 26520 | U24: 20 | V24: 0.45833333 | W24: 65934.12 | X24: =W24*0.65 -> 42857.178 | Y24: =X24*assumptions!$D$8 -> 55714.331 | Z24: =(W24*0.35)*43/3600 -> 275.64125 | AA24: =Z24*assumptions!$C$11 -> 26185.919 | AB24: 3 | AC24: 12 | AD24: 963 | AE24: 3.5 | AF24: 13457 | AG24: 11550 | AH24: 26604 | AI24: 88000 | AJ24: 22000 | AK24: 20625 | AL24: 7650 | AM24: 19990 | AN24: =Y24+AG24+AH24+AI24+AJ24+AK24+AL24+AM24+AA24+AF24 -> 291776.25 | AO24: 245565 | AP24: 70000 | AQ24: =AO24+AP24 -> 315565
B25: 19 PTY | C25: B777-200er | D25: SAF | E25: =156*2 -> 312 | F25: =E25/2 -> 156 | G25: =E25 -> 312 | H25: =_xlfn.XLOOKUP(B25,'[1]Baseline 2025'!$B:$B,'[1]Baseline 2025'!$C:$C) -> 8818 | I25: =E25*H25 -> 2751216 | J25: =_xlfn.XLOOKUP(B25,'[1]Baseline 2025'!$B:$B,'[1]Baseline 2025'!$E:$E) -> Long Haul | K25: =_xlfn.XLOOKUP(B25,'[1]Baseline 2025'!$B:$B,'[1]Baseline 2025'!$I:$I)/100 -> 204140.23 | L25: =(K25*100)*0.65 -> 13269115 | M25: =1.3 -> 1.3 | N25: =(L25*M25)/1000 -> 17249.849 | O25: =9/1000 -> 0.009 | P25: =(O25*L25)/1000 -> 119.42203 | Q25: =0.03/1000 -> 3e-05 | R25: =(Q25*L25)/1000 -> 0.39807344 | S25: 300 | T25: =G25*S25*assumptions!$D$6 -> 79560 | U25: 20 | V25: 0.46527778 | W25: 65429.56 | X25: =W25*0.65 -> 42529.214 | Y25: =X25*assumptions!$D$8 -> 55287.978 | Z25: =(W25*0.35)*43/3600 -> 273.53191 | AA25: =Z25*assumptions!$C$11 -> 25985.532 | AB25: 3 | AC25: 12 | AD25: 969 | AE25: 3.5 | AF25: 13354 | AG25: 11728.5 | AH25: 26502 | AI25: 89360 | AJ25: 22340 | AK25: 20944 | AL25: 7650 | AM25: 20084 | AN25: =Y25+AG25+AH25+AI25+AJ25+AK25+AL25+AM25+AA25+AF25 -> 293236.01 | AO25: 247095 | AP25: 70000 | AQ25: =AO25+AP25 -> 317095
B26: 20 MEX | C26: B777-200er | D26: SAF | E26: =156*2 -> 312 | F26: =E26/2 -> 156 | G26: =E26 -> 312 | H26: =_xlfn.XLOOKUP(B26,'[1]Baseline 2025'!$B:$B,'[1]Baseline 2025'!$C:$C) -> 9220 | I26: =E26*H26 -> 2876640 | J26: =_xlfn.XLOOKUP(B26,'[1]Baseline 2025'!$B:$B,'[1]Baseline 2025'!$E:$E) -> Long Haul | K26: =_xlfn.XLOOKUP(B26,'[1]Baseline 2025'!$B:$B,'[1]Baseline 2025'!$I:$I)/100 -> 213446.69 | L26: =(K26*100)*0.65 -> 13874035 | M26: =1.3 -> 1.3 | N26: =(L26*M26)/1000 -> 18036.245 | O26: =9/1000 -> 0.009 | P26: =(O26*L26)/1000 -> 124.86631 | Q26: =0.03/1000 -> 3e-05 | R26: =(Q26*L26)/1000 -> 0.41622104 | S26: 300 | T26: =G26*S26*assumptions!$D$6 -> 79560 | U26: 20 | V26: 0.47916667 | W26: 68412.4 | X26: =W26*0.65 -> 44468.06 | Y26: =X26*assumptions!$D$8 -> 57808.478 | Z26: =(W26*0.35)*43/3600 -> 286.00184 | AA26: =Z26*assumptions!$C$11 -> 27170.175 | AB26: 3 | AC26: 12 | AD26: 1011 | AE26: 3.5 | AF26: 13963 | AG26: 12075 | AH26: 27105 | AI26: 92000 | AJ26: 23000 | AK26: 21563 | AL26: 7650 | AM26: 20766 | AN26: =Y26+AG26+AH26+AI26+AJ26+AK26+AL26+AM26+AA26+AF26 -> 303100.65 | AO26: 257805 | AP26: 70000 | AQ26: =AO26+AP26 -> 327805
B27: 21 GIG | C27: B777-200er | D27: SAF | E27: =52*2 -> 104 | F27: =E27/2 -> 52 | G27: =E27 -> 104 | H27: =_xlfn.XLOOKUP(B27,'[1]Baseline 2025'!$B:$B,'[1]Baseline 2025'!$C:$C) -> 9536 | I27: =E27*H27 -> 991744 | J27: =_xlfn.XLOOKUP(B27,'[1]Baseline 2025'!$B:$B,'[1]Baseline 2025'!$E:$E) -> Long Haul | K27: =_xlfn.XLOOKUP(B27,'[1]Baseline 2025'!$B:$B,'[1]Baseline 2025'!$I:$I)/100 -> 73587.405 | L27: =(K27*100)*0.65 -> 4783181.3 | M27: =1.3 -> 1.3 | N27: =(L27*M27)/1000 -> 6218.1357 | O27: =9/1000 -> 0.009 | P27: =(O27*L27)/1000 -> 43.048632 | Q27: =0.03/1000 -> 3e-05 | R27: =(Q27*L27)/1000 -> 0.14349544 | S27: 300 | T27: =G27*S27*assumptions!$D$6 -> 26520 | U27: 20 | V27: 0.5 | W27: 70757.12 | X27: =W27*0.65 -> 45992.128 | Y27: =X27*assumptions!$D$8 -> 59789.766 | Z27: =(W27*0.35)*43/3600 -> 295.80407 | AA27: =Z27*assumptions!$C$11 -> 28101.387 | AB27: 3 | AC27: 12 | AD27: 1058 | AE27: 3.5 | AF27: 14441 | AG27: 12600 | AH27: 27579 | AI27: 96000 | AJ27: 24000 | AK27: 22500 | AL27: 7650 | AM27: 21523 | AN27: =Y27+AG27+AH27+AI27+AJ27+AK27+AL27+AM27+AA27+AF27 -> 314184.15 | AO27: 269790 | AP27: 70000 | AQ27: =AO27+AP27 -> 339790
B28: 22 CPT | C28: B777-200er | D28: SAF | E28: =156*2 -> 312 | F28: =E28/2 -> 156 | G28: =E28 -> 312 | H28: =_xlfn.XLOOKUP(B28,'[1]Baseline 2025'!$B:$B,'[1]Baseline 2025'!$C:$C) -> 9652 | I28: =E28*H28 -> 3011424 | J28: =_xlfn.XLOOKUP(B28,'[1]Baseline 2025'!$B:$B,'[1]Baseline 2025'!$E:$E) -> Long Haul | K28: =_xlfn.XLOOKUP(B28,'[1]Baseline 2025'!$B:$B,'[1]Baseline 2025'!$I:$I)/100 -> 223447.66 | L28: =(K28*100)*0.65 -> 14524098 | M28: =1.3 -> 1.3 | N28: =(L28*M28)/1000 -> 18881.327 | O28: =9/1000 -> 0.009 | P28: =(O28*L28)/1000 -> 130.71688 | Q28: =0.03/1000 -> 3e-05 | R28: =(Q28*L28)/1000 -> 0.43572294 | S28: 300 | T28: =G28*S28*assumptions!$D$6 -> 79560 | U28: 20 | V28: 0.47222222 | W28: 71617.84 | X28: =W28*0.65 -> 46551.596 | Y28: =X28*assumptions!$D$8 -> 60517.075 | Z28: =(W28*0.35)*43/3600 -> 299.40236 | AA28: =Z28*assumptions!$C$11 -> 28443.224 | AB28: 3 | AC28: 12 | AD28: 1026 | AE28: 3.5 | AF28: 14617 | AG28: 11896.5 | AH28: 27753 | AI28: 90640 | AJ28: 22660 | AK28: 21244 | AL28: 7650 | AM28: 21014 | AN28: =Y28+AG28+AH28+AI28+AJ28+AK28+AL28+AM28+AA28+AF28 -> 306434.8 | AO28: 261630 | AP28: 70000 | AQ28: =AO28+AP28 -> 331630
N29: =SUM(N7:N28) -> 138904.45 | P29: =SUM(P7:P28) -> 961.6462 | R29: =SUM(R7:R28) -> 3.2054873
A32: yearly fuel ussage [tons] | D32: yearly energy ussage [kW] | G32: yearly costs | I32: yearly revenue
A33: =(E7*X7)/1000 -> 2801.2068 | D33: =E7*Z7 -> 18016.309 | G33: =E7*AN7 -> 37109206 | I33: =E7*AQ7 -> 39530400
A34: =(E8*X8)/1000 -> 2005.8238 | D34: =E8*Z8 -> 12900.704 | G34: =E8*AN8 -> 28878522 | I34: =E8*AQ8 -> 31056698
A35: =(E9*X9)/1000 -> 2155.1752 | D35: =E9*Z9 -> 13861.276 | G35: =E9*AN9 -> 32186953 | I35: =E9*AQ9 -> 34679008
A36: =(E10*X10)/1000 -> 274.38975 | D36: =E10*Z10 -> 1764.7717 | G36: =E10*AN10 -> 12071168 | I36: =E10*AQ10 -> 30650620
A37: =(E11*X11)/1000 -> 974.25728 | D37: =E11*Z11 -> 6266.0565 | G37: =E11*AN11 -> 19922398 | I37: =E11*AQ11 -> 31238480
A38: =(E12*X12)/1000 -> 346.46048 | D38: =E12*Z12 -> 2228.3035 | G38: =E12*AN12 -> 9528945.5 | I38: =E12*AQ12 -> 15433600
A39: =(E13*X13)/1000 -> 653.84647 | D39: =E13*Z13 -> 4205.2946 | G39: =E13*AN13 -> 11898687 | I39: =E13*AQ13 -> 15804880
A40: =(E14*X14)/1000 -> 1710.5943 | D40: =E14*Z14 -> 11001.899 | G40: =E14*AN14 -> 20931325 | I40: =E14*AQ14 -> 22395100
A41: =(E15*X15)/1000 -> 1604.6591 | D41: =E15*Z15 -> 10320.564 | G41: =E15*AN15 -> 21326206 | I41: =E15*AQ15 -> 22766380
A42: =(E16*X16)/1000 -> 577.43413 | D42: =E16*Z16 -> 3713.8392 | G42: =E16*AN16 -> 10627539 | I42: =E16*AQ16 -> 15756923
A43: =(E17*X17)/1000 -> 834.45744 | D43: =E17*Z17 -> 5366.9165 | G43: =E17*AN17 -> 12842070 | I43: =E17*AQ17 -> 15897700
A44: =(E18*X18)/1000 -> 1238.2272 | D44: =E18*Z18 -> 7963.8115 | G44: =E18*AN18 -> 16975761 | I44: =E18*AQ18 -> 18125380
... A54: =(E28*X28)/1000 -> 14524.098 | D54: =E28*Z28 -> 93413.536 | G54: =E28*AN28 -> 95607657 | I54: =E28*AQ28 -> 103468560
A56: sum | D56: sum | G56: sum | I56: sum
A57: =SUM(A33:A54) -> 97814.687 | D57: =SUM(D33:D54) -> 629107.28 | G57: =SUM(G33:G54) -> 8.3486766e+08 | I57: =SUM(I33:I54) -> 9.6325838e+08

Sheet Scenario 3 2025
A4: Hydrogen
Z5: Crew costs | AG5: Costs | AM5: Revenu
B6: Destination | C6: Aircraft | D6: Fuel type | E6: Frequency [per year] | F6: # retour | G6: # flights | H6: Lookup: Distance [km] | I6: Total distance travelled [km] | J6: Lookup: Flight Type | K6: Lookup: fuel consumption [l/100km] | L6: Conditional: Total fuel consumption [l] | M6: SAF LFEC CO2 per kg [kg/kg] | N6: Total CO2 emmission [kg] (tons) | O6: NOX per KG | P6: Total NOX emmision(Tons) | Q6: Sox per KG | R6: Total Sox emmission(Ton) | S6: Seats | T6: Passengers per year | U6: Available cargo (Tons) | V6: Flight time | W6: Fuel | X6: Hydrogen | Y6: Hydrogen costs | Z6: Pilot | AA6: Cabin crew | AB6: Ticket price | AC6: Freight rate (Euro/KG) | AD6: Crew costs | AE6: Airport & Navigation charges | AF6: Maintenance costs | AG6: Maintenance reserve | AH6: Operational lease | AI6: catering and inflight services | AJ6: Insurance and overhead | AK6: Total costs | AL6: Passenger revenue | AM6: Cargo revenue | AN6: Total revenuee | AO6: marge
B7: 1 ALC | C7: Fokker 100 | D7: SAF | E7: =7*52*2 -> 728 | F7: =E7/2 -> 364 | G7: =E7 -> 728 | H7: =_xlfn.XLOOKUP(B7,'[1]Baseline 2025'!$B:$B,'[1]Baseline 2025'!$C:$C) -> 1613 | I7: =E7*H7 -> 1174264 | J7: =_xlfn.XLOOKUP(B7,'[1]Baseline 2025'!$B:$B,'[1]Baseline 2025'!$E:$E) -> Short Haul | K7: =_xlfn.XLOOKUP(B7,'[1]Baseline 2025'!$B:$B,'[1]Baseline 2025'!$I:$I)/100 -> 43095.489 | L7: =(K7*100)*43/120 -> 1544255 | M7: 3.97 | N7: =(L7*M7)/1000 -> 6130.6924 | O7: =9/1000 -> 0.009 | P7: =(O7*L7)/1000 -> 13.898295 | Q7: 0 | R7: =Q7*L7 -> 0 | S7: 100 | T7: =G7*S7*assumptions!$D$6 -> 61880 | U7: 10.9 | V7: 0.11111111 | W7: 5919.71 | X7: =W7*43/120 -> 2121.2294 | Y7: =X7*17 -> 36060.9 | Z7: 2 | AA7: 3 | AB7: 545 | AC7: 3.5 | AD7: 1201.5 | AE7: 6845 | AF7: 21360 | AG7: 5340 | AH7: 1669 | AI7: 2550 | AJ7: 5353 | AK7: =Y7+AD7+AE7+AF7+AG7+AH7+AI7+AJ7 -> 80379.4 | AL7: 46325 | AM7: 38150 | AN7: =AL7+AM7 -> 84475 | AO7: =(AN7/AK7)-1 -> 0.050953353
B8: 2 ARN | C8: Fokker 100 | D8: SAF | E8: =7*52*2 -> 728 | F8: =E8/2 -> 364 | G8: =E8 -> 728 | H8: =_xlfn.XLOOKUP(B8,'[1]Baseline 2025'!$B:$B,'[1]Baseline 2025'!$C:$C) -> 1155 | I8: =E8*H8 -> 840840 | J8: =_xlfn.XLOOKUP(B8,'[1]Baseline 2025'!$B:$B,'[1]Baseline 2025'!$E:$E) -> Short Haul | K8: =_xlfn.XLOOKUP(B8,'[1]Baseline 2025'!$B:$B,'[1]Baseline 2025'!$I:$I)/100 -> 30858.828 | L8: =(K8*100)*43/120 -> 1105774.7 | M8: 3.97 | N8: =(L8*M8)/1000 -> 4389.9254 | O8: =9/1000 -> 0.009 | P8: =(O8*L8)/1000 -> 9.951972 | Q8: 0 | R8: =Q8*L8 -> 0 | S8: 100 | T8: =G8*S8*assumptions!$D$6 -> 61880 | U8: 10.9 | V8: 0.083333333 | W8: 4238.85 | X8: =W8*43/120 -> 1518.9213 | Y8: =X8*17 -> 25821.661 | Z8: 2 | AA8: 3 | AB8: 370 | AC8: 3 | AD8: 900 | AE8: 6158 | AF8: 16000 | AG8: 4000 | AH8: 1250 | AI8: 2550 | AJ8: 4050 | AK8: =Y8+AD8+AE8+AF8+AG8+AH8+AI8+AJ8 -> 60729.661 | AL8: 31450 | AM8: 32700 | AN8: =AL8+AM8 -> 64150 | AO8: =(AN8/AK8)-1 -> 0.056320728
B9: 3 BCN | C9: Fokker 100 | D9: SAF | E9: =7*52*2 -> 728 | F9: =E9/2 -> 364 | G9: =E9 -> 728 | H9: =_xlfn.XLOOKUP(B9,'[1]Baseline 2025'!$B:$B,'[1]Baseline 2025'!$C:$C) -> 1241 | I9: =E9*H9 -> 903448 | J9: =_xlfn.XLOOKUP(B9,'[1]Baseline 2025'!$B:$B,'[1]Baseline 2025'!$E:$E) -> Short Haul | K9: =_xlfn.XLOOKUP(B9,'[1]Baseline 2025'!$B:$B,'[1]Baseline 2025'!$I:$I)/100 -> 33156.542 | L9: =(K9*100)*43/120 -> 1188109.4 | M9: 3.97 | N9: =(L9*M9)/1000 -> 4716.7943 | O9: =9/1000 -> 0.009 | P9: =(O9*L9)/1000 -> 10.692985 | Q9: 0 | R9: =Q9*L9 -> 0 | S9: 100 | T9: =G9*S9*assumptions!$D$6 -> 61880 | U9: 10.9 | V9: 0.097222222 | W9: 4554.47 | X9: =W9*43/120 -> 1632.0184 | Y9: =X9*17 -> 27744.313 | Z9: 2 | AA9: 3 | AB9: 380 | AC9: 3.5 | AD9: 1048.5 | AE9: 6287 | AF9: 18664 | AG9: 4666 | AH9: 1458 | AI9: 2550 | AJ9: 4460 | AK9: =Y9+AD9+AE9+AF9+AG9+AH9+AI9+AJ9 -> 66877.813 | AL9: 32300 | AM9: 38150 | AN9: =AL9+AM9 -> 70450 | AO9: =(AN9/AK9)-1 -> 0.053413632
B10: 4 BRU | C10: Fokker 100 | D10: SAF | E10: =14*52 -> 728 | F10: =E10/2 -> 364 | G10: =E10 -> 728 | H10: =_xlfn.XLOOKUP(B10,'[1]Baseline 2025'!$B:$B,'[1]Baseline 2025'!$C:$C) -> 158 | I10: =E10*H10 -> 115024 | J10: =_xlfn.XLOOKUP(B10,'[1]Baseline 2025'!$B:$B,'[1]Baseline 2025'!$E:$E) -> Short Haul | K10: =_xlfn.XLOOKUP(B10,'[1]Baseline 2025'!$B:$B,'[1]Baseline 2025'!$I:$I)/100 -> 8442.7616 | L10: =(K10*100)*43/120 -> 302532.29 | M10: 3.97 | N10: =(L10*M10)/1000 -> 1201.0532 | O10: =9/1000 -> 0.009 | P10: =(O10*L10)/1000 -> 2.7227906 | Q10: 0 | R10: =Q10*L10 -> 0 | S10: 100 | T10: =G10*S10*assumptions!$D$6 -> 61880 | U10: 10.9 | V10: 0.027777778 | W10: 579.86 | X10: =W10*43/120 -> 207.78317 | Y10: =X10*17 -> 3532.3138 | Z10: 2 | AA10: 3 | AB10: 120 | AC10: 3.5 | AD10: 297 | AE10: 4662 | AF10: 5280 | AG10: 1320 | AH10: 413 | AI10: 2550 | AJ10: 1290 | AK10: =Y10+AD10+AE10+AF10+AG10+AH10+AI10+AJ10 -> 19344.314 | AL10: 10200 | AM10: 38150 | AN10: =AL10+AM10 -> 48350 | AO10: 0.6
B11: 5 BSL | C11: Fokker 100 | D11: SAF | E11: =7*52*2 -> 728 | F11: =E11/2 -> 364 | G11: =E11 -> 728 | H11: =_xlfn.XLOOKUP(B11,'[1]Baseline 2025'!$B:$B,'[1]Baseline 2025'!$C:$C) -> 561 | I11: =E11*H11 -> 408408 | J11: =_xlfn.XLOOKUP(B11,'[1]Baseline 2025'!$B:$B,'[1]Baseline 2025'!$E:$E) -> Short Haul | K11: =_xlfn.XLOOKUP(B11,'[1]Baseline 2025'!$B:$B,'[1]Baseline 2025'!$I:$I)/100 -> 14988.574 | L11: =(K11*100)*43/120 -> 537090.55 | M11: 3.97 | N11: =(L11*M11)/1000 -> 2132.2495 | O11: =9/1000 -> 0.009 | P11: =(O11*L11)/1000 -> 4.833815 | Q11: 0 | R11: =Q11*L11 -> 0 | S11: 100 | T11: =G11*S11*assumptions!$D$6 -> 61880 | U11: 10.9 | V11: 0.055555556 | W11: 2058.87 | X11: =W11*43/120 -> 737.76175 | Y11: =X11*17 -> 12541.95 | Z11: 2 | AA11: 3 | AB11: 72 | AC11: 3.5 | AD11: 598.5 | AE11: 5267 | AF11: 10640 | AG11: 2660 | AH11: 831 | AI11: 2550 | AJ11: 2508 | AK11: =Y11+AD11+AE11+AF11+AG11+AH11+AI11+AJ11 -> 37596.45 | AL11: 6120 | AM11: 38150 | AN11: =AL11+AM11 -> 44270 | AO11: =(AN11/AK11)-1 -> 0.1775048
B12: 6 CDG | C12: Fokker 100 | D12: SAF | E12: =7*52 -> 364 | F12: =E12/2 -> 182 | G12: =E12 -> 364 | H12: =_xlfn.XLOOKUP(B12,'[1]Baseline 2025'!$B:$B,'[1]Baseline 2025'!$C:$C) -> 399 | I12: =E12*H12 -> 145236 | J12: =_xlfn.XLOOKUP(B12,'[1]Baseline 2025'!$B:$B,'[1]Baseline 2025'!$E:$E) -> Short Haul | K12: =_xlfn.XLOOKUP(B12,'[1]Baseline 2025'!$B:$B,'[1]Baseline 2025'!$I:$I)/100 -> 10660.322 | L12: =(K12*100)*43/120 -> 381994.89 | M12: 3.97 | N12: =(L12*M12)/1000 -> 1516.5197 | O12: =9/1000 -> 0.009 | P12: =(O12*L12)/1000 -> 3.437954 | Q12: 0 | R12: =Q12*L12 -> 0 | S12: 100 | T12: =G12*S12*assumptions!$D$6 -> 30940 | U12: 10.9 | V12: 0.055555556 | W12: 1464.33 | X12: =W12*43/120 -> 524.71825 | Y12: =X12*17 -> 8920.2103 | Z12: 2 | AA12: 3 | AB12: 100 | AC12: 3.5 | AD12: 598.5 | AE12: 5024 | AF12: 10640 | AG12: 2660 | AH12: 831 | AI12: 2550 | AJ12: 2231 | AK12: =Y12+AD12+AE12+AF12+AG12+AH12+AI12+AJ12 -> 33454.71 | AL12: 8500 | AM12: 38150 | AN12: =AL12+AM12 -> 46650 | AO12: =(AN12/AK12)-1 -> 0.39442248
B13: 7 DUB | C13: Fokker 100 | D13: SAF | E13: =7*52 -> 364 | F13: =E13/2 -> 182 | G13: =E13 -> 364 | H13: =_xlfn.XLOOKUP(B13,'[1]Baseline 2025'!$B:$B,'[1]Baseline 2025'!$C:$C) -> 753 | I13: =E13*H13 -> 274092 | J13: =_xlfn.XLOOKUP(B13,'[1]Baseline 2025'!$B:$B,'[1]Baseline 2025'!$E:$E) -> Short Haul | K13: =_xlfn.XLOOKUP(B13,'[1]Baseline 2025'!$B:$B,'[1]Baseline 2025'!$I:$I)/100 -> 20118.353 | L13: =(K13*100)*43/120 -> 720907.64 | M13: 3.97 | N13: =(L13*M13)/1000 -> 2862.0033 | O13: =9/1000 -> 0.009 | P13: =(O13*L13)/1000 -> 6.4881688 | Q13: 0 | R13: =Q13*L13 -> 0 | S13: 100 | T13: =G13*S13*assumptions!$D$6 -> 30940 | U13: 10.9 | V13: 0.069444444 | W13: 2763.51 | X13: =W13*43/120 -> 990.25775 | Y13: =X13*17 -> 16834.382 | Z13: 2 | AA13: 3 | AB13: 126 | AC13: 3.5 | AD13: 747 | AE13: 5555 | AF13: 13280 | AG13: 3320 | AH13: 1038 | AI13: 2550 | AJ13: 3095 | AK13: =Y13+AD13+AE13+AF13+AG13+AH13+AI13+AJ13 -> 46419.382 | AL13: 10710 | AM13: 38150 | AN13: =AL13+AM13 -> 48860 | AO13: =(AN13/AK13)-1 -> 0.052577569
B14: 8 FAO | C14: Fokker 100 | D14: SAF | E14: =7*52 -> 364 | F14: =E14/2 -> 182 | G14: =E14 -> 364 | H14: =_xlfn.XLOOKUP(B14,'[1]Baseline 2025'!$B:$B,'[1]Baseline 2025'!$C:$C) -> 1970 | I14: =E14*H14 -> 717080 | J14: =_xlfn.XLOOKUP(B14,'[1]Baseline 2025'!$B:$B,'[1]Baseline 2025'!$E:$E) -> Short Haul | K14: =_xlfn.XLOOKUP(B14,'[1]Baseline 2025'!$B:$B,'[1]Baseline 2025'!$I:$I)/100 -> 52633.672 | L14: =(K14*100)*43/120 -> 1886039.9 | M14: 3.97 | N14: =(L14*M14)/1000 -> 7487.5785 | O14: =9/1000 -> 0.009 | P14: =(O14*L14)/1000 -> 16.974359 | Q14: 0 | R14: =Q14*L14 -> 0 | S14: 100 | T14: =G14*S14*assumptions!$D$6 -> 30940 | U14: 10.9 | V14: 0.125 | W14: 7229.9 | X14: =W14*43/120 -> 2590.7142 | Y14: =X14*17 -> 44042.141 | Z14: 2 | AA14: 3 | AB14: 708 | AC14: 3.5 | AD14: 1350 | AE14: 7380 | AF14: 24000 | AG14: 6000 | AH14: 1875 | AI14: 2550 | AJ14: 6231 | AK14: =Y14+AD14+AE14+AF14+AG14+AH14+AI14+AJ14 -> 93428.141 | AL14: 60180 | AM14: 38150 | AN14: =AL14+AM14 -> 98330 | AO14: =(AN14/AK14)-1 -> 0.052466624
B15: 9 LIS | C15: Fokker 100 | D15: SAF | E15: =7*52 -> 364 | F15: =E15/2 -> 182 | G15: =E15 -> 364 | H15: =_xlfn.XLOOKUP(B15,'[1]Baseline 2025'!$B:$B,'[1]Baseline 2025'!$C:$C) -> 1848 | I15: =E15*H15 -> 672672 | J15: =_xlfn.XLOOKUP(B15,'[1]Baseline 2025'!$B:$B,'[1]Baseline 2025'!$E:$E) -> Short Haul | K15: =_xlfn.XLOOKUP(B15,'[1]Baseline 2025'!$B:$B,'[1]Baseline 2025'!$I:$I)/100 -> 49374.125 | L15: =(K15*100)*43/120 -> 1769239.5 | M15: 3.97 | N15: =(L15*M15)/1000 -> 7023.8807 | O15: =9/1000 -> 0.009 | P15: =(O15*L15)/1000 -> 15.923155 | Q15: 0 | R15: =Q15*L15 -> 0 | S15: 100 | T15: =G15*S15*assumptions!$D$6 -> 30940 | U15: 10.9 | V15: 0.13194444 | W15: 6782.16 | X15: =W15*43/120 -> 2430.274 | Y15: =X15*17 -> 41314.658 | Z15: 2 | AA15: 3 | AB15: 694 | AC15: 3.5 | AD15: 1425.015 | AE15: 7197 | AF15: 25333 | AG15: 6333.4 | AH15: 1979 | AI15: 2550 | AJ15: 6154 | AK15: =Y15+AD15+AE15+AF15+AG15+AH15+AI15+AJ15 -> 92286.073 | AL15: 58990 | AM15: 38150 | AN15: =AL15+AM15 -> 97140 | AO15: =(AN15/AK15)-1 -> 0.052596528
B16: 10 MUC | C16: Fokker 100 | D16: SAF | E16: =7*52 -> 364 | F16: =E16/2 -> 182 | G16: =E16 -> 364 | H16: =_xlfn.XLOOKUP(B16,'[1]Baseline 2025'!$B:$B,'[1]Baseline 2025'!$C:$C) -> 665 | I16: =E16*H16 -> 242060 | J16: =_xlfn.XLOOKUP(B16,'[1]Baseline 2025'!$B:$B,'[1]Baseline 2025'!$E:$E) -> Short Haul | K16: =_xlfn.XLOOKUP(B16,'[1]Baseline 2025'!$B:$B,'[1]Baseline 2025'!$I:$I)/100 -> 17767.204 | L16: =(K16*100)*43/120 -> 636658.14 | M16: 3.97 | N16: =(L16*M16)/1000 -> 2527.5328 | O16: =9/1000 -> 0.009 | P16: =(O16*L16)/1000 -> 5.7299233 | Q16: 0 | R16: =Q16*L16 -> 0 | S16: 100 | T16: =G16*S16*assumptions!$D$6 -> 30940 | U16: 10.9 | V16: 0.059027778 | W16: 2440.55 | X16: =W16*43/120 -> 874.53042 | Y16: =X16*17 -> 14867.017 | Z16: 2 | AA16: 3 | AB16: 75 | AC16: 3.5 | AD16: 639 | AE16: 5738 | AF16: 11360 | AG16: 2840 | AH16: 888 | AI16: 2550 | AJ16: 2756 | AK16: =Y16+AD16+AE16+AF16+AG16+AH16+AI16+AJ16 -> 41638.017 | AL16: 6375 | AM16: 38150 | AN16: =AL16+AM16 -> 44525 | AO16: =(AN16/AK16)-1 -> 0.069335264
B17: 11 OSL | C17: Fokker 100 | D17: SAF | E17: =7*52 -> 364 | F17: =E17/2 -> 182 | G17: =E17 -> 364 | H17: =_xlfn.XLOOKUP(B17,'[1]Baseline 2025'!$B:$B,'[1]Baseline 2025'!$C:$C) -> 961 | I17: =E17*H17 -> 349804 | J17: =_xlfn.XLOOKUP(B17,'[1]Baseline 2025'!$B:$B,'[1]Baseline 2025'!$E:$E) -> Short Haul | K17: =_xlfn.XLOOKUP(B17,'[1]Baseline 2025'!$B:$B,'[1]Baseline 2025'!$I:$I)/100 -> 25675.614 | L17: =(K17*100)*43/120 -> 920042.82 | M17: 3.97 | N17: =(L17*M17)/1000 -> 3652.57 | O17: =9/1000 -> 0.009 | P17: =(O17*L17)/1000 -> 8.2803854 | Q17: 0 | R17: =Q17*L17 -> 0 | S17: 100 | T17: =G17*S17*assumptions!$D$6 -> 30940 | U17: 10.9 | V17: 0.072916667 | W17: 3526.87 | X17: =W17*43/120 -> 1263.7951 | Y17: =X17*17 -> 21484.516 | Z17: 2 | AA17: 3 | AB17: 205 | AC17: 3.5 | AD17: 787.5 | AE17: 5867 | AF17: 14000 | AG17: 3500 | AH17: 1094 | AI17: 2550 | AJ17: 3522 | AK17: =Y17+AD17+AE17+AF17+AG17+AH17+AI17+AJ17 -> 52805.016 | AL17: 17425 | AM17: 38150 | AN17: =AL17+AM17 -> 55575 | AO17: =(AN17/AK17)-1 -> 0.052456826
B18: 12 PMI | C18: Fokker 100 | D18: SAF | E18: =7*52 -> 364 | F18: =E18/2 -> 182 | G18: =E18 -> 364 | H18: =_xlfn.XLOOKUP(B18,'[1]Baseline 2025'!$B:$B,'[1]Baseline 2025'!$C:$C) -> 1426 | I18: =E18*H18 -> 519064 | J18: =_xlfn.XLOOKUP(B18,'[1]Baseline 2025'!$B:$B,'[1]Baseline 2025'!$E:$E) -> Short Haul | K18: =_xlfn.XLOOKUP(B18,'[1]Baseline 2025'!$B:$B,'[1]Baseline 2025'!$I:$I)/100 -> 38099.298 | L18: =(K18*100)*43/120 -> 1365224.8 | M18: 3.97 | N18: =(L18*M18)/1000 -> 5419.9426 | O18: =9/1000 -> 0.009 | P18: =(O18*L18)/1000 -> 12.287023 | Q18: 0 | R18: =Q18*L18 -> 0 | S18: 100 | T18: =G18*S18*assumptions!$D$6 -> 30940 | U18: 10.9 | V18: 0.10069444 | W18: 5233.42 | X18: =W18*43/120 -> 1875.3088 | Y18: =X18*17 -> 31880.25 | Z18: 2 | AA18: 3 | AB18: 451 | AC18: 3.5 | AD18: 1089 | AE18: 6564 | AF18: 19360 | AG18: 4840 | AH18: 1513 | AI18: 2550 | AJ18: 4844 | AK18: =Y18+AD18+AE18+AF18+AG18+AH18+AI18+AJ18 -> 72640.25 | AL18: 38335 | AM18: 38150 | AN18: =AL18+AM18 -> 76485 | AO18: =(AN18/AK18)-1 -> 0.052928643
B19: 13 VIE | C19: Fokker 100 | D19: SAF | E19: =7*52 -> 364 | F19: =E19/2 -> 182 | G19: =E19 -> 364 | H19: =_xlfn.XLOOKUP(B19,'[1]Baseline 2025'!$B:$B,'[1]Baseline 2025'!$C:$C) -> 962 | I19: =E19*H19 -> 350168 | J19: =_xlfn.XLOOKUP(B19,'[1]Baseline 2025'!$B:$B,'[1]Baseline 2025'!$E:$E) -> Short Haul | K19: =_xlfn.XLOOKUP(B19,'[1]Baseline 2025'!$B:$B,'[1]Baseline 2025'!$I:$I)/100 -> 25702.331 | L19: =(K19*100)*43/120 -> 921000.2 | M19: 3.97 | N19: =(L19*M19)/1000 -> 3656.3708 | O19: =9/1000 -> 0.009 | P19: =(O19*L19)/1000 -> 8.2890018 | Q19: 0 | R19: =Q19*L19 -> 0 | S19: 100 | T19: =G19*S19*assumptions!$D$6 -> 30940 | U19: 10.9 | V19: 0.072916667 | W19: 3530.54 | X19: =W19*43/120 -> 1265.1102 | Y19: =X19*17 -> 21506.873 | Z19: 2 | AA19: 3 | AB19: 205.5 | AC19: 3.5 | AD19: 787.5 | AE19: 5868 | AF19: 14000 | AG19: 3500 | AH19: 1094 | AI19: 2550 | AJ19: 3523 | AK19: =Y19+AD19+AE19+AF19+AG19+AH19+AI19+AJ19 -> 52829.373 | AL19: 17467.5 | AM19: 38150 | AN19: =AL19+AM19 -> 55617.5 | AO19: =(AN19/AK19)-1 -> 0.052776079
B20: 14 WAW | C20: Fokker 100 | D20: SAF | E20: =7*52 -> 364 | F20: =E20/2 -> 182 | G20: =E20 -> 364 | H20: =_xlfn.XLOOKUP(B20,'[1]Baseline 2025'!$B:$B,'[1]Baseline 2025'!$C:$C) -> 1105 | I20: =E20*H20 -> 402220 | J20: =_xlfn.XLOOKUP(B20,'[1]Baseline 2025'!$B:$B,'[1]Baseline 2025'!$E:$E) -> Short Haul | K20: =_xlfn.XLOOKUP(B20,'[1]Baseline 2025'!$B:$B,'[1]Baseline 2025'!$I:$I)/100 -> 29522.948 | L20: =(K20*100)*43/120 -> 1057905.6 | M20: 3.97 | N20: =(L20*M20)/1000 -> 4199.8854 | O20: =9/1000 -> 0.009 | P20: =(O20*L20)/1000 -> 9.5211507 | Q20: 0 | R20: =Q20*L20 -> 0 | S20: 100 | T20: =G20*S20*assumptions!$D$6 -> 30940 | U20: 10.9 | V20: 0.079861111 | W20: 4055.35 | X20: =W20*43/120 -> 1453.1671 | Y20: =X20*17 -> 24703.84 | Z20: 2 | AA20: 3 | AB20: 275 | AC20: 3.5 | AD20: 862.515 | AE20: 6083 | AF20: 15333.6 | AG20: 3833.4 | AH20: 1198 | AI20: 2550 | AJ20: 3899 | AK20: =Y20+AD20+AE20+AF20+AG20+AH20+AI20+AJ20 -> 58463.355 | AL20: 23375 | AM20: 38150 | AN20: =AL20+AM20 -> 61525 | AO20: =(AN20/AK20)-1 -> 0.052368609
B21: 15 ZRH | C21: Fokker 100 | D21: SAF | E21: =14*52*2 -> 1456 | F21: =E21/2 -> 728 | G21: =E21 -> 1456 | H21: =_xlfn.XLOOKUP(B21,'[1]Baseline 2025'!$B:$B,'[1]Baseline 2025'!$C:$C) -> 603 | I21: =E21*H21 -> 877968 | J21: =_xlfn.XLOOKUP(B21,'[1]Baseline 2025'!$B:$B,'[1]Baseline 2025'!$E:$E) -> Short Haul | K21: =_xlfn.XLOOKUP(B21,'[1]Baseline 2025'!$B:$B,'[1]Baseline 2025'!$I:$I)/100 -> 32221.426 | L21: =(K21*100)*43/120 -> 1154601.1 | M21: 3.97 | N21: =(L21*M21)/1000 -> 4583.7663 | O21: =9/1000 -> 0.009 | P21: =(O21*L21)/1000 -> 10.39141 | Q21: 0 | R21: =Q21*L21 -> 0 | S21: 100 | T21: =G21*S21*assumptions!$D$6 -> 123760 | U21: 10.9 | V21: 0.059027778 | W21: 2213.01 | X21: =W21*43/120 -> 792.99525 | Y21: =X21*17 -> 13480.919 | Z21: 2 | AA21: 3 | AB21: 75 | AC21: 3.5 | AD21: 637.515 | AE21: 5330 | AF21: 11333.6 | AG21: 2833.4 | AH21: 885 | AI21: 2550 | AJ21: 2647 | AK21: =Y21+AD21+AE21+AF21+AG21+AH21+AI21+AJ21 -> 39697.434 | AL21: 6375 | AM21: 38150 | AN21: =AL21+AM21 -> 44525 | AO21: =(AN21/AK21)-1 -> 0.12160901
B22: 16 BKK | C22: B777-200er | D22: SAF | E22: =3*52*2 -> 312 | F22: =E22/2 -> 156 | G22: =E22 -> 312 | H22: =_xlfn.XLOOKUP(B22,'[1]Baseline 2025'!$B:$B,'[1]Baseline 2025'!$C:$C) -> 9217 | I22: =E22*H22 -> 2875704 | J22: =_xlfn.XLOOKUP(B22,'[1]Baseline 2025'!$B:$B,'[1]Baseline 2025'!$E:$E) -> Long Haul | K22: =_xlfn.XLOOKUP(B22,'[1]Baseline 2025'!$B:$B,'[1]Baseline 2025'!$I:$I)/100 -> 213377.24 | L22: =(K22*100)*43/120 -> 7646017.7 | M22: 3.97 | N22: =(L22*M22)/1000 -> 30354.69 | O22: =9/1000 -> 0.009 | P22: =(O22*L22)/1000 -> 68.814159 | Q22: 0 | R22: =Q22*L22 -> 0 | S22: 300 | T22: =G22*S22*assumptions!$D$6 -> 79560 | U22: 20 | V22: 0.46875 | W22: 68390.14 | X22: =W22*43/120 -> 24506.467 | Y22: =X22*17 -> 416609.94 | Z22: 3 | AA22: 12 | AB22: 2364 | AC22: 2.5 | AD22: 11812.5 | AE22: 27101 | AF22: 90000 | AG22: 22500 | AH22: 21094 | AI22: 7650 | AJ22: 42642 | AK22: =Y22+AD22+AE22+AF22+AG22+AH22+AI22+AJ22 -> 639409.44 | AL22: 602820 | AM22: 70000 | AN22: =AL22+AM22 -> 672820 | AO22: =(AN22/AK22)-1 -> 0.052252222
B23: 17 MFM | C23: B777-200er | D23: SAF | E23: =3*52*2 -> 312 | F23: =E23/2 -> 156 | G23: =E23 -> 312 | H23: =_xlfn.XLOOKUP(B23,'[1]Baseline 2025'!$B:$B,'[1]Baseline 2025'!$C:$C) -> 9285 | I23: =E23*H23 -> 2896920 | J23: =_xlfn.XLOOKUP(B23,'[1]Baseline 2025'!$B:$B,'[1]Baseline 2025'!$E:$E) -> Long Haul | K23: =_xlfn.XLOOKUP(B23,'[1]Baseline 2025'!$B:$B,'[1]Baseline 2025'!$I:$I)/100 -> 214951.46 | L23: =(K23*100)*43/120 -> 7702427.5 | M23: 3.97 | N23: =(L23*M23)/1000 -> 30578.637 | O23: =9/1000 -> 0.009 | P23: =(O23*L23)/1000 -> 69.321847 | Q23: 0 | R23: =Q23*L23 -> 0 | S23: 300 | T23: =G23*S23*assumptions!$D$6 -> 79560 | U23: 20 | V23: 0.46875 | W23: 68894.7 | X23: =W23*43/120 -> 24687.268 | Y23: =X23*17 -> 419683.55 | Z23: 3 | AA23: 12 | AB23: 2378 | AC23: 3.5 | AD23: 11812.5 | AE23: 27203 | AF23: 90000 | AG23: 22500 | AH23: 21094 | AI23: 7650 | AJ23: 42869 | AK23: =Y23+AD23+AE23+AF23+AG23+AH23+AI23+AJ23 -> 642812.05 | AL23: 606390 | AM23: 70000 | AN23: =AL23+AM23 -> 676390 | AO23: =(AN23/AK23)-1 -> 0.052236035
B24: 18 HAN | C24: B777-200er | D24: SAF | E24: =52*2 -> 104 | F24: =E24/2 -> 52 | G24: =E24 -> 104 | H24: =_xlfn.XLOOKUP(B24,'[1]Baseline 2025'!$B:$B,'[1]Baseline 2025'!$C:$C) -> 8886 | I24: =E24*H24 -> 924144 | J24: =_xlfn.XLOOKUP(B24,'[1]Baseline 2025'!$B:$B,'[1]Baseline 2025'!$E:$E) -> Long Haul | K24: =_xlfn.XLOOKUP(B24,'[1]Baseline 2025'!$B:$B,'[1]Baseline 2025'!$I:$I)/100 -> 68571.485 | L24: =(K24*100)*43/120 -> 2457144.9 | M24: 3.97 | N24: =(L24*M24)/1000 -> 9754.8651 | O24: =9/1000 -> 0.009 | P24: =(O24*L24)/1000 -> 22.114304 | Q24: 0 | R24: =Q24*L24 -> 0 | S24: 300 | T24: =G24*S24*assumptions!$D$6 -> 26520 | U24: 20 | V24: 0.45833333 | W24: 65934.12 | X24: =W24*43/120 -> 23626.393 | Y24: =X24*17 -> 401648.68 | Z24: 3 | AA24: 12 | AB24: 2282 | AC24: 3.5 | AD24: 11550 | AE24: 26604 | AF24: 88000 | AG24: 22000 | AH24: 20625 | AI24: 7650 | AJ24: 41307 | AK24: =Y24+AD24+AE24+AF24+AG24+AH24+AI24+AJ24 -> 619384.68 | AL24: 581910 | AM24: 70000 | AN24: =AL24+AM24 -> 651910 | AO24: =(AN24/AK24)-1 -> 0.052512308
B25: 19 PTY | C25: B777-200er | D25: SAF | E25: =156*2 -> 312 | F25: =E25/2 -> 156 | G25: =E25 -> 312 | H25: =_xlfn.XLOOKUP(B25,'[1]Baseline 2025'!$B:$B,'[1]Baseline 2025'!$C:$C) -> 8818 | I25: =E25*H25 -> 2751216 | J25: =_xlfn.XLOOKUP(B25,'[1]Baseline 2025'!$B:$B,'[1]Baseline 2025'!$E:$E) -> Long Haul | K25: =_xlfn.XLOOKUP(B25,'[1]Baseline 2025'!$B:$B,'[1]Baseline 2025'!$I:$I)/100 -> 204140.23 | L25: =(K25*100)*43/120 -> 7315024.8 | M25: 3.97 | N25: =(L25*M25)/1000 -> 29040.648 | O25: =9/1000 -> 0.009 | P25: =(O25*L25)/1000 -> 65.835223 | Q25: 0 | R25: =Q25*L25 -> 0 | S25: 300 | T25: =G25*S25*assumptions!$D$6 -> 79560 | U25: 20 | V25: 0.46527778 | W25: 65429.56 | X25: =W25*43/120 -> 23445.592 | Y25: =X25*17 -> 398575.07 | Z25: 3 | AA25: 12 | AB25: 2277 | AC25: 3.5 | AD25: 11718 | AE25: 26502 | AF25: 89280 | AG25: 22320 | AH25: 20925 | AI25: 7650 | AJ25: 41228 | AK25: =Y25+AD25+AE25+AF25+AG25+AH25+AI25+AJ25 -> 618198.07 | AL25: 580635 | AM25: 70000 | AN25: =AL25+AM25 -> 650635 | AO25: =(AN25/AK25)-1 -> 0.052470126
B26: 20 MEX | C26: B777-200er | D26: SAF | E26: =156*2 -> 312 | F26: =E26/2 -> 156 | G26: =E26 -> 312 | H26: =_xlfn.XLOOKUP(B26,'[1]Baseline 2025'!$B:$B,'[1]Baseline 2025'!$C:$C) -> 9220 | I26: =E26*H26 -> 2876640 | J26: =_xlfn.XLOOKUP(B26,'[1]Baseline 2025'!$B:$B,'[1]Baseline 2025'!$E:$E) -> Long Haul | K26: =_xlfn.XLOOKUP(B26,'[1]Baseline 2025'!$B:$B,'[1]Baseline 2025'!$I:$I)/100 -> 213446.69 | L26: =(K26*100)*43/120 -> 7648506.3 | M26: 3.97 | N26: =(L26*M26)/1000 -> 30364.57 | O26: =9/1000 -> 0.009 | P26: =(O26*L26)/1000 -> 68.836557 | Q26: 0 | R26: =Q26*L26 -> 0 | S26: 300 | T26: =G26*S26*assumptions!$D$6 -> 79560 | U26: 20 | V26: 0.47916667 | W26: 68412.4 | X26: =W26*43/120 -> 24514.443 | Y26: =X26*17 -> 416745.54 | Z26: 3 | AA26: 12 | AB26: 2380 | AC26: 3.5 | AD26: 12075 | AE26: 27105 | AF26: 92000 | AG26: 23000 | AH26: 21563 | AI26: 7650 | AJ26: 42883 | AK26: =Y26+AD26+AE26+AF26+AG26+AH26+AI26+AJ26 -> 643021.54 | AL26: 606900 | AM26: 70000 | AN26: =AL26+AM26 -> 676900 | AO26: =(AN26/AK26)-1 -> 0.052686359
B27: 21 GIG | C27: B777-200er | D27: SAF | E27: =52*2 -> 104 | F27: =E27/2 -> 52 | G27: =E27 -> 104 | H27: =_xlfn.XLOOKUP(B27,'[1]Baseline 2025'!$B:$B,'[1]Baseline 2025'!$C:$C) -> 9536 | I27: =E27*H27 -> 991744 | J27: =_xlfn.XLOOKUP(B27,'[1]Baseline 2025'!$B:$B,'[1]Baseline 2025'!$E:$E) -> Long Haul | K27: =_xlfn.XLOOKUP(B27,'[1]Baseline 2025'!$B:$B,'[1]Baseline 2025'!$I:$I)/100 -> 73587.405 | L27: =(K27*100)*43/120 -> 2636882 | M27: 3.97 | N27: =(L27*M27)/1000 -> 10468.422 | O27: =9/1000 -> 0.009 | P27: =(O27*L27)/1000 -> 23.731938 | Q27: 0 | R27: =Q27*L27 -> 0 | S27: 300 | T27: =G27*S27*assumptions!$D$6 -> 26520 | U27: 20 | V27: 0.5 | W27: 70757.12 | X27: =W27*43/120 -> 25354.635 | Y27: =X27*17 -> 431028.79 | Z27: 3 | AA27: 12 | AB27: 2475 | AC27: 3.5 | AD27: 12600 | AE27: 27579 | AF27: 96000 | AG27: 24000 | AH27: 22500 | AI27: 7650 | AJ27: 44400 | AK27: =Y27+AD27+AE27+AF27+AG27+AH27+AI27+AJ27 -> 665757.79 | AL27: 631125 | AM27: 70000 | AN27: =AL27+AM27 -> 701125 | AO27: =(AN27/AK27)-1 -> 0.05312324
B28: 22 CPT | C28: B777-200er | D28: SAF | E28: =156*2 -> 312 | F28: =E28/2 -> 156 | G28: =E28 -> 312 | H28: =_xlfn.XLOOKUP(B28,'[1]Baseline 2025'!$B:$B,'[1]Baseline 2025'!$C:$C) -> 9652 | I28: =E28*H28 -> 3011424 | J28: =_xlfn.XLOOKUP(B28,'[1]Baseline 2025'!$B:$B,'[1]Baseline 2025'!$E:$E) -> Long Haul | K28: =_xlfn.XLOOKUP(B28,'[1]Baseline 2025'!$B:$B,'[1]Baseline 2025'!$I:$I)/100 -> 223447.66 | L28: =(K28*100)*43/120 -> 8006874.5 | M28: 3.97 | N28: =(L28*M28)/1000 -> 31787.292 | O28: =9/1000 -> 0.009 | P28: =(O28*L28)/1000 -> 72.061871 | Q28: 0 | R28: =Q28*L28 -> 0 | S28: 300 | T28: =G28*S28*assumptions!$D$6 -> 79560 | U28: 20 | V28: 0.47222222 | W28: 71617.84 | X28: =W28*43/120 -> 25663.059 | Y28: =X28*17 -> 436272.01 | Z28: 3 | AA28: 12 | AB28: 2455 | AC28: 3.5 | AD28: 11896.5 | AE28: 27753 | AF28: 90640 | AG28: 22660 | AH28: 21244 | AI28: 7650 | AJ28: 44168 | AK28: =Y28+AD28+AE28+AF28+AG28+AH28+AI28+AJ28 -> 662283.51 | AL28: 627300 | AM28: 70000 | AN28: =AL28+AM28 -> 697300 | AO28: =(AN28/AK28)-1 -> 0.052872359
N29: =SUM(N7:N28) -> 233849.89 | P29: =SUM(P7:P28) -> 530.13829 | R29: =SUM(R7:R28) -> 0
A33: yearly fuel ussage [tons] | D33: yearly costs | F33: yearly revenue
A34: =(E7*X7)/1000 -> 1544.255 | D34: =E7*AK7 -> 58516203 | F34: =E7*AN7 -> 61497800
A35: =(E8*X8)/1000 -> 1105.7747 | D35: =E8*AK8 -> 44211193 | F35: =E8*AN8 -> 46701200
A36: =(E9*X9)/1000 -> 1188.1094 | D36: =E9*AK9 -> 48687048 | F36: =E9*AN9 -> 51287600
A37: =(E10*X10)/1000 -> 151.26615 | D37: =E10*AK10 -> 14082660 | F37: =E10*AN10 -> 35198800
A38: =(E11*X11)/1000 -> 537.09055 | D38: =E11*AK11 -> 27370215 | F38: =E11*AN11 -> 32228560
A39: =(E12*X12)/1000 -> 190.99744 | D39: =E12*AK12 -> 12177515 | F39: =E12*AN12 -> 16980600
A40: =(E13*X13)/1000 -> 360.45382 | D40: =E13*AK13 -> 16896655 | F40: =E13*AN13 -> 17785040
A41: =(E14*X14)/1000 -> 943.01996 | D41: =E14*AK14 -> 34007843 | F41: =E14*AN14 -> 35792120
A42: =(E15*X15)/1000 -> 884.61974 | D42: =E15*AK15 -> 33592131 | F42: =E15*AN15 -> 35358960
A43: =(E16*X16)/1000 -> 318.32907 | D43: =E16*AK16 -> 15156238 | F43: =E16*AN16 -> 16207100
A44: =(E17*X17)/1000 -> 460.02141 | D44: =E17*AK17 -> 19221026 | F44: =E17*AN17 -> 20229300
A45: =(E18*X18)/1000 -> 682.61242 | D45: =E18*AK18 -> 26441051 | F45: =E18*AN18 -> 27840540
... A55: =(E28*X28)/1000 -> 8006.8745 | D55: =E28*AK28 -> 2.0663245e+08 | F55: =E28*AN28 -> 217557600
A57: sum | D57: sum | F57: sum
A58: =SUM(A34:A55) -> 53923.481 | D58: =SUM(D34:D55) -> 1.5825107e+09 | F58: =SUM(F34:F55) -> 1697993570

Sheet Scenario 3 2050
A4: Hydrogen
Z5: Crew costs | AG5: Costs | AM5: Revenu
B6: Destination | C6: Aircraft | D6: Fuel type | E6: Frequency [per year] | F6: # retour | G6: # flights | H6: Lookup: Distance [km] | I6: Total distance travelled [km] | J6: Lookup: Flight Type | K6: Lookup: fuel consumption [l/100km] | L6: Conditional: Total fuel consumption [l] | M6: SAF LFEC CO2 per kg [kg/kg] | N6: Total CO2 emmission [kg] (tons) | O6: NOX per KG | P6: Total NOX emmision(Tons) | Q6: Sox per KG | R6: Total Sox emmission(Ton) | S6: Seats | T6: Passengers per year | U6: Available cargo (Tons) | V6: Flight time | W6: Fuel | X6: Hydrogen | Y6: Hydrogen costs | Z6: Pilot | AA6: Cabin crew | AB6: Ticket price | AC6: Freight rate (Euro/KG) | AD6: Crew costs | AE6: Airport & Navigation charges | AF6: Maintenance costs | AG6: Maintenance reserve | AH6: Operational lease | AI6: catering and inflight services | AJ6: Insurance and overhead | AK6: Total costs | AL6: Passenger revenue | AM6: Cargo revenue | AN6: Total revenuee
B7: 1 ALC | C7: Fokker 100 | D7: SAF | E7: =7*52*2 -> 728 | F7: =E7/2 -> 364 | G7: =E7 -> 728 | H7: =_xlfn.XLOOKUP(B7,'[1]Baseline 2025'!$B:$B,'[1]Baseline 2025'!$C:$C) -> 1613 | I7: =E7*H7 -> 1174264 | J7: =_xlfn.XLOOKUP(B7,'[1]Baseline 2025'!$B:$B,'[1]Baseline 2025'!$E:$E) -> Short Haul | K7: =_xlfn.XLOOKUP(B7,'[1]Baseline 2025'!$B:$B,'[1]Baseline 2025'!$I:$I)/100 -> 43095.489 | L7: =(K7*100)*43/120 -> 1544255 | M7: 3.97 | N7: =(L7*M7)/1000 -> 6130.6924 | O7: =9/1000 -> 0.009 | P7: =(O7*L7)/1000 -> 13.898295 | Q7: 0 | R7: =Q7*L7 -> 0 | S7: 100 | T7: =G7*S7*assumptions!$D$6 -> 61880 | U7: 10.9 | V7: 0.11111111 | W7: 5919.71 | X7: =W7*43/120 -> 2121.2294 | Y7: =X7*6 -> 12727.376 | Z7: 2 | AA7: 3 | AB7: 545 | AC7: 3.5 | AD7: 1201.5 | AE7: 6845 | AF7: 21360 | AG7: 5340 | AH7: 1669 | AI7: 2550 | AJ7: 5353 | AK7: =Y7+AD7+AE7+AF7+AG7+AH7+AI7+AJ7 -> 57045.876 | AL7: 46325 | AM7: 38150 | AN7: =AL7+AM7 -> 84475
B8: 2 ARN | C8: Fokker 100 | D8: SAF | E8: =7*52*2 -> 728 | F8: =E8/2 -> 364 | G8: =E8 -> 728 | H8: =_xlfn.XLOOKUP(B8,'[1]Baseline 2025'!$B:$B,'[1]Baseline 2025'!$C:$C) -> 1155 | I8: =E8*H8 -> 840840 | J8: =_xlfn.XLOOKUP(B8,'[1]Baseline 2025'!$B:$B,'[1]Baseline 2025'!$E:$E) -> Short Haul | K8: =_xlfn.XLOOKUP(B8,'[1]Baseline 2025'!$B:$B,'[1]Baseline 2025'!$I:$I)/100 -> 30858.828 | L8: =(K8*100)*43/120 -> 1105774.7 | M8: 3.97 | N8: =(L8*M8)/1000 -> 4389.9254 | O8: =9/1000 -> 0.009 | P8: =(O8*L8)/1000 -> 9.951972 | Q8: 0 | R8: =Q8*L8 -> 0 | S8: 100 | T8: =G8*S8*assumptions!$D$6 -> 61880 | U8: 10.9 | V8: 0.083333333 | W8: 4238.85 | X8: =W8*43/120 -> 1518.9213 | Y8: =X8*6 -> 9113.5275 | Z8: 2 | AA8: 3 | AB8: 370 | AC8: 3 | AD8: 900 | AE8: 6158 | AF8: 16000 | AG8: 4000 | AH8: 1250 | AI8: 2550 | AJ8: 4050 | AK8: =Y8+AD8+AE8+AF8+AG8+AH8+AI8+AJ8 -> 44021.527 | AL8: 31450 | AM8: 32700 | AN8: =AL8+AM8 -> 64150
B9: 3 BCN | C9: Fokker 100 | D9: SAF | E9: =7*52*2 -> 728 | F9: =E9/2 -> 364 | G9: =E9 -> 728 | H9: =_xlfn.XLOOKUP(B9,'[1]Baseline 2025'!$B:$B,'[1]Baseline 2025'!$C:$C) -> 1241 | I9: =E9*H9 -> 903448 | J9: =_xlfn.XLOOKUP(B9,'[1]Baseline 2025'!$B:$B,'[1]Baseline 2025'!$E:$E) -> Short Haul | K9: =_xlfn.XLOOKUP(B9,'[1]Baseline 2025'!$B:$B,'[1]Baseline 2025'!$I:$I)/100 -> 33156.542 | L9: =(K9*100)*43/120 -> 1188109.4 | M9: 3.97 | N9: =(L9*M9)/1000 -> 4716.7943 | O9: =9/1000 -> 0.009 | P9: =(O9*L9)/1000 -> 10.692985 | Q9: 0 | R9: =Q9*L9 -> 0 | S9: 100 | T9: =G9*S9*assumptions!$D$6 -> 61880 | U9: 10.9 | V9: 0.097222222 | W9: 4554.47 | X9: =W9*43/120 -> 1632.0184 | Y9: =X9*6 -> 9792.1105 | Z9: 2 | AA9: 3 | AB9: 380 | AC9: 3.5 | AD9: 1048.5 | AE9: 6287 | AF9: 18664 | AG9: 4666 | AH9: 1458 | AI9: 2550 | AJ9: 4460 | AK9: =Y9+AD9+AE9+AF9+AG9+AH9+AI9+AJ9 -> 48925.611 | AL9: 32300 | AM9: 38150 | AN9: =AL9+AM9 -> 70450
B10: 4 BRU | C10: Fokker 100 | D10: SAF | E10: =14*52 -> 728 | F10: =E10/2 -> 364 | G10: =E10 -> 728 | H10: =_xlfn.XLOOKUP(B10,'[1]Baseline 2025'!$B:$B,'[1]Baseline 2025'!$C:$C) -> 158 | I10: =E10*H10 -> 115024 | J10: =_xlfn.XLOOKUP(B10,'[1]Baseline 2025'!$B:$B,'[1]Baseline 2025'!$E:$E) -> Short Haul | K10: =_xlfn.XLOOKUP(B10,'[1]Baseline 2025'!$B:$B,'[1]Baseline 2025'!$I:$I)/100 -> 8442.7616 | L10: =(K10*100)*43/120 -> 302532.29 | M10: 3.97 | N10: =(L10*M10)/1000 -> 1201.0532 | O10: =9/1000 -> 0.009 | P10: =(O10*L10)/1000 -> 2.7227906 | Q10: 0 | R10: =Q10*L10 -> 0 | S10: 100 | T10: =G10*S10*assumptions!$D$6 -> 61880 | U10: 10.9 | V10: 0.027777778 | W10: 579.86 | X10: =W10*43/120 -> 207.78317 | Y10: =X10*6 -> 1246.699 | Z10: 2 | AA10: 3 | AB10: 120 | AC10: 3.5 | AD10: 297 | AE10: 4662 | AF10: 5280 | AG10: 1320 | AH10: 413 | AI10: 2550 | AJ10: 1290 | AK10: =Y10+AD10+AE10+AF10+AG10+AH10+AI10+AJ10 -> 17058.699 | AL10: 10200 | AM10: 38150 | AN10: =AL10+AM10 -> 48350
B11: 5 BSL | C11: Fokker 100 | D11: SAF | E11: =7*52*2 -> 728 | F11: =E11/2 -> 364 | G11: =E11 -> 728 | H11: =_xlfn.XLOOKUP(B11,'[1]Baseline 2025'!$B:$B,'[1]Baseline 2025'!$C:$C) -> 561 | I11: =E11*H11 -> 408408 | J11: =_xlfn.XLOOKUP(B11,'[1]Baseline 2025'!$B:$B,'[1]Baseline 2025'!$E:$E) -> Short Haul | K11: =_xlfn.XLOOKUP(B11,'[1]Baseline 2025'!$B:$B,'[1]Baseline 2025'!$I:$I)/100 -> 14988.574 | L11: =(K11*100)*43/120 -> 537090.55 | M11: 3.97 | N11: =(L11*M11)/1000 -> 2132.2495 | O11: =9/1000 -> 0.009 | P11: =(O11*L11)/1000 -> 4.833815 | Q11: 0 | R11: =Q11*L11 -> 0 | S11: 100 | T11: =G11*S11*assumptions!$D$6 -> 61880 | U11: 10.9 | V11: 0.055555556 | W11: 2058.87 | X11: =W11*43/120 -> 737.76175 | Y11: =X11*6 -> 4426.5705 | Z11: 2 | AA11: 3 | AB11: 72 | AC11: 3.5 | AD11: 598.5 | AE11: 5267 | AF11: 10640 | AG11: 2660 | AH11: 831 | AI11: 2550 | AJ11: 2508 | AK11: =Y11+AD11+AE11+AF11+AG11+AH11+AI11+AJ11 -> 29481.071 | AL11: 6120 | AM11: 38150 | AN11: =AL11+AM11 -> 44270
B12: 6 CDG | C12: Fokker 100 | D12: SAF | E12: =7*52 -> 364 | F12: =E12/2 -> 182 | G12: =E12 -> 364 | H12: =_xlfn.XLOOKUP(B12,'[1]Baseline 2025'!$B:$B,'[1]Baseline 2025'!$C:$C) -> 399 | I12: =E12*H12 -> 145236 | J12: =_xlfn.XLOOKUP(B12,'[1]Baseline 2025'!$B:$B,'[1]Baseline 2025'!$E:$E) -> Short Haul | K12: =_xlfn.XLOOKUP(B12,'[1]Baseline 2025'!$B:$B,'[1]Baseline 2025'!$I:$I)/100 -> 10660.322 | L12: =(K12*100)*43/120 -> 381994.89 | M12: 3.97 | N12: =(L12*M12)/1000 -> 1516.5197 | O12: =9/1000 -> 0.009 | P12: =(O12*L12)/1000 -> 3.437954 | Q12: 0 | R12: =Q12*L12 -> 0 | S12: 100 | T12: =G12*S12*assumptions!$D$6 -> 30940 | U12: 10.9 | V12: 0.055555556 | W12: 1464.33 | X12: =W12*43/120 -> 524.71825 | Y12: =X12*6 -> 3148.3095 | Z12: 2 | AA12: 3 | AB12: 100 | AC12: 3.5 | AD12: 598.5 | AE12: 5024 | AF12: 10640 | AG12: 2660 | AH12: 831 | AI12: 2550 | AJ12: 2231 | AK12: =Y12+AD12+AE12+AF12+AG12+AH12+AI12+AJ12 -> 27682.809 | AL12: 8500 | AM12: 38150 | AN12: =AL12+AM12 -> 46650
B13: 7 DUB | C13: Fokker 100 | D13: SAF | E13: =7*52 -> 364 | F13: =E13/2 -> 182 | G13: =E13 -> 364 | H13: =_xlfn.XLOOKUP(B13,'[1]Baseline 2025'!$B:$B,'[1]Baseline 2025'!$C:$C) -> 753 | I13: =E13*H13 -> 274092 | J13: =_xlfn.XLOOKUP(B13,'[1]Baseline 2025'!$B:$B,'[1]Baseline 2025'!$E:$E) -> Short Haul | K13: =_xlfn.XLOOKUP(B13,'[1]Baseline 2025'!$B:$B,'[1]Baseline 2025'!$I:$I)/100 -> 20118.353 | L13: =(K13*100)*43/120 -> 720907.64 | M13: 3.97 | N13: =(L13*M13)/1000 -> 2862.0033 | O13: =9/1000 -> 0.009 | P13: =(O13*L13)/1000 -> 6.4881688 | Q13: 0 | R13: =Q13*L13 -> 0 | S13: 100 | T13: =G13*S13*assumptions!$D$6 -> 30940 | U13: 10.9 | V13: 0.069444444 | W13: 2763.51 | X13: =W13*43/120 -> 990.25775 | Y13: =X13*6 -> 5941.5465 | Z13: 2 | AA13: 3 | AB13: 126 | AC13: 3.5 | AD13: 747 | AE13: 5555 | AF13: 13280 | AG13: 3320 | AH13: 1038 | AI13: 2550 | AJ13: 3095 | AK13: =Y13+AD13+AE13+AF13+AG13+AH13+AI13+AJ13 -> 35526.546 | AL13: 10710 | AM13: 38150 | AN13: =AL13+AM13 -> 48860
B14: 8 FAO | C14: Fokker 100 | D14: SAF | E14: =7*52 -> 364 | F14: =E14/2 -> 182 | G14: =E14 -> 364 | H14: =_xlfn.XLOOKUP(B14,'[1]Baseline 2025'!$B:$B,'[1]Baseline 2025'!$C:$C) -> 1970 | I14: =E14*H14 -> 717080 | J14: =_xlfn.XLOOKUP(B14,'[1]Baseline 2025'!$B:$B,'[1]Baseline 2025'!$E:$E) -> Short Haul | K14: =_xlfn.XLOOKUP(B14,'[1]Baseline 2025'!$B:$B,'[1]Baseline 2025'!$I:$I)/100 -> 52633.672 | L14: =(K14*100)*43/120 -> 1886039.9 | M14: 3.97 | N14: =(L14*M14)/1000 -> 7487.5785 | O14: =9/1000 -> 0.009 | P14: =(O14*L14)/1000 -> 16.974359 | Q14: 0 | R14: =Q14*L14 -> 0 | S14: 100 | T14: =G14*S14*assumptions!$D$6 -> 30940 | U14: 10.9 | V14: 0.125 | W14: 7229.9 | X14: =W14*43/120 -> 2590.7142 | Y14: =X14*6 -> 15544.285 | Z14: 2 | AA14: 3 | AB14: 708 | AC14: 3.5 | AD14: 1350 | AE14: 7380 | AF14: 24000 | AG14: 6000 | AH14: 1875 | AI14: 2550 | AJ14: 6231 | AK14: =Y14+AD14+AE14+AF14+AG14+AH14+AI14+AJ14 -> 64930.285 | AL14: 60180 | AM14: 38150 | AN14: =AL14+AM14 -> 98330
B15: 9 LIS | C15: Fokker 100 | D15: SAF | E15: =7*52 -> 364 | F15: =E15/2 -> 182 | G15: =E15 -> 364 | H15: =_xlfn.XLOOKUP(B15,'[1]Baseline 2025'!$B:$B,'[1]Baseline 2025'!$C:$C) -> 1848 | I15: =E15*H15 -> 672672 | J15: =_xlfn.XLOOKUP(B15,'[1]Baseline 2025'!$B:$B,'[1]Baseline 2025'!$E:$E) -> Short Haul | K15: =_xlfn.XLOOKUP(B15,'[1]Baseline 2025'!$B:$B,'[1]Baseline 2025'!$I:$I)/100 -> 49374.125 | L15: =(K15*100)*43/120 -> 1769239.5 | M15: 3.97 | N15: =(L15*M15)/1000 -> 7023.8807 | O15: =9/1000 -> 0.009 | P15: =(O15*L15)/1000 -> 15.923155 | Q15: 0 | R15: =Q15*L15 -> 0 | S15: 100 | T15: =G15*S15*assumptions!$D$6 -> 30940 | U15: 10.9 | V15: 0.13194444 | W15: 6782.16 | X15: =W15*43/120 -> 2430.274 | Y15: =X15*6 -> 14581.644 | Z15: 2 | AA15: 3 | AB15: 694 | AC15: 3.5 | AD15: 1425.015 | AE15: 7197 | AF15: 25333 | AG15: 6333.4 | AH15: 1979 | AI15: 2550 | AJ15: 6154 | AK15: =Y15+AD15+AE15+AF15+AG15+AH15+AI15+AJ15 -> 65553.059 | AL15: 58990 | AM15: 38150 | AN15: =AL15+AM15 -> 97140
B16: 10 MUC | C16: Fokker 100 | D16: SAF | E16: =7*52 -> 364 | F16: =E16/2 -> 182 | G16: =E16 -> 364 | H16: =_xlfn.XLOOKUP(B16,'[1]Baseline 2025'!$B:$B,'[1]Baseline 2025'!$C:$C) -> 665 | I16: =E16*H16 -> 242060 | J16: =_xlfn.XLOOKUP(B16,'[1]Baseline 2025'!$B:$B,'[1]Baseline 2025'!$E:$E) -> Short Haul | K16: =_xlfn.XLOOKUP(B16,'[1]Baseline 2025'!$B:$B,'[1]Baseline 2025'!$I:$I)/100 -> 17767.204 | L16: =(K16*100)*43/120 -> 636658.14 | M16: 3.97 | N16: =(L16*M16)/1000 -> 2527.5328 | O16: =9/1000 -> 0.009 | P16: =(O16*L16)/1000 -> 5.7299233 | Q16: 0 | R16: =Q16*L16 -> 0 | S16: 100 | T16: =G16*S16*assumptions!$D$6 -> 30940 | U16: 10.9 | V16: 0.059027778 | W16: 2440.55 | X16: =W16*43/120 -> 874.53042 | Y16: =X16*6 -> 5247.1825 | Z16: 2 | AA16: 3 | AB16: 75 | AC16: 3.5 | AD16: 639 | AE16: 5738 | AF16: 11360 | AG16: 2840 | AH16: 888 | AI16: 2550 | AJ16: 2756 | AK16: =Y16+AD16+AE16+AF16+AG16+AH16+AI16+AJ16 -> 32018.182 | AL16: 6375 | AM16: 38150 | AN16: =AL16+AM16 -> 44525
B17: 11 OSL | C17: Fokker 100 | D17: SAF | E17: =7*52 -> 364 | F17: =E17/2 -> 182 | G17: =E17 -> 364 | H17: =_xlfn.XLOOKUP(B17,'[1]Baseline 2025'!$B:$B,'[1]Baseline 2025'!$C:$C) -> 961 | I17: =E17*H17 -> 349804 | J17: =_xlfn.XLOOKUP(B17,'[1]Baseline 2025'!$B:$B,'[1]Baseline 2025'!$E:$E) -> Short Haul | K17: =_xlfn.XLOOKUP(B17,'[1]Baseline 2025'!$B:$B,'[1]Baseline 2025'!$I:$I)/100 -> 25675.614 | L17: =(K17*100)*43/120 -> 920042.82 | M17: 3.97 | N17: =(L17*M17)/1000 -> 3652.57 | O17: =9/1000 -> 0.009 | P17: =(O17*L17)/1000 -> 8.2803854 | Q17: 0 | R17: =Q17*L17 -> 0 | S17: 100 | T17: =G17*S17*assumptions!$D$6 -> 30940 | U17: 10.9 | V17: 0.072916667 | W17: 3526.87 | X17: =W17*43/120 -> 1263.7951 | Y17: =X17*6 -> 7582.7705 | Z17: 2 | AA17: 3 | AB17: 205 | AC17: 3.5 | AD17: 787.5 | AE17: 5867 | AF17: 14000 | AG17: 3500 | AH17: 1094 | AI17: 2550 | AJ17: 3522 | AK17: =Y17+AD17+AE17+AF17+AG17+AH17+AI17+AJ17 -> 38903.27 | AL17: 17425 | AM17: 38150 | AN17: =AL17+AM17 -> 55575
B18: 12 PMI | C18: Fokker 100 | D18: SAF | E18: =7*52 -> 364 | F18: =E18/2 -> 182 | G18: =E18 -> 364 | H18: =_xlfn.XLOOKUP(B18,'[1]Baseline 2025'!$B:$B,'[1]Baseline 2025'!$C:$C) -> 1426 | I18: =E18*H18 -> 519064 | J18: =_xlfn.XLOOKUP(B18,'[1]Baseline 2025'!$B:$B,'[1]Baseline 2025'!$E:$E) -> Short Haul | K18: =_xlfn.XLOOKUP(B18,'[1]Baseline 2025'!$B:$B,'[1]Baseline 2025'!$I:$I)/100 -> 38099.298 | L18: =(K18*100)*43/120 -> 1365224.8 | M18: 3.97 | N18: =(L18*M18)/1000 -> 5419.9426 | O18: =9/1000 -> 0.009 | P18: =(O18*L18)/1000 -> 12.287023 | Q18: 0 | R18: =Q18*L18 -> 0 | S18: 100 | T18: =G18*S18*assumptions!$D$6 -> 30940 | U18: 10.9 | V18: 0.10069444 | W18: 5233.42 | X18: =W18*43/120 -> 1875.3088 | Y18: =X18*6 -> 11251.853 | Z18: 2 | AA18: 3 | AB18: 451 | AC18: 3.5 | AD18: 1089 | AE18: 6564 | AF18: 19360 | AG18: 4840 | AH18: 1513 | AI18: 2550 | AJ18: 4844 | AK18: =Y18+AD18+AE18+AF18+AG18+AH18+AI18+AJ18 -> 52011.853 | AL18: 38335 | AM18: 38150 | AN18: =AL18+AM18 -> 76485
B19: 13 VIE | C19: Fokker 100 | D19: SAF | E19: =7*52 -> 364 | F19: =E19/2 -> 182 | G19: =E19 -> 364 | H19: =_xlfn.XLOOKUP(B19,'[1]Baseline 2025'!$B:$B,'[1]Baseline 2025'!$C:$C) -> 962 | I19: =E19*H19 -> 350168 | J19: =_xlfn.XLOOKUP(B19,'[1]Baseline 2025'!$B:$B,'[1]Baseline 2025'!$E:$E) -> Short Haul | K19: =_xlfn.XLOOKUP(B19,'[1]Baseline 2025'!$B:$B,'[1]Baseline 2025'!$I:$I)/100 -> 25702.331 | L19: =(K19*100)*43/120 -> 921000.2 | M19: 3.97 | N19: =(L19*M19)/1000 -> 3656.3708 | O19: =9/1000 -> 0.009 | P19: =(O19*L19)/1000 -> 8.2890018 | Q19: 0 | R19: =Q19*L19 -> 0 | S19: 100 | T19: =G19*S19*assumptions!$D$6 -> 30940 | U19: 10.9 | V19: 0.072916667 | W19: 3530.54 | X19: =W19*43/120 -> 1265.1102 | Y19: =X19*6 -> 7590.661 | Z19: 2 | AA19: 3 | AB19: 205.5 | AC19: 3.5 | AD19: 787.5 | AE19: 5868 | AF19: 14000 | AG19: 3500 | AH19: 1094 | AI19: 2550 | AJ19: 3523 | AK19: =Y19+AD19+AE19+AF19+AG19+AH19+AI19+AJ19 -> 38913.161 | AL19: 17467.5 | AM19: 38150 | AN19: =AL19+AM19 -> 55617.5
B20: 14 WAW | C20: Fokker 100 | D20: SAF | E20: =7*52 -> 364 | F20: =E20/2 -> 182 | G20: =E20 -> 364 | H20: =_xlfn.XLOOKUP(B20,'[1]Baseline 2025'!$B:$B,'[1]Baseline 2025'!$C:$C) -> 1105 | I20: =E20*H20 -> 402220 | J20: =_xlfn.XLOOKUP(B20,'[1]Baseline 2025'!$B:$B,'[1]Baseline 2025'!$E:$E) -> Short Haul | K20: =_xlfn.XLOOKUP(B20,'[1]Baseline 2025'!$B:$B,'[1]Baseline 2025'!$I:$I)/100 -> 29522.948 | L20: =(K20*100)*43/120 -> 1057905.6 | M20: 3.97 | N20: =(L20*M20)/1000 -> 4199.8854 | O20: =9/1000 -> 0.009 | P20: =(O20*L20)/1000 -> 9.5211507 | Q20: 0 | R20: =Q20*L20 -> 0 | S20: 100 | T20: =G20*S20*assumptions!$D$6 -> 30940 | U20: 10.9 | V20: 0.079861111 | W20: 4055.35 | X20: =W20*43/120 -> 1453.1671 | Y20: =X20*6 -> 8719.0025 | Z20: 2 | AA20: 3 | AB20: 275 | AC20: 3.5 | AD20: 862.515 | AE20: 6083 | AF20: 15333.6 | AG20: 3833.4 | AH20: 1198 | AI20: 2550 | AJ20: 3899 | AK20: =Y20+AD20+AE20+AF20+AG20+AH20+AI20+AJ20 -> 42478.518 | AL20: 23375 | AM20: 38150 | AN20: =AL20+AM20 -> 61525
B21: 15 ZRH | C21: Fokker 100 | D21: SAF | E21: =14*52*2 -> 1456 | F21: =E21/2 -> 728 | G21: =E21 -> 1456 | H21: =_xlfn.XLOOKUP(B21,'[1]Baseline 2025'!$B:$B,'[1]Baseline 2025'!$C:$C) -> 603 | I21: =E21*H21 -> 877968 | J21: =_xlfn.XLOOKUP(B21,'[1]Baseline 2025'!$B:$B,'[1]Baseline 2025'!$E:$E) -> Short Haul | K21: =_xlfn.XLOOKUP(B21,'[1]Baseline 2025'!$B:$B,'[1]Baseline 2025'!$I:$I)/100 -> 32221.426 | L21: =(K21*100)*43/120 -> 1154601.1 | M21: 3.97 | N21: =(L21*M21)/1000 -> 4583.7663 | O21: =9/1000 -> 0.009 | P21: =(O21*L21)/1000 -> 10.39141 | Q21: 0 | R21: =Q21*L21 -> 0 | S21: 100 | T21: =G21*S21*assumptions!$D$6 -> 123760 | U21: 10.9 | V21: 0.059027778 | W21: 2213.01 | X21: =W21*43/120 -> 792.99525 | Y21: =X21*6 -> 4757.9715 | Z21: 2 | AA21: 3 | AB21: 75 | AC21: 3.5 | AD21: 637.515 | AE21: 5330 | AF21: 11333.6 | AG21: 2833.4 | AH21: 885 | AI21: 2550 | AJ21: 2647 | AK21: =Y21+AD21+AE21+AF21+AG21+AH21+AI21+AJ21 -> 30974.486 | AL21: 6375 | AM21: 38150 | AN21: =AL21+AM21 -> 44525
B22: 16 BKK | C22: B777-200er | D22: SAF | E22: =3*52*2 -> 312 | F22: =E22/2 -> 156 | G22: =E22 -> 312 | H22: =_xlfn.XLOOKUP(B22,'[1]Baseline 2025'!$B:$B,'[1]Baseline 2025'!$C:$C) -> 9217 | I22: =E22*H22 -> 2875704 | J22: =_xlfn.XLOOKUP(B22,'[1]Baseline 2025'!$B:$B,'[1]Baseline 2025'!$E:$E) -> Long Haul | K22: =_xlfn.XLOOKUP(B22,'[1]Baseline 2025'!$B:$B,'[1]Baseline 2025'!$I:$I)/100 -> 213377.24 | L22: =(K22*100)*43/120 -> 7646017.7 | M22: 3.97 | N22: =(L22*M22)/1000 -> 30354.69 | O22: =9/1000 -> 0.009 | P22: =(O22*L22)/1000 -> 68.814159 | Q22: 0 | R22: =Q22*L22 -> 0 | S22: 300 | T22: =G22*S22*assumptions!$D$6 -> 79560 | U22: 20 | V22: 0.46875 | W22: 68390.14 | X22: =W22*43/120 -> 24506.467 | Y22: =X22*6 -> 147038.8 | Z22: 3 | AA22: 12 | AB22: 2364 | AC22: 2.5 | AD22: 11812.5 | AE22: 27101 | AF22: 90000 | AG22: 22500 | AH22: 21094 | AI22: 7650 | AJ22: 42642 | AK22: =Y22+AD22+AE22+AF22+AG22+AH22+AI22+AJ22 -> 369838.3 | AL22: 602820 | AM22: 70000 | AN22: =AL22+AM22 -> 672820
